Workbook
Name Levered_Raw_Beta: 'Beta Regression'!$J$11
Name Market_Beta: 'Beta Regression'!$J$14
Name Market_Beta_Weight: 'Beta Regression'!$J$15
Name Raw_Beta_Weight: 'Beta Regression'!$J$12

Sheet Financials>

Sheet HistoricalFS
B2: HINDUSTAN UNILEVER LTD
B3: (NSE: HINDUNILVR | BSE: 500696 )
B4: INR 1927.0
B5: 52 Week - (High- 2667.2 & Low- 1926.2)
B8: ="Historical Financial Statements -"&'Data Sheet'!B1 -> Historical Financial Statements -HINDUSTAN UNILEVER LTD
B9: Year | C9: ='Data Sheet'!B16 -> 42825 | D9: ='Data Sheet'!C16 -> 43190 | E9: ='Data Sheet'!D16 -> 43555 | F9: ='Data Sheet'!E16 -> 43921 | G9: ='Data Sheet'!F16 -> 44286 | H9: ='Data Sheet'!G16 -> 44651 | I9: ='Data Sheet'!H16 -> 45016 | J9: ='Data Sheet'!I16 -> 45382 | ... L9: ='Data Sheet'!K16 -> 46112 | M9: LTM
A10: # | B10: Income Statement
B11: Sales | C11: =IFERROR('Data Sheet'!B17,0) -> 33162 | D11: =IFERROR('Data Sheet'!C17,0) -> 35545 | E11: =IFERROR('Data Sheet'!D17,0) -> 39310 | F11: =IFERROR('Data Sheet'!E17,0) -> 39783 | G11: =IFERROR('Data Sheet'!F17,0) -> 47028 | H11: =IFERROR('Data Sheet'!G17,0) -> 52446 | I11: =IFERROR('Data Sheet'!H17,0) -> 60580 | J11: =IFERROR('Data Sheet'!I17,0) -> 61896 | ... L11: =IFERROR('Data Sheet'!K17,0) -> 64468 | M11: =IFERROR(SUM('Data Sheet'!H42:K42),0) -> 66052
B12: Sales Growth | C12: - | D12: =D11/C11-1 -> 0.071859357 | E12: =E11/D11-1 -> 0.10592207 | F12: =F11/E11-1 -> 0.012032562 | G12: =G11/F11-1 -> 0.18211296 | H12: =H11/G11-1 -> 0.11520796 | I12: =I11/H11-1 -> 0.15509286 | J12: =J11/I11-1 -> 0.021723341 | K12: =K11/J11-1 -> -0.0091766835 | ... M12: =M11/L11-1 -> 0.024570329
B14: COGS | C14: =IFERROR(SUM('Data Sheet'!B18,'Data Sheet'!B20:B22)-1*'Data Sheet'!B19,0) -> 18675 | D14: =IFERROR(SUM('Data Sheet'!C18,'Data Sheet'!C20:C22)-1*'Data Sheet'!C19,0) -> 19314 | E14: =IFERROR(SUM('Data Sheet'!D18,'Data Sheet'!D20:D22)-1*'Data Sheet'!D19,0) -> 21081 | F14: =IFERROR(SUM('Data Sheet'!E18,'Data Sheet'!E20:E22)-1*'Data Sheet'!E19,0) -> 20614 | G14: =IFERROR(SUM('Data Sheet'!F18,'Data Sheet'!F20:F22)-1*'Data Sheet'!F19,0) -> 25301 | H14: =IFERROR(SUM('Data Sheet'!G18,'Data Sheet'!G20:G22)-1*'Data Sheet'!G19,0) -> 29066 | I14: =IFERROR(SUM('Data Sheet'!H18,'Data Sheet'!H20:H22)-1*'Data Sheet'!H19,0) -> 35381 | J14: =IFERROR(SUM('Data Sheet'!I18,'Data Sheet'!I20:I22)-1*'Data Sheet'!I19,0) -> 33651 | ... L14: =IFERROR(SUM('Data Sheet'!K18,'Data Sheet'!K20:K22)-1*'Data Sheet'!K19,0) -> 35634 | M14: =IFERROR(SUM('Data Sheet'!H43:K43),0) -> 50705
B15: COGS % Sales | C15: =C14/C11 -> 0.56314456 | D15: =D14/D11 -> 0.54336756 | E15: =E14/E11 -> 0.53627576 | F15: =F14/F11 -> 0.51816102 | G15: =G14/G11 -> 0.53799864 | H15: =H14/H11 -> 0.55420814 | I15: =I14/I11 -> 0.58403764 | J15: =J14/J11 -> 0.54367003 | ... M15: =M14/M11 -> 0.76765276
B17: Gross Profit | C17: =C11-C14 -> 14487 | D17: =D11-D14 -> 16231 | E17: =E11-E14 -> 18229 | F17: =F11-F14 -> 19169 | G17: =G11-G14 -> 21727 | H17: =H11-H14 -> 23380 | I17: =I11-I14 -> 25199 | J17: =J11-J14 -> 28245 | ... M17: =M11-M14 -> 15347
B18: Gross Margins | C18: =C17/C11 -> 0.43685544 | D18: =D17/D11 -> 0.45663244 | E18: =E17/E11 -> 0.46372424 | F18: =F17/F11 -> 0.48183898 | G18: =G17/G11 -> 0.46200136 | H18: =H17/H11 -> 0.44579186 | I18: =I17/I11 -> 0.41596236 | J18: =J17/J11 -> 0.45632997 | ... M18: =M17/M11 -> 0.23234724
B20: Selling & General Expenses | C20: =IFERROR(SUM('Data Sheet'!B23:B24),0) -> 8159 | D20: =IFERROR(SUM('Data Sheet'!C23:C24),0) -> 8732 | E20: =IFERROR(SUM('Data Sheet'!D23:D24),0) -> 9349 | F20: =IFERROR(SUM('Data Sheet'!E23:E24),0) -> 9308 | G20: =IFERROR(SUM('Data Sheet'!F23:F24),0) -> 10101 | H20: =IFERROR(SUM('Data Sheet'!G23:G24),0) -> 10523 | I20: =IFERROR(SUM('Data Sheet'!H23:H24),0) -> 11052 | J20: =IFERROR(SUM('Data Sheet'!I23:I24),0) -> 13586 | ... L20: =IFERROR(SUM('Data Sheet'!K23:K24),0) -> 13795
B21: SG&A Exp % Sales | C21: =C20/C11 -> 0.24603462 | D21: =D20/D11 -> 0.24566043 | E21: =E20/E11 -> 0.23782752 | F21: =F20/F11 -> 0.23396928 | G21: =G20/G11 -> 0.21478694 | H21: =H20/H11 -> 0.20064447 | I21: =I20/I11 -> 0.18243645 | J21: =J20/J11 -> 0.21949722 | ... M21: =M20/M11 -> 0
B23: EBITDA | C23: =C17-C20 -> 6328 | D23: =D17-D20 -> 7499 | E23: =E17-E20 -> 8880 | F23: =F17-F20 -> 9861 | G23: =G17-G20 -> 11626 | H23: =H17-H20 -> 12857 | I23: =I17-I20 -> 14147 | J23: =J17-J20 -> 14659 | ... L23: =L17-L20 -> 15039 | M23: =IFERROR(SUM('Data Sheet'!H51:K51),0) -> 20266
B24: EBITDA Margins | C24: =C23/C11 -> 0.19082082 | D24: =D23/D11 -> 0.21097201 | E24: =E23/E11 -> 0.22589672 | F24: =F23/F11 -> 0.24786969 | G24: =G23/G11 -> 0.24721443 | H24: =H23/H11 -> 0.24514739 | I24: =I23/I11 -> 0.23352592 | J24: =J23/J11 -> 0.23683275 | ... M24: =M23/M11 -> 0.30681887
B26: Interest | C26: =IFERROR('Data Sheet'!B27,0) -> 35 | D26: =IFERROR('Data Sheet'!C27,0) -> 26 | E26: =IFERROR('Data Sheet'!D27,0) -> 33 | F26: =IFERROR('Data Sheet'!E27,0) -> 118 | G26: =IFERROR('Data Sheet'!F27,0) -> 117 | H26: =IFERROR('Data Sheet'!G27,0) -> 106 | I26: =IFERROR('Data Sheet'!H27,0) -> 114 | J26: =IFERROR('Data Sheet'!I27,0) -> 334 | ... L26: =IFERROR('Data Sheet'!K27,0) -> 410 | M26: =IFERROR(SUM('Data Sheet'!H46:K46),0) -> 363
B27: Interest % Sales | C27: =C26/C11 -> 0.0010554249 | D27: =D26/D11 -> 0.00073146715 | E27: =E26/E11 -> 0.00083948105 | F27: =F26/F11 -> 0.002966091 | G27: =G26/G11 -> 0.0024878796 | H27: =H26/H11 -> 0.0020211265 | I27: =I26/I11 -> 0.0018818092 | J27: =J26/J11 -> 0.0053961484 | ... M27: =M26/M11 -> 0.0054956701
B29: Depriciation | C29: =IFERROR('Data Sheet'!B26,0) -> 432 | D29: =IFERROR('Data Sheet'!C26,0) -> 520 | E29: =IFERROR('Data Sheet'!D26,0) -> 565 | F29: =IFERROR('Data Sheet'!E26,0) -> 1002 | G29: =IFERROR('Data Sheet'!F26,0) -> 1074 | H29: =IFERROR('Data Sheet'!G26,0) -> 1091 | I29: =IFERROR('Data Sheet'!H26,0) -> 1137 | J29: =IFERROR('Data Sheet'!I26,0) -> 1216 | ... L29: =IFERROR('Data Sheet'!K26,0) -> 1333 | M29: =IFERROR(SUM('Data Sheet'!H45:K45),0) -> 1360
B30: Depreciation% Sales | C30: =C29/C11 -> 0.013026959 | D30: =D29/D11 -> 0.014629343 | E30: =E29/E11 -> 0.014372933 | F30: =F29/F11 -> 0.025186638 | G30: =G29/G11 -> 0.022837459 | H30: =H29/H11 -> 0.020802349 | I30: =I29/I11 -> 0.01876857 | J30: =J29/J11 -> 0.019645858 | ... M30: =M29/M11 -> 0.020589838
B32: Earning Before Tax | C32: =C23-SUM(C26,C29) -> 5861 | D32: =D23-SUM(D26,D29) -> 6953 | E32: =E23-SUM(E26,E29) -> 8282 | F32: =F23-SUM(F26,F29) -> 8741 | G32: =G23-SUM(G26,G29) -> 10435 | H32: =H23-SUM(H26,H29) -> 11660 | I32: =I23-SUM(I26,I29) -> 12896 | J32: =J23-SUM(J26,J29) -> 13109 | ... M32: =M23-SUM(M26,M29) -> 18543
B33: EBT% Sales | C33: =C32/C11 -> 0.17673844 | D33: =D32/D11 -> 0.1956112 | E33: =E32/E11 -> 0.2106843 | F33: =F32/F11 -> 0.21971696 | G33: =G32/G11 -> 0.22188909 | H33: =H32/H11 -> 0.22232391 | I33: =I32/I11 -> 0.21287554 | J33: =J32/J11 -> 0.21179075 | ... M33: =M32/M11 -> 0.28073336
B35: Tax | C35: =IFERROR('Data Sheet'!B29,0) -> 1977 | D35: =IFERROR('Data Sheet'!C29,0) -> 2079 | E35: =IFERROR('Data Sheet'!D29,0) -> 2544 | F35: =IFERROR('Data Sheet'!E29,0) -> 2409 | G35: =IFERROR('Data Sheet'!F29,0) -> 2606 | H35: =IFERROR('Data Sheet'!G29,0) -> 2987 | I35: =IFERROR('Data Sheet'!H29,0) -> 3201 | J35: =IFERROR('Data Sheet'!I29,0) -> 3644 | ... L35: =IFERROR('Data Sheet'!K29,0) -> 3160 | M35: =IFERROR(SUM('Data Sheet'!H48:K48),0) -> 3586
B36: Effective Tax Rtae | C36: =C35/C32 -> 0.33731445 | D36: =D35/D32 -> 0.29900762 | E36: =E35/E32 -> 0.30717218 | F36: =F35/F32 -> 0.27559776 | G36: =G35/G32 -> 0.24973646 | H36: =H35/H32 -> 0.25617496 | I36: =I35/I32 -> 0.2482165 | J36: =J35/J32 -> 0.27797696 | ... M36: =M35/M32 -> 0.19338834
B38: Net Profit | C38: =C32-C35 -> 3884 | D38: =D32-D35 -> 4874 | E38: =E32-E35 -> 5738 | F38: =F32-F35 -> 6332 | G38: =G32-G35 -> 7829 | H38: =H32-H35 -> 8673 | I38: =I32-I35 -> 9695 | J38: =J32-J35 -> 9465 | ... M38: =M32-M35 -> 14957
B39: Net Margins | C39: =C38/C11 -> 0.11712201 | D39: =D38/D11 -> 0.13712196 | E39: =E38/E11 -> 0.14596795 | F39: =F38/F11 -> 0.15916346 | G39: =G38/G11 -> 0.16647529 | H39: =H38/H11 -> 0.16537009 | I39: =I38/I11 -> 0.16003632 | J39: =J38/J11 -> 0.1529178 | ... M39: =M38/M11 -> 0.2264428
B41: No. of Equity Shares | C41: =IFERROR('Data Sheet'!B93,0) -> 216.43 | D41: =IFERROR('Data Sheet'!C93,0) -> 216.45 | E41: =IFERROR('Data Sheet'!D93,0) -> 216.47 | F41: =IFERROR('Data Sheet'!E93,0) -> 216.48 | G41: =IFERROR('Data Sheet'!F93,0) -> 234.96 | H41: =IFERROR('Data Sheet'!G93,0) -> 234.96 | I41: =IFERROR('Data Sheet'!H93,0) -> 234.96 | J41: =IFERROR('Data Sheet'!I93,0) -> 234.96 | ... M41: =IFERROR('Data Sheet'!L93,0) -> 0
B43: Earning Per Share | C43: =IFERROR(C38/C41,0) -> 17.945756 | D43: =IFERROR(D38/D41,0) -> 22.517903 | E43: =IFERROR(E38/E41,0) -> 26.507137 | F43: =IFERROR(F38/F41,0) -> 29.249815 | G43: =IFERROR(G38/G41,0) -> 33.320565 | H43: =IFERROR(H38/H41,0) -> 36.912666 | I43: =IFERROR(I38/I41,0) -> 41.262343 | J43: =IFERROR(J38/J41,0) -> 40.283453 | ... M43: =IFERROR(M38/M41,0) -> 0
B44: EPS Growth % | D44: =IFERROR(D43/C43-1,0) -> 0.25477591 | E44: =IFERROR(E43/D43-1,0) -> 0.17715836 | F44: =IFERROR(F43/E43-1,0) -> 0.10346941 | G44: =IFERROR(G43/F43-1,0) -> 0.13917182 | H44: =IFERROR(H43/G43-1,0) -> 0.10780432 | I44: =IFERROR(I43/H43-1,0) -> 0.11783697 | J44: =IFERROR(J43/I43-1,0) -> -0.023723569 | K44: =IFERROR(K43/J43-1,0) -> -0.015742208 | ... M44: =IFERROR(M43/L43-1,0) -> -1
B46: Dividend per Share | C46: =IFERROR('Data Sheet'!B31/HistoricalFS!C41,0) -> 16.966225 | D46: =IFERROR('Data Sheet'!C31/HistoricalFS!D41,0) -> 19.95842 | E46: =IFERROR('Data Sheet'!D31/HistoricalFS!E41,0) -> 21.952234 | F46: =IFERROR('Data Sheet'!E31/HistoricalFS!F41,0) -> 24.944568 | G46: =IFERROR('Data Sheet'!F31/HistoricalFS!G41,0) -> 40.506895 | H46: =IFERROR('Data Sheet'!G31/HistoricalFS!H41,0) -> 34.005788 | I46: =IFERROR('Data Sheet'!H31/HistoricalFS!I41,0) -> 39.006639 | J46: =IFERROR('Data Sheet'!I31/HistoricalFS!J41,0) -> 42.00715 | ... M46: =IFERROR('Data Sheet'!L31/HistoricalFS!M41,0) -> 0
B47: Dividend Payout Ratio | C47: =IFERROR(C46/C43,0) -> 0.9454171 | D47: =IFERROR(D46/D43,0) -> 0.88633566 | E47: =IFERROR(E46/E43,0) -> 0.82816312 | F47: =IFERROR(F46/F43,0) -> 0.85281112 | G47: =IFERROR(G46/G43,0) -> 1.2156725 | H47: =IFERROR(H46/H43,0) -> 0.92124986 | I47: =IFERROR(I46/I43,0) -> 0.94533265 | J47: =IFERROR(J46/J43,0) -> 1.0427892 | ... M47: =IFERROR(M46/M43,0) -> 0
B49: Retained Earnings | C49: =IFERROR(IF(C43>C46,1-C47,0),0) -> 0.054582904 | D49: =IFERROR(IF(D43>D46,1-D47,0),0) -> 0.11366434 | E49: =IFERROR(IF(E43>E46,1-E47,0),0) -> 0.17183688 | F49: =IFERROR(IF(F43>F46,1-F47,0),0) -> 0.14718888 | G49: =IFERROR(IF(G43>G46,1-G47,0),0) -> 0 | H49: =IFERROR(IF(H43>H46,1-H47,0),0) -> 0.078750144 | I49: =IFERROR(IF(I43>I46,1-I47,0),0) -> 0.054667354 | J49: =IFERROR(IF(J43>J46,1-J47,0),0) -> 0 | ... M49: =IFERROR(IF(M43>M46,1-M47,0),0) -> 0
A53: # | B53: Balance Sheet
B54: Equity Share Capital | C54: =IFERROR('Data Sheet'!B57,0) -> 216 | D54: =IFERROR('Data Sheet'!C57,0) -> 216 | E54: =IFERROR('Data Sheet'!D57,0) -> 216 | F54: =IFERROR('Data Sheet'!E57,0) -> 216 | G54: =IFERROR('Data Sheet'!F57,0) -> 235 | H54: =IFERROR('Data Sheet'!G57,0) -> 235 | I54: =IFERROR('Data Sheet'!H57,0) -> 235 | J54: =IFERROR('Data Sheet'!I57,0) -> 235 | ... L54: =IFERROR('Data Sheet'!K57,0) -> 235
B55: Reserves | C55: =IFERROR('Data Sheet'!B58,0) -> 6528 | D55: =IFERROR('Data Sheet'!C58,0) -> 7065 | E55: =IFERROR('Data Sheet'!D58,0) -> 7651 | F55: =IFERROR('Data Sheet'!E58,0) -> 8013 | G55: =IFERROR('Data Sheet'!F58,0) -> 47439 | H55: =IFERROR('Data Sheet'!G58,0) -> 48826 | I55: =IFERROR('Data Sheet'!H58,0) -> 50069 | J55: =IFERROR('Data Sheet'!I58,0) -> 50983 | ... L55: =IFERROR('Data Sheet'!K58,0) -> 48504
B56: Borrowings | C56: =IFERROR('Data Sheet'!B59,0) -> 277 | D56: =IFERROR('Data Sheet'!C59,0) -> 0 | E56: =IFERROR('Data Sheet'!D59,0) -> 99 | F56: =IFERROR('Data Sheet'!E59,0) -> 0 | G56: =IFERROR('Data Sheet'!F59,0) -> 0 | H56: =IFERROR('Data Sheet'!G59,0) -> 1043 | I56: =IFERROR('Data Sheet'!H59,0) -> 1219 | J56: =IFERROR('Data Sheet'!I59,0) -> 1484 | ... L56: =IFERROR('Data Sheet'!K59,0) -> 1478
B57: Other Liabilities | C57: =IFERROR('Data Sheet'!B60,0) -> 8685 | D57: =IFERROR('Data Sheet'!C60,0) -> 10581 | E57: =IFERROR('Data Sheet'!D60,0) -> 10663 | F57: =IFERROR('Data Sheet'!E60,0) -> 11924 | G57: =IFERROR('Data Sheet'!F60,0) -> 21066 | H57: =IFERROR('Data Sheet'!G60,0) -> 20402 | I57: =IFERROR('Data Sheet'!H60,0) -> 21554 | J57: =IFERROR('Data Sheet'!I60,0) -> 25787 | ... L57: =IFERROR('Data Sheet'!K60,0) -> 29521
B58: Total Liabilities | C58: =IFERROR(SUM(C54:C57),0) -> 15706 | D58: =IFERROR(SUM(D54:D57),0) -> 17862 | E58: =IFERROR(SUM(E54:E57),0) -> 18629 | F58: =IFERROR(SUM(F54:F57),0) -> 20153 | G58: =IFERROR(SUM(G54:G57),0) -> 68740 | H58: =IFERROR(SUM(H54:H57),0) -> 70506 | I58: =IFERROR(SUM(I54:I57),0) -> 73077 | J58: =IFERROR(SUM(J54:J57),0) -> 78489 | ... L58: =IFERROR(SUM(L54:L57),0) -> 79738
B60: Fixed Asset Net Block | C60: =IFERROR('Data Sheet'!B62,0) -> 4419 | D60: =IFERROR('Data Sheet'!C62,0) -> 4528 | E60: =IFERROR('Data Sheet'!D62,0) -> 4715 | F60: =IFERROR('Data Sheet'!E62,0) -> 5479 | G60: =IFERROR('Data Sheet'!F62,0) -> 51443 | H60: =IFERROR('Data Sheet'!G62,0) -> 51473 | I60: =IFERROR('Data Sheet'!H62,0) -> 52678 | J60: =IFERROR('Data Sheet'!I62,0) -> 53744 | ... L60: =IFERROR('Data Sheet'!K62,0) -> 57428
B61: Capital Work in Progress | C61: =IFERROR('Data Sheet'!B63,0) -> 229 | D61: =IFERROR('Data Sheet'!C63,0) -> 461 | E61: =IFERROR('Data Sheet'!D63,0) -> 406 | F61: =IFERROR('Data Sheet'!E63,0) -> 597 | G61: =IFERROR('Data Sheet'!F63,0) -> 745 | H61: =IFERROR('Data Sheet'!G63,0) -> 1313 | I61: =IFERROR('Data Sheet'!H63,0) -> 1132 | J61: =IFERROR('Data Sheet'!I63,0) -> 1025 | ... L61: =IFERROR('Data Sheet'!K63,0) -> 880
B62: Investments | C62: =IFERROR('Data Sheet'!B64,0) -> 3794 | D62: =IFERROR('Data Sheet'!C64,0) -> 2873 | E62: =IFERROR('Data Sheet'!D64,0) -> 2716 | F62: =IFERROR('Data Sheet'!E64,0) -> 1255 | G62: =IFERROR('Data Sheet'!F64,0) -> 2709 | H62: =IFERROR('Data Sheet'!G64,0) -> 3521 | I62: =IFERROR('Data Sheet'!H64,0) -> 2882 | J62: =IFERROR('Data Sheet'!I64,0) -> 4625 | ... L62: =IFERROR('Data Sheet'!K64,0) -> 4359
B63: Other Assets | C63: =IFERROR('Data Sheet'!B65-SUM('Data Sheet'!B67:B69),0) -> 1810 | D63: =IFERROR('Data Sheet'!C65-SUM('Data Sheet'!C67:C69),0) -> 2692 | E63: =IFERROR('Data Sheet'!D65-SUM('Data Sheet'!D67:D69),0) -> 2645 | F63: =IFERROR('Data Sheet'!E65-SUM('Data Sheet'!E67:E69),0) -> 3793 | G63: =IFERROR('Data Sheet'!F65-SUM('Data Sheet'!F67:F69),0) -> 4035 | H63: =IFERROR('Data Sheet'!G65-SUM('Data Sheet'!G67:G69),0) -> 4021 | I63: =IFERROR('Data Sheet'!H65-SUM('Data Sheet'!H67:H69),0) -> 4377 | J63: =IFERROR('Data Sheet'!I65-SUM('Data Sheet'!I67:I69),0) -> 4517 | ... L63: =IFERROR('Data Sheet'!K65-SUM('Data Sheet'!K67:K69),0) -> 5655
B64: Total Non Current Asset | C64: =IFERROR(SUM(C60:C63),0) -> 10252 | D64: =IFERROR(SUM(D60:D63),0) -> 10554 | E64: =IFERROR(SUM(E60:E63),0) -> 10482 | F64: =IFERROR(SUM(F60:F63),0) -> 11124 | G64: =IFERROR(SUM(G60:G63),0) -> 58932 | H64: =IFERROR(SUM(H60:H63),0) -> 60328 | I64: =IFERROR(SUM(I60:I63),0) -> 61069 | J64: =IFERROR(SUM(J60:J63),0) -> 63911 | ... L64: =IFERROR(SUM(L60:L63),0) -> 68322
B66: Receivables | C66: =IFERROR('Data Sheet'!B67,0) -> 1085 | D66: =IFERROR('Data Sheet'!C67,0) -> 1310 | E66: =IFERROR('Data Sheet'!D67,0) -> 1816 | F66: =IFERROR('Data Sheet'!E67,0) -> 1149 | G66: =IFERROR('Data Sheet'!F67,0) -> 1758 | H66: =IFERROR('Data Sheet'!G67,0) -> 2236 | I66: =IFERROR('Data Sheet'!H67,0) -> 3079 | J66: =IFERROR('Data Sheet'!I67,0) -> 2997 | ... L66: =IFERROR('Data Sheet'!K67,0) -> 3379
B67: Inventory | C67: =IFERROR('Data Sheet'!B68,0) -> 2541 | D67: =IFERROR('Data Sheet'!C68,0) -> 2513 | E67: =IFERROR('Data Sheet'!D68,0) -> 2574 | F67: =IFERROR('Data Sheet'!E68,0) -> 2767 | G67: =IFERROR('Data Sheet'!F68,0) -> 3579 | H67: =IFERROR('Data Sheet'!G68,0) -> 4096 | I67: =IFERROR('Data Sheet'!H68,0) -> 4251 | J67: =IFERROR('Data Sheet'!I68,0) -> 4022 | ... L67: =IFERROR('Data Sheet'!K68,0) -> 4789
B68: Cash & Bank | C68: =IFERROR('Data Sheet'!B69,0) -> 1828 | D68: =IFERROR('Data Sheet'!C69,0) -> 3485 | E68: =IFERROR('Data Sheet'!D69,0) -> 3757 | F68: =IFERROR('Data Sheet'!E69,0) -> 5113 | G68: =IFERROR('Data Sheet'!F69,0) -> 4471 | H68: =IFERROR('Data Sheet'!G69,0) -> 3846 | I68: =IFERROR('Data Sheet'!H69,0) -> 4678 | J68: =IFERROR('Data Sheet'!I69,0) -> 7559 | ... L68: =IFERROR('Data Sheet'!K69,0) -> 3248
B69: Total Current Asset | C69: =IFERROR(SUM(C66:C68),0) -> 5454 | D69: =IFERROR(SUM(D66:D68),0) -> 7308 | E69: =IFERROR(SUM(E66:E68),0) -> 8147 | F69: =IFERROR(SUM(F66:F68),0) -> 9029 | G69: =IFERROR(SUM(G66:G68),0) -> 9808 | H69: =IFERROR(SUM(H66:H68),0) -> 10178 | I69: =IFERROR(SUM(I66:I68),0) -> 12008 | J69: =IFERROR(SUM(J66:J68),0) -> 14578 | ... L69: =IFERROR(SUM(L66:L68),0) -> 11416
B71: Total Asset | C71: =IFERROR(SUM(C69,C64),0) -> 15706 | D71: =IFERROR(SUM(D69,D64),0) -> 17862 | E71: =IFERROR(SUM(E69,E64),0) -> 18629 | F71: =IFERROR(SUM(F69,F64),0) -> 20153 | G71: =IFERROR(SUM(G69,G64),0) -> 68740 | H71: =IFERROR(SUM(H69,H64),0) -> 70506 | I71: =IFERROR(SUM(I69,I64),0) -> 73077 | J71: =IFERROR(SUM(J69,J64),0) -> 78489 | ... L71: =IFERROR(SUM(L69,L64),0) -> 79738
B73: Check | C73: =C71=C58 -> TRUE | D73: =D71=D58 -> TRUE | E73: =E71=E58 -> TRUE | F73: =F71=F58 -> TRUE | G73: =G71=G58 -> TRUE | H73: =H71=H58 -> TRUE | I73: =I71=I58 -> TRUE | J73: =J71=J58 -> TRUE | ... L73: =L71=L58 -> TRUE
A77: # | B77: Cash Flow Statement
B78: Operations Acitivities
B79: Profit from operations | C79: =IFERROR('Cash Flow Data '!E4,0) -> 6512 | D79: =IFERROR('Cash Flow Data '!F4,0) -> 7485 | E79: =IFERROR('Cash Flow Data '!G4,0) -> 8909 | F79: =IFERROR('Cash Flow Data '!H4,0) -> 9723 | G79: =IFERROR('Cash Flow Data '!I4,0) -> 11672 | H79: =IFERROR('Cash Flow Data '!J4,0) -> 12829 | I79: =IFERROR('Cash Flow Data '!K4,0) -> 14089 | J79: =IFERROR('Cash Flow Data '!L4,0) -> 14537 | ... L79: =IFERROR('Cash Flow Data '!N4,0) -> 15153
B80: Receivables | C80: =IFERROR('Cash Flow Data '!E5,0) -> 173 | D80: =IFERROR('Cash Flow Data '!F5,0) -> 0 | E80: =IFERROR('Cash Flow Data '!G5,0) -> 0 | F80: =IFERROR('Cash Flow Data '!H5,0) -> 0 | G80: =IFERROR('Cash Flow Data '!I5,0) -> 0 | H80: =IFERROR('Cash Flow Data '!J5,0) -> 0 | I80: =IFERROR('Cash Flow Data '!K5,0) -> 0 | J80: =IFERROR('Cash Flow Data '!L5,0) -> 0 | ... L80: =IFERROR('Cash Flow Data '!N5,0) -> 0
B81: Inventory | C81: =IFERROR('Cash Flow Data '!E6,0) -> 37 | D81: =IFERROR('Cash Flow Data '!F6,0) -> -146 | E81: =IFERROR('Cash Flow Data '!G6,0) -> -195 | F81: =IFERROR('Cash Flow Data '!H6,0) -> -331 | G81: =IFERROR('Cash Flow Data '!I6,0) -> -543 | H81: =IFERROR('Cash Flow Data '!J6,0) -> -758 | I81: =IFERROR('Cash Flow Data '!K6,0) -> -339 | J81: =IFERROR('Cash Flow Data '!L6,0) -> 74 | ... L81: =IFERROR('Cash Flow Data '!N6,0) -> -692
B82: Payables | C82: =IFERROR('Cash Flow Data '!E7,0) -> 501 | D82: =IFERROR('Cash Flow Data '!F7,0) -> 0 | E82: =IFERROR('Cash Flow Data '!G7,0) -> 0 | F82: =IFERROR('Cash Flow Data '!H7,0) -> 0 | G82: =IFERROR('Cash Flow Data '!I7,0) -> 0 | H82: =IFERROR('Cash Flow Data '!J7,0) -> 0 | I82: =IFERROR('Cash Flow Data '!K7,0) -> 0 | J82: =IFERROR('Cash Flow Data '!L7,0) -> 0 | ... L82: =IFERROR('Cash Flow Data '!N7,0) -> 0
B83: Loans Advances | C83: =IFERROR('Cash Flow Data '!E8,0) -> 0 | D83: =IFERROR('Cash Flow Data '!F8,0) -> 0 | E83: =IFERROR('Cash Flow Data '!G8,0) -> 0 | F83: =IFERROR('Cash Flow Data '!H8,0) -> 0 | G83: =IFERROR('Cash Flow Data '!I8,0) -> 0 | H83: =IFERROR('Cash Flow Data '!J8,0) -> 0 | I83: =IFERROR('Cash Flow Data '!K8,0) -> 0 | J83: =IFERROR('Cash Flow Data '!L8,0) -> 0 | ... L83: =IFERROR('Cash Flow Data '!N8,0) -> 0
B84: Operating Deposits | C84: =IFERROR('Cash Flow Data '!E9,0) -> -46 | D84: =IFERROR('Cash Flow Data '!F9,0) -> 0 | E84: =IFERROR('Cash Flow Data '!G9,0) -> 0 | F84: =IFERROR('Cash Flow Data '!H9,0) -> 0 | G84: =IFERROR('Cash Flow Data '!I9,0) -> 0 | H84: =IFERROR('Cash Flow Data '!J9,0) -> 0 | I84: =IFERROR('Cash Flow Data '!K9,0) -> 0 | J84: =IFERROR('Cash Flow Data '!L9,0) -> 0 | ... L84: =IFERROR('Cash Flow Data '!N9,0) -> 0
B85: Other WC items | C85: =IFERROR('Cash Flow Data '!E10,0) -> -99 | D85: =IFERROR('Cash Flow Data '!F10,0) -> 982 | E85: =IFERROR('Cash Flow Data '!G10,0) -> -147 | F85: =IFERROR('Cash Flow Data '!H10,0) -> 742 | G85: =IFERROR('Cash Flow Data '!I10,0) -> 442 | H85: =IFERROR('Cash Flow Data '!J10,0) -> -242 | I85: =IFERROR('Cash Flow Data '!K10,0) -> -621 | J85: =IFERROR('Cash Flow Data '!L10,0) -> 1239 | ... L85: =IFERROR('Cash Flow Data '!N10,0) -> 1378
B86: Working capital changes | C86: =IFERROR('Cash Flow Data '!E11,0) -> 566 | D86: =IFERROR('Cash Flow Data '!F11,0) -> 836 | E86: =IFERROR('Cash Flow Data '!G11,0) -> -342 | F86: =IFERROR('Cash Flow Data '!H11,0) -> 411 | G86: =IFERROR('Cash Flow Data '!I11,0) -> -101 | H86: =IFERROR('Cash Flow Data '!J11,0) -> -1000 | I86: =IFERROR('Cash Flow Data '!K11,0) -> -960 | J86: =IFERROR('Cash Flow Data '!L11,0) -> 1313 | ... L86: =IFERROR('Cash Flow Data '!N11,0) -> 686
B87: Direct taxes | C87: =IFERROR('Cash Flow Data '!E12,0) -> -1859 | D87: =IFERROR('Cash Flow Data '!F12,0) -> -2264 | E87: =IFERROR('Cash Flow Data '!G12,0) -> -2767 | F87: =IFERROR('Cash Flow Data '!H12,0) -> -2505 | G87: =IFERROR('Cash Flow Data '!I12,0) -> -2407 | H87: =IFERROR('Cash Flow Data '!J12,0) -> -2784 | I87: =IFERROR('Cash Flow Data '!K12,0) -> -3138 | J87: =IFERROR('Cash Flow Data '!L12,0) -> -381 | ... L87: =IFERROR('Cash Flow Data '!N12,0) -> -4840
B88: Other operating items | C88: =IFERROR('Cash Flow Data '!E13,0) -> -21 | D88: =IFERROR('Cash Flow Data '!F13,0) -> 0 | E88: =IFERROR('Cash Flow Data '!G13,0) -> 0 | F88: =IFERROR('Cash Flow Data '!H13,0) -> 0 | G88: =IFERROR('Cash Flow Data '!I13,0) -> 0 | H88: =IFERROR('Cash Flow Data '!J13,0) -> 0 | I88: =IFERROR('Cash Flow Data '!K13,0) -> 0 | J88: =IFERROR('Cash Flow Data '!L13,0) -> 0 | ... L88: =IFERROR('Cash Flow Data '!N13,0) -> 0
B89: Exceptional CF items | C89: =IFERROR('Cash Flow Data '!E14,0) -> -13 | D89: =IFERROR('Cash Flow Data '!F14,0) -> 2 | E89: =IFERROR('Cash Flow Data '!G14,0) -> 0 | F89: =IFERROR('Cash Flow Data '!H14,0) -> -6 | G89: =IFERROR('Cash Flow Data '!I14,0) -> -1 | H89: =IFERROR('Cash Flow Data '!J14,0) -> 3 | I89: =IFERROR('Cash Flow Data '!K14,0) -> 0 | J89: =IFERROR('Cash Flow Data '!L14,0) -> 0 | ... L89: =IFERROR('Cash Flow Data '!N14,0) -> 0
B90: Cash Flow from Operations | C90: =SUM(C79:C89) -> 5751 | D90: =SUM(D79:D87) -> 6893 | E90: =SUM(E79:E87) -> 5458 | F90: =SUM(F79:F87) -> 8040 | G90: =SUM(G79:G87) -> 9063 | H90: =SUM(H79:H87) -> 8045 | I90: =SUM(I79:I87) -> 9031 | J90: =SUM(J79:J87) -> 16782 | K90: =SUM(K79:K87) -> 11098 | L90: =SUM(L79:L87) -> 11685
B92: Investing Activities
B93: Fixed assets purchased | C93: =IFERROR('Cash Flow Data '!E16,0) -> -1113 | D93: =IFERROR('Cash Flow Data '!F16,0) -> -895 | E93: =IFERROR('Cash Flow Data '!G16,0) -> -767 | F93: =IFERROR('Cash Flow Data '!H16,0) -> -862 | G93: =IFERROR('Cash Flow Data '!I16,0) -> -4163 | H93: =IFERROR('Cash Flow Data '!J16,0) -> -1228 | I93: =IFERROR('Cash Flow Data '!K16,0) -> -1192 | J93: =IFERROR('Cash Flow Data '!L16,0) -> -1477 | ... L93: =IFERROR('Cash Flow Data '!N16,0) -> -1361
B94: Fixed assets sold | C94: =IFERROR('Cash Flow Data '!E17,0) -> 176 | D94: =IFERROR('Cash Flow Data '!F17,0) -> 32 | E94: =IFERROR('Cash Flow Data '!G17,0) -> 13 | F94: =IFERROR('Cash Flow Data '!H17,0) -> 52 | G94: =IFERROR('Cash Flow Data '!I17,0) -> 97 | H94: =IFERROR('Cash Flow Data '!J17,0) -> 175 | I94: =IFERROR('Cash Flow Data '!K17,0) -> 181 | J94: =IFERROR('Cash Flow Data '!L17,0) -> 20 | ... L94: =IFERROR('Cash Flow Data '!N17,0) -> 29
B95: Investments purchased | C95: =IFERROR('Cash Flow Data '!E18,0) -> -31214 | D95: =IFERROR('Cash Flow Data '!F18,0) -> -51855 | E95: =IFERROR('Cash Flow Data '!G18,0) -> -74365 | F95: =IFERROR('Cash Flow Data '!H18,0) -> -36090 | G95: =IFERROR('Cash Flow Data '!I18,0) -> -39920 | H95: =IFERROR('Cash Flow Data '!J18,0) -> -48522 | I95: =IFERROR('Cash Flow Data '!K18,0) -> -22649 | J95: =IFERROR('Cash Flow Data '!L18,0) -> -21337 | ... L95: =IFERROR('Cash Flow Data '!N18,0) -> -25529
B96: Investments sold | C96: =IFERROR('Cash Flow Data '!E19,0) -> 30083 | D96: =IFERROR('Cash Flow Data '!F19,0) -> 52897 | E96: =IFERROR('Cash Flow Data '!G19,0) -> 74691 | F96: =IFERROR('Cash Flow Data '!H19,0) -> 37690 | G96: =IFERROR('Cash Flow Data '!I19,0) -> 38486 | H96: =IFERROR('Cash Flow Data '!J19,0) -> 47786 | I96: =IFERROR('Cash Flow Data '!K19,0) -> 23462 | J96: =IFERROR('Cash Flow Data '!L19,0) -> 19846 | ... L96: =IFERROR('Cash Flow Data '!N19,0) -> 25117
B97: Interest received | C97: =IFERROR('Cash Flow Data '!E20,0) -> 264 | D97: =IFERROR('Cash Flow Data '!F20,0) -> 297 | E97: =IFERROR('Cash Flow Data '!G20,0) -> 289 | F97: =IFERROR('Cash Flow Data '!H20,0) -> 351 | G97: =IFERROR('Cash Flow Data '!I20,0) -> 277 | H97: =IFERROR('Cash Flow Data '!J20,0) -> 161 | I97: =IFERROR('Cash Flow Data '!K20,0) -> 259 | J97: =IFERROR('Cash Flow Data '!L20,0) -> 425 | ... L97: =IFERROR('Cash Flow Data '!N20,0) -> 428
B98: Dividends received | C98: =IFERROR('Cash Flow Data '!E21,0) -> 14 | D98: =IFERROR('Cash Flow Data '!F21,0) -> 0 | E98: =IFERROR('Cash Flow Data '!G21,0) -> 1 | F98: =IFERROR('Cash Flow Data '!H21,0) -> 1 | G98: =IFERROR('Cash Flow Data '!I21,0) -> 1 | H98: =IFERROR('Cash Flow Data '!J21,0) -> 1 | I98: =IFERROR('Cash Flow Data '!K21,0) -> 2 | J98: =IFERROR('Cash Flow Data '!L21,0) -> 3 | ... L98: =IFERROR('Cash Flow Data '!N21,0) -> 5
B99: Redemp n Canc of Shares | C99: =IFERROR('Cash Flow Data '!E22,0) -> 20 | D99: =IFERROR('Cash Flow Data '!F22,0) -> 73 | E99: =IFERROR('Cash Flow Data '!G22,0) -> 0 | F99: =IFERROR('Cash Flow Data '!H22,0) -> 0 | G99: =IFERROR('Cash Flow Data '!I22,0) -> 0 | H99: =IFERROR('Cash Flow Data '!J22,0) -> 0 | I99: =IFERROR('Cash Flow Data '!K22,0) -> 0 | J99: =IFERROR('Cash Flow Data '!L22,0) -> 0 | ... L99: =IFERROR('Cash Flow Data '!N22,0) -> 298
B100: Acquisition of companies | C100: =IFERROR('Cash Flow Data '!E23,0) -> 0 | D100: =IFERROR('Cash Flow Data '!F23,0) -> 0 | E100: =IFERROR('Cash Flow Data '!G23,0) -> 0 | F100: =IFERROR('Cash Flow Data '!H23,0) -> 0 | G100: =IFERROR('Cash Flow Data '!I23,0) -> 0 | H100: =IFERROR('Cash Flow Data '!J23,0) -> 0 | I100: =IFERROR('Cash Flow Data '!K23,0) -> -334 | J100: =IFERROR('Cash Flow Data '!L23,0) -> 0 | ... L100: =IFERROR('Cash Flow Data '!N23,0) -> 0
B101: Other investing items | C101: =IFERROR('Cash Flow Data '!E24,0) -> 597 | D101: =IFERROR('Cash Flow Data '!F24,0) -> -1612 | E101: =IFERROR('Cash Flow Data '!G24,0) -> -300 | F101: =IFERROR('Cash Flow Data '!H24,0) -> 649 | G101: =IFERROR('Cash Flow Data '!I24,0) -> 3994 | H101: =IFERROR('Cash Flow Data '!J24,0) -> -101 | I101: =IFERROR('Cash Flow Data '!K24,0) -> -1213 | J101: =IFERROR('Cash Flow Data '!L24,0) -> -2804 | ... L101: =IFERROR('Cash Flow Data '!N24,0) -> -2663
B102: Cash Flow from Investing | C102: =SUM(C93:C101) -> -1173 | D102: =SUM(D93:D101) -> -1063 | E102: =SUM(E93:E101) -> -438 | F102: =SUM(F93:F101) -> 1791 | G102: =SUM(G93:G101) -> -1228 | H102: =SUM(H93:H101) -> -1728 | I102: =SUM(I93:I101) -> -1484 | J102: =SUM(J93:J101) -> -5324 | ... L102: =SUM(L93:L101) -> -3676
B104: Financing Activities
B105: Proceeds from shares | C105: =IFERROR('Cash Flow Data '!E26,0) -> 0 | D105: =IFERROR('Cash Flow Data '!F26,0) -> 0 | E105: =IFERROR('Cash Flow Data '!G26,0) -> 0 | F105: =IFERROR('Cash Flow Data '!H26,0) -> 0 | G105: =IFERROR('Cash Flow Data '!I26,0) -> 0 | H105: =IFERROR('Cash Flow Data '!J26,0) -> 0 | I105: =IFERROR('Cash Flow Data '!K26,0) -> 0 | J105: =IFERROR('Cash Flow Data '!L26,0) -> 0 | ... L105: =IFERROR('Cash Flow Data '!N26,0) -> 0
B106: Proceeds from borrowings | C106: =IFERROR('Cash Flow Data '!E27,0) -> 460 | D106: =IFERROR('Cash Flow Data '!F27,0) -> 0 | E106: =IFERROR('Cash Flow Data '!G27,0) -> 99 | F106: =IFERROR('Cash Flow Data '!H27,0) -> 0 | G106: =IFERROR('Cash Flow Data '!I27,0) -> 188 | H106: =IFERROR('Cash Flow Data '!J27,0) -> 55 | I106: =IFERROR('Cash Flow Data '!K27,0) -> 286 | J106: =IFERROR('Cash Flow Data '!L27,0) -> 0 | ... L106: =IFERROR('Cash Flow Data '!N27,0) -> 0
B107: Repayment of borrowings | C107: =IFERROR('Cash Flow Data '!E28,0) -> -360 | D107: =IFERROR('Cash Flow Data '!F28,0) -> -277 | E107: =IFERROR('Cash Flow Data '!G28,0) -> 0 | F107: =IFERROR('Cash Flow Data '!H28,0) -> -99 | G107: =IFERROR('Cash Flow Data '!I28,0) -> -188 | H107: =IFERROR('Cash Flow Data '!J28,0) -> -55 | I107: =IFERROR('Cash Flow Data '!K28,0) -> -208 | J107: =IFERROR('Cash Flow Data '!L28,0) -> -85 | ... L107: =IFERROR('Cash Flow Data '!N28,0) -> -46
B108: Interest paid fin | C108: =IFERROR('Cash Flow Data '!E29,0) -> -14 | D108: =IFERROR('Cash Flow Data '!F29,0) -> -6 | E108: =IFERROR('Cash Flow Data '!G29,0) -> -7 | F108: =IFERROR('Cash Flow Data '!H29,0) -> -90 | G108: =IFERROR('Cash Flow Data '!I29,0) -> -92 | H108: =IFERROR('Cash Flow Data '!J29,0) -> -82 | I108: =IFERROR('Cash Flow Data '!K29,0) -> -88 | J108: =IFERROR('Cash Flow Data '!L29,0) -> -110 | ... L108: =IFERROR('Cash Flow Data '!N29,0) -> -133
B109: Dividends paid | C109: =IFERROR('Cash Flow Data '!E30,0) -> -3572 | D109: =IFERROR('Cash Flow Data '!F30,0) -> -3911 | E109: =IFERROR('Cash Flow Data '!G30,0) -> -4554 | F109: =IFERROR('Cash Flow Data '!H30,0) -> -5196 | G109: =IFERROR('Cash Flow Data '!I30,0) -> -8811 | H109: =IFERROR('Cash Flow Data '!J30,0) -> -7526 | I109: =IFERROR('Cash Flow Data '!K30,0) -> -8474 | J109: =IFERROR('Cash Flow Data '!L30,0) -> -9416 | ... L109: =IFERROR('Cash Flow Data '!N30,0) -> -10124
B110: Financial liabilities | C110: =IFERROR('Cash Flow Data '!E31,0) -> 0 | D110: =IFERROR('Cash Flow Data '!F31,0) -> 0 | E110: =IFERROR('Cash Flow Data '!G31,0) -> 0 | F110: =IFERROR('Cash Flow Data '!H31,0) -> -373 | G110: =IFERROR('Cash Flow Data '!I31,0) -> -406 | H110: =IFERROR('Cash Flow Data '!J31,0) -> -407 | I110: =IFERROR('Cash Flow Data '!K31,0) -> -467 | J110: =IFERROR('Cash Flow Data '!L31,0) -> -423 | ... L110: =IFERROR('Cash Flow Data '!N31,0) -> -507
B111: Other financing items | C111: =IFERROR('Cash Flow Data '!E32,0) -> -728 | D111: =IFERROR('Cash Flow Data '!F32,0) -> -781 | E111: =IFERROR('Cash Flow Data '!G32,0) -> -928 | F111: =IFERROR('Cash Flow Data '!H32,0) -> -1061 | G111: =IFERROR('Cash Flow Data '!I32,0) -> 0 | H111: =IFERROR('Cash Flow Data '!J32,0) -> 0 | I111: =IFERROR('Cash Flow Data '!K32,0) -> -2 | J111: =IFERROR('Cash Flow Data '!L32,0) -> 0 | ... L111: =IFERROR('Cash Flow Data '!N32,0) -> 0
B112: Cash Flow from Financing | C112: =SUM(C105:C111) -> -4214 | D112: =SUM(D105:D111) -> -4975 | E112: =SUM(E105:E111) -> -5390 | F112: =SUM(F105:F111) -> -6819 | G112: =SUM(G105:G111) -> -9309 | H112: =SUM(H105:H111) -> -8015 | I112: =SUM(I105:I111) -> -8953 | J112: =SUM(J105:J111) -> -10034 | ... L112: =SUM(L105:L111) -> -10810
B114: Net Cash Flow | C114: =IFERROR(C90+C102+C112,0) -> 364 | D114: =IFERROR(D90+D102+D112,0) -> 855 | E114: =IFERROR(E90+E102+E112,0) -> -370 | F114: =IFERROR(F90+F102+F112,0) -> 3012 | G114: =IFERROR(G90+G102+G112,0) -> -1474 | H114: =IFERROR(H90+H102+H112,0) -> -1698 | I114: =IFERROR(I90+I102+I112,0) -> -1406 | J114: =IFERROR(J90+J102+J112,0) -> 1424 | ... L114: =IFERROR(L90+L102+L112,0) -> -2801

Sheet Forecasting
B2: HINDUSTAN UNILEVER LTD
B3: (NSE: HINDUNILVR | BSE: 500696 )
B4: INR 1927.0
B5: 52 Week - (High- 2667.2 & Low- 1926.2)
B7: ='Data Sheet'!B1&" -"&'Data Sheet'!A17&" Forecasting" -> HINDUSTAN UNILEVER LTD -Sales Forecasting | G7: ='Data Sheet'!B1&" -"&HistoricalFS!B23&" Forecasting" -> HINDUSTAN UNILEVER LTD -EBITDA Forecasting | L7: ='Data Sheet'!B1&" -"&HistoricalFS!B43&" Forecasting" -> HINDUSTAN UNILEVER LTD -Earning Per Share Forecasting
B8: Year Weight | C8: Year | D8: Sales | E8: Sales Growth | G8: Year Weight | H8: Year | I8: Sales | J8: Sales Growth | L8: Year Weight | M8: Year | N8: Sales | O8: Sales Growth
B9: 1 | C9: ='Data Sheet'!B16 -> 42825 | D9: {=TRANSPOSE('Data Sheet'!B17:K17)} -> 33162 | G9: 1 | H9: 41364 | I9: {=TRANSPOSE(HistoricalFS!C23:L23)} -> 6328 | L9: 1 | M9: 41364 | N9: {=TRANSPOSE(HistoricalFS!C43:L43)} -> 17.945756
B10: =B9+1 -> 2 | C10: =C9+365 -> 43190 | D10: 35545 | E10: =IFERROR(D10/D9-1,0) -> 0.071859357 | G10: =G9+1 -> 2 | H10: 41729 | I10: 7499 | J10: =IFERROR(I10/I9-1,0) -> 0.18505057 | L10: =L9+1 -> 2 | M10: 41729 | N10: 22.517903 | O10: =IFERROR(N10/N9-1,0) -> 0.25477591
B11: =B10+1 -> 3 | C11: =C10+365 -> 43555 | D11: 39310 | E11: =IFERROR(D11/D10-1,0) -> 0.10592207 | G11: =G10+1 -> 3 | H11: 42094 | I11: 8880 | J11: =IFERROR(I11/I10-1,0) -> 0.18415789 | L11: =L10+1 -> 3 | M11: 42094 | N11: 26.507137 | O11: =IFERROR(N11/N10-1,0) -> 0.17715836
B12: =B11+1 -> 4 | C12: =C11+365 -> 43920 | D12: 39783 | E12: =IFERROR(D12/D11-1,0) -> 0.012032562 | G12: =G11+1 -> 4 | H12: 42459 | I12: 9861 | J12: =IFERROR(I12/I11-1,0) -> 0.11047297 | L12: =L11+1 -> 4 | M12: 42459 | N12: 29.249815 | O12: =IFERROR(N12/N11-1,0) -> 0.10346941
B13: =B12+1 -> 5 | C13: =C12+365 -> 44285 | D13: 47028 | E13: =IFERROR(D13/D12-1,0) -> 0.18211296 | G13: =G12+1 -> 5 | H13: 42824 | I13: 11626 | J13: =IFERROR(I13/I12-1,0) -> 0.17898793 | L13: =L12+1 -> 5 | M13: 42824 | N13: 33.320565 | O13: =IFERROR(N13/N12-1,0) -> 0.13917182
B14: =B13+1 -> 6 | C14: =C13+365 -> 44650 | D14: 52446 | E14: =IFERROR(D14/D13-1,0) -> 0.11520796 | G14: =G13+1 -> 6 | H14: 43189 | I14: 12857 | J14: =IFERROR(I14/I13-1,0) -> 0.10588336 | L14: =L13+1 -> 6 | M14: 43189 | N14: 36.912666 | O14: =IFERROR(N14/N13-1,0) -> 0.10780432
B15: =B14+1 -> 7 | C15: =C14+365 -> 45015 | D15: 60580 | E15: =IFERROR(D15/D14-1,0) -> 0.15509286 | G15: =G14+1 -> 7 | H15: 43554 | I15: 14147 | J15: =IFERROR(I15/I14-1,0) -> 0.10033445 | L15: =L14+1 -> 7 | M15: 43554 | N15: 41.262343 | O15: =IFERROR(N15/N14-1,0) -> 0.11783697
B16: =B15+1 -> 8 | C16: =C15+365 -> 45380 | D16: 61896 | E16: =IFERROR(D16/D15-1,0) -> 0.021723341 | G16: =G15+1 -> 8 | H16: 43919 | I16: 14659 | J16: =IFERROR(I16/I15-1,0) -> 0.036191419 | L16: =L15+1 -> 8 | M16: 43919 | N16: 40.283453 | O16: =IFERROR(N16/N15-1,0) -> -0.023723569
B17: =B16+1 -> 9 | C17: =C16+365 -> 45745 | D17: 61328 | E17: =IFERROR(D17/D16-1,0) -> -0.0091766835 | G17: =G16+1 -> 9 | H17: 44284 | I17: 14698 | J17: =IFERROR(I17/I16-1,0) -> 0.0026604816 | L17: =L16+1 -> 9 | M17: 44284 | N17: 39.649302 | O17: =IFERROR(N17/N16-1,0) -> -0.015742208
B18: =B17+1 -> 10 | C18: =C17+365 -> 46110 | D18: 64468 | E18: =IFERROR(D18/D17-1,0) -> 0.051200104 | G18: =G17+1 -> 10 | H18: 44649 | I18: 15039 | J18: =IFERROR(I18/I17-1,0) -> 0.023200435 | L18: =L17+1 -> 10 | M18: 44649 | N18: 43.139258 | O18: =IFERROR(N18/N17-1,0) -> 0.08802061
B19: =B18+1 -> 11 | C19: =C18+365 -> 46475 | D19: =IFERROR(FORECAST(B19,$D$9:$D$18,$B$9:$B$18),0) -> 70987.067 | E19: =IFERROR(D19/D18-1,0) -> 0.10112097 | G19: =G18+1 -> 11 | H19: 45014 | I19: =IFERROR(FORECAST(G19,$I$9:$I$18,$G$9:$G$18),0) -> 17285.267 | J19: =IFERROR(I19/I18-1,0) -> 0.14936277 | L19: =L18+1 -> 11 | M19: 45014 | N19: =IFERROR(FORECAST(L19,$N$9:$N$18,$L$9:$L$18),0) -> 48.251239 | O19: =IFERROR(N19/N18-1,0) -> 0.11849951
B20: =B19+1 -> 12 | C20: =C19+365 -> 46840 | D20: =IFERROR(FORECAST(B20,$D$9:$D$18,$B$9:$B$18),0) -> 74883.879 | E20: =IFERROR(D20/D19-1,0) -> 0.054894677 | G20: =G19+1 -> 12 | H20: 45379 | I20: =IFERROR(FORECAST(G20,$I$9:$I$18,$G$9:$G$18),0) -> 18326.333 | J20: =IFERROR(I20/I19-1,0) -> 0.060228557 | L20: =L19+1 -> 12 | M20: 45379 | N20: =IFERROR(FORECAST(L20,$N$9:$N$18,$L$9:$L$18),0) -> 51.00986 | O20: =IFERROR(N20/N19-1,0) -> 0.057172038
B21: =B20+1 -> 13 | C21: =C20+365 -> 47205 | D21: =IFERROR(FORECAST(B21,$D$9:$D$18,$B$9:$B$18),0) -> 78780.691 | E21: =IFERROR(D21/D20-1,0) -> 0.052038065 | G21: =G20+1 -> 13 | H21: 45744 | I21: =IFERROR(FORECAST(G21,$I$9:$I$18,$G$9:$G$18),0) -> 19367.4 | J21: =IFERROR(I21/I20-1,0) -> 0.056807145 | L21: =L20+1 -> 13 | M21: 45744 | N21: =IFERROR(FORECAST(L21,$N$9:$N$18,$L$9:$L$18),0) -> 53.768482 | O21: =IFERROR(N21/N20-1,0) -> 0.054080164
B22: =B21+1 -> 14 | C22: =C21+365 -> 47570 | D22: =IFERROR(FORECAST(B22,$D$9:$D$18,$B$9:$B$18),0) -> 82677.503 | E22: =IFERROR(D22/D21-1,0) -> 0.049464051 | G22: =G21+1 -> 14 | H22: 46109 | I22: =IFERROR(FORECAST(G22,$I$9:$I$18,$G$9:$G$18),0) -> 20408.467 | J22: =IFERROR(I22/I21-1,0) -> 0.053753558 | L22: =L21+1 -> 14 | M22: 46109 | N22: =IFERROR(FORECAST(L22,$N$9:$N$18,$L$9:$L$18),0) -> 56.527104 | O22: =IFERROR(N22/N21-1,0) -> 0.051305552
B23: =B22+1 -> 15 | C23: =C22+365 -> 47935 | D23: =IFERROR(FORECAST(B23,$D$9:$D$18,$B$9:$B$18),0) -> 86574.315 | E23: =IFERROR(D23/D22-1,0) -> 0.047132678 | G23: =G22+1 -> 15 | H23: 46474 | I23: =IFERROR(FORECAST(G23,$I$9:$I$18,$G$9:$G$18),0) -> 21449.533 | J23: =IFERROR(I23/I22-1,0) -> 0.051011508 | L23: =L22+1 -> 15 | M23: 46474 | N23: =IFERROR(FORECAST(L23,$N$9:$N$18,$L$9:$L$18),0) -> 59.285725 | O23: =IFERROR(N23/N22-1,0) -> 0.048801751

Sheet Ratio Analysis
A1: _
B2: HINDUSTAN UNILEVER LTD
B3: (NSE: HINDUNILVR | BSE: 500696 )
B4: INR 1927.0
B5: 52 Week - (High- 2667.2 & Low- 1926.2)
B7: ="Ratio Analysis -"&'Data Sheet'!B1 -> Ratio Analysis -HINDUSTAN UNILEVER LTD
B8: Year | C8: ='Data Sheet'!B16 -> 42825 | D8: ='Data Sheet'!C16 -> 43190 | E8: ='Data Sheet'!D16 -> 43555 | F8: ='Data Sheet'!E16 -> 43921 | G8: ='Data Sheet'!F16 -> 44286 | H8: ='Data Sheet'!G16 -> 44651 | I8: ='Data Sheet'!H16 -> 45016 | J8: ='Data Sheet'!I16 -> 45382 | ... L8: ='Data Sheet'!K16 -> 46112 | M8: Trend | N8: Mean | O8: Median
B10: SalesGrowth | D10: =IFERROR(HistoricalFS!D12,0) -> 0.071859357 | E10: =IFERROR(HistoricalFS!E12,0) -> 0.10592207 | F10: =IFERROR(HistoricalFS!F12,0) -> 0.012032562 | G10: =IFERROR(HistoricalFS!G12,0) -> 0.18211296 | H10: =IFERROR(HistoricalFS!H12,0) -> 0.11520796 | I10: =IFERROR(HistoricalFS!I12,0) -> 0.15509286 | J10: =IFERROR(HistoricalFS!J12,0) -> 0.021723341 | K10: =IFERROR(HistoricalFS!K12,0) -> -0.0091766835 | L10: =IFERROR(HistoricalFS!L12,0) -> 0.051200104 | N10: =IFERROR(AVERAGE(D10:L10),0) -> 0.078441615 | O10: =IFERROR(MEDIAN(C10:L10),0) -> 0.071859357
B11: EBITDA Growth | D11: =IFERROR(HistoricalFS!D23/HistoricalFS!C23-1,0) -> 0.18505057 | E11: =IFERROR(HistoricalFS!E23/HistoricalFS!D23-1,0) -> 0.18415789 | F11: =IFERROR(HistoricalFS!F23/HistoricalFS!E23-1,0) -> 0.11047297 | G11: =IFERROR(HistoricalFS!G23/HistoricalFS!F23-1,0) -> 0.17898793 | H11: =IFERROR(HistoricalFS!H23/HistoricalFS!G23-1,0) -> 0.10588336 | I11: =IFERROR(HistoricalFS!I23/HistoricalFS!H23-1,0) -> 0.10033445 | J11: =IFERROR(HistoricalFS!J23/HistoricalFS!I23-1,0) -> 0.036191419 | K11: =IFERROR(HistoricalFS!K23/HistoricalFS!J23-1,0) -> 0.0026604816 | L11: =IFERROR(HistoricalFS!L23/HistoricalFS!K23-1,0) -> 0.023200435 | N11: =IFERROR(AVERAGE(D11:L11),0) -> 0.10299328 | O11: =IFERROR(MEDIAN(C11:L11),0) -> 0.10588336
B12: EBT Growth | D12: =IFERROR(HistoricalFS!D32/HistoricalFS!C32-1,0) -> 0.18631633 | E12: =IFERROR(HistoricalFS!E32/HistoricalFS!D32-1,0) -> 0.19114051 | F12: =IFERROR(HistoricalFS!F32/HistoricalFS!E32-1,0) -> 0.055421396 | G12: =IFERROR(HistoricalFS!G32/HistoricalFS!F32-1,0) -> 0.19379934 | H12: =IFERROR(HistoricalFS!H32/HistoricalFS!G32-1,0) -> 0.11739339 | I12: =IFERROR(HistoricalFS!I32/HistoricalFS!H32-1,0) -> 0.10600343 | J12: =IFERROR(HistoricalFS!J32/HistoricalFS!I32-1,0) -> 0.016516749 | K12: =IFERROR(HistoricalFS!K32/HistoricalFS!J32-1,0) -> -0.0034327561 | L12: =IFERROR(HistoricalFS!L32/HistoricalFS!K32-1,0) -> 0.017758726 | N12: =IFERROR(AVERAGE(D12:L12),0) -> 0.097879679 | O12: =IFERROR(MEDIAN(C12:L12),0) -> 0.10600343
B13: Net Profit Growth | D13: =IFERROR(HistoricalFS!D38/HistoricalFS!C38-1,0) -> 0.25489186 | E13: =IFERROR(HistoricalFS!E38/HistoricalFS!D38-1,0) -> 0.17726713 | F13: =IFERROR(HistoricalFS!F38/HistoricalFS!E38-1,0) -> 0.10352039 | G13: =IFERROR(HistoricalFS!G38/HistoricalFS!F38-1,0) -> 0.23641819 | H13: =IFERROR(HistoricalFS!H38/HistoricalFS!G38-1,0) -> 0.10780432 | I13: =IFERROR(HistoricalFS!I38/HistoricalFS!H38-1,0) -> 0.11783697 | J13: =IFERROR(HistoricalFS!J38/HistoricalFS!I38-1,0) -> -0.023723569 | K13: =IFERROR(HistoricalFS!K38/HistoricalFS!J38-1,0) -> -0.015742208 | L13: =IFERROR(HistoricalFS!L38/HistoricalFS!K38-1,0) -> 0.08802061 | N13: =IFERROR(AVERAGE(D13:L13),0) -> 0.11625485 | O13: =IFERROR(MEDIAN(C13:L13),0) -> 0.10780432
B14: Dividend Growth | D14: =IFERROR(HistoricalFS!D46/HistoricalFS!C46-1,0) -> 0.17636188 | E14: =IFERROR(HistoricalFS!E46/HistoricalFS!D46-1,0) -> 0.099898369 | F14: =IFERROR(HistoricalFS!F46/HistoricalFS!E46-1,0) -> 0.13631114 | G14: =IFERROR(HistoricalFS!G46/HistoricalFS!F46-1,0) -> 0.6238764 | H14: =IFERROR(HistoricalFS!H46/HistoricalFS!G46-1,0) -> -0.16049383 | I14: =IFERROR(HistoricalFS!I46/HistoricalFS!H46-1,0) -> 0.14705882 | J14: =IFERROR(HistoricalFS!J46/HistoricalFS!I46-1,0) -> 0.076923077 | K14: =IFERROR(HistoricalFS!K46/HistoricalFS!J46-1,0) -> 0.26190476 | L14: =IFERROR(HistoricalFS!L46/HistoricalFS!K46-1,0) -> -0.22641509 | N14: =IFERROR(AVERAGE(D14:L14),0) -> 0.12615839 | O14: =IFERROR(MEDIAN(C14:L14),0) -> 0.13631114
B16: Gross Margin | C16: =IFERROR(HistoricalFS!C18,0) -> 0.43685544 | D16: =IFERROR(HistoricalFS!D18,0) -> 0.45663244 | E16: =IFERROR(HistoricalFS!E18,0) -> 0.46372424 | F16: =IFERROR(HistoricalFS!F18,0) -> 0.48183898 | G16: =IFERROR(HistoricalFS!G18,0) -> 0.46200136 | H16: =IFERROR(HistoricalFS!H18,0) -> 0.44579186 | I16: =IFERROR(HistoricalFS!I18,0) -> 0.41596236 | J16: =IFERROR(HistoricalFS!J18,0) -> 0.45632997 | ... L16: =IFERROR(HistoricalFS!L18,0) -> 0.44726066 | N16: =IFERROR(AVERAGE(C16:L16),0) -> 0.45198443 | O16: =IFERROR(MEDIAN(C16:L16),0) -> 0.45488851
B17: EBITDA Margin | C17: =IFERROR(HistoricalFS!C24,0) -> 0.19082082 | D17: =IFERROR(HistoricalFS!D24,0) -> 0.21097201 | E17: =IFERROR(HistoricalFS!E24,0) -> 0.22589672 | F17: =IFERROR(HistoricalFS!F24,0) -> 0.24786969 | G17: =IFERROR(HistoricalFS!G24,0) -> 0.24721443 | H17: =IFERROR(HistoricalFS!H24,0) -> 0.24514739 | I17: =IFERROR(HistoricalFS!I24,0) -> 0.23352592 | J17: =IFERROR(HistoricalFS!J24,0) -> 0.23683275 | ... L17: =IFERROR(HistoricalFS!L24,0) -> 0.23327853 | N17: =IFERROR(AVERAGE(C17:L17),0) -> 0.23112204 | O17: =IFERROR(MEDIAN(C17:L17),0) -> 0.23517933
B18: EBIT Margin | C18: =IFERROR((HistoricalFS!C23-HistoricalFS!C29)/HistoricalFS!C11,0) -> 0.17779386 | D18: =IFERROR((HistoricalFS!D23-HistoricalFS!D29)/HistoricalFS!D11,0) -> 0.19634266 | E18: =IFERROR((HistoricalFS!E23-HistoricalFS!E29)/HistoricalFS!E11,0) -> 0.21152379 | F18: =IFERROR((HistoricalFS!F23-HistoricalFS!F29)/HistoricalFS!F11,0) -> 0.22268306 | G18: =IFERROR((HistoricalFS!G23-HistoricalFS!G29)/HistoricalFS!G11,0) -> 0.22437697 | H18: =IFERROR((HistoricalFS!H23-HistoricalFS!H29)/HistoricalFS!H11,0) -> 0.22434504 | I18: =IFERROR((HistoricalFS!I23-HistoricalFS!I29)/HistoricalFS!I11,0) -> 0.21475735 | J18: =IFERROR((HistoricalFS!J23-HistoricalFS!J29)/HistoricalFS!J11,0) -> 0.21718689 | ... L18: =IFERROR((HistoricalFS!L23-HistoricalFS!L29)/HistoricalFS!L11,0) -> 0.2126016 | N18: =IFERROR(AVERAGE(C18:L18),0) -> 0.21208422 | O18: =IFERROR(MEDIAN(C18:L18),0) -> 0.21597212
B19: EBT Margin | C19: =IFERROR(HistoricalFS!C33,0) -> 0.17673844 | D19: =IFERROR(HistoricalFS!D33,0) -> 0.1956112 | E19: =IFERROR(HistoricalFS!E33,0) -> 0.2106843 | F19: =IFERROR(HistoricalFS!F33,0) -> 0.21971696 | G19: =IFERROR(HistoricalFS!G33,0) -> 0.22188909 | H19: =IFERROR(HistoricalFS!H33,0) -> 0.22232391 | I19: =IFERROR(HistoricalFS!I33,0) -> 0.21287554 | J19: =IFERROR(HistoricalFS!J33,0) -> 0.21179075 | ... L19: =IFERROR(HistoricalFS!L33,0) -> 0.20624186 | N19: =IFERROR(AVERAGE(C19:L19),0) -> 0.20908906 | O19: =IFERROR(MEDIAN(C19:L19),0) -> 0.21233314
B20: Net Profit Margin | C20: =IFERROR(HistoricalFS!C39,0) -> 0.11712201 | D20: =IFERROR(HistoricalFS!D39,0) -> 0.13712196 | E20: =IFERROR(HistoricalFS!E39,0) -> 0.14596795 | F20: =IFERROR(HistoricalFS!F39,0) -> 0.15916346 | G20: =IFERROR(HistoricalFS!G39,0) -> 0.16647529 | H20: =IFERROR(HistoricalFS!H39,0) -> 0.16537009 | I20: =IFERROR(HistoricalFS!I39,0) -> 0.16003632 | J20: =IFERROR(HistoricalFS!J39,0) -> 0.1529178 | ... L20: =IFERROR(HistoricalFS!L39,0) -> 0.15722529 | N20: =IFERROR(AVERAGE(C20:L20),0) -> 0.15133047 | O20: =IFERROR(MEDIAN(C20:L20),0) -> 0.15507154
B22: SalesExpenses%Sales | C22: =IFERROR(HistoricalFS!C21,0) -> 0.24603462 | D22: =IFERROR(HistoricalFS!D21,0) -> 0.24566043 | E22: =IFERROR(HistoricalFS!E21,0) -> 0.23782752 | F22: =IFERROR(HistoricalFS!F21,0) -> 0.23396928 | G22: =IFERROR(HistoricalFS!G21,0) -> 0.21478694 | H22: =IFERROR(HistoricalFS!H21,0) -> 0.20064447 | I22: =IFERROR(HistoricalFS!I21,0) -> 0.18243645 | J22: =IFERROR(HistoricalFS!J21,0) -> 0.21949722 | ... L22: =IFERROR(HistoricalFS!L21,0) -> 0.21398213 | N22: =IFERROR(AVERAGE(C22:L22),0) -> 0.2208624 | O22: =IFERROR(MEDIAN(C22:L22),0) -> 0.21714208
B23: Depreciation%Sales | C23: =IFERROR(HistoricalFS!C30,0) -> 0.013026959 | D23: =IFERROR(HistoricalFS!D30,0) -> 0.014629343 | E23: =IFERROR(HistoricalFS!E30,0) -> 0.014372933 | F23: =IFERROR(HistoricalFS!F30,0) -> 0.025186638 | G23: =IFERROR(HistoricalFS!G30,0) -> 0.022837459 | H23: =IFERROR(HistoricalFS!H30,0) -> 0.020802349 | I23: =IFERROR(HistoricalFS!I30,0) -> 0.01876857 | J23: =IFERROR(HistoricalFS!J30,0) -> 0.019645858 | ... L23: =IFERROR(HistoricalFS!L30,0) -> 0.020676925 | N23: =IFERROR(AVERAGE(C23:L23),0) -> 0.019037816 | O23: =IFERROR(MEDIAN(C23:L23),0) -> 0.020038491
B24: OperatingIncome%Sales | C24: =C18 -> 0.17779386 | D24: =D18 -> 0.19634266 | E24: =E18 -> 0.21152379 | F24: =F18 -> 0.22268306 | G24: =G18 -> 0.22437697 | H24: =H18 -> 0.22434504 | I24: =I18 -> 0.21475735 | J24: =J18 -> 0.21718689 | ... L24: =L18 -> 0.2126016 | N24: =IFERROR(AVERAGE(C24:L24),0) -> 0.21208422 | O24: =IFERROR(MEDIAN(C24:L24),0) -> 0.21597212
B26: Return on Capital Employed | C26: =IFERROR((HistoricalFS!C23-HistoricalFS!C29)/SUM(HistoricalFS!C54:C56),0) -> 0.83976642 | D26: =IFERROR((HistoricalFS!D23-HistoricalFS!D29)/SUM(HistoricalFS!D54:D56),0) -> 0.95852218 | E26: =IFERROR((HistoricalFS!E23-HistoricalFS!E29)/SUM(HistoricalFS!E54:E56),0) -> 1.0438112 | F26: =IFERROR((HistoricalFS!F23-HistoricalFS!F29)/SUM(HistoricalFS!F54:F56),0) -> 1.0765585 | G26: =IFERROR((HistoricalFS!G23-HistoricalFS!G29)/SUM(HistoricalFS!G54:G56),0) -> 0.22133658 | H26: =IFERROR((HistoricalFS!H23-HistoricalFS!H29)/SUM(HistoricalFS!H54:H56),0) -> 0.23483155 | I26: =IFERROR((HistoricalFS!I23-HistoricalFS!I29)/SUM(HistoricalFS!I54:I56),0) -> 0.25250859 | J26: =IFERROR((HistoricalFS!J23-HistoricalFS!J29)/SUM(HistoricalFS!J54:J56),0) -> 0.25507571 | ... L26: =IFERROR((HistoricalFS!L23-HistoricalFS!L29)/SUM(HistoricalFS!L54:L56),0) -> 0.27293546 | N26: =IFERROR(AVERAGE(C26:L26),0) -> 0.54187154 | O26: =IFERROR(MEDIAN(C26:L26),0) -> 0.26815235
B27: Retained Earnings % | C27: =IFERROR(HistoricalFS!C49,0) -> 0.054582904 | D27: =IFERROR(HistoricalFS!D49,0) -> 0.11366434 | E27: =IFERROR(HistoricalFS!E49,0) -> 0.17183688 | F27: =IFERROR(HistoricalFS!F49,0) -> 0.14718888 | G27: =IFERROR(HistoricalFS!G49,0) -> 0 | H27: =IFERROR(HistoricalFS!H49,0) -> 0.078750144 | I27: =IFERROR(HistoricalFS!I49,0) -> 0.054667354 | J27: =IFERROR(HistoricalFS!J49,0) -> 0 | ... L27: =IFERROR(HistoricalFS!L49,0) -> 0.049427782 | N27: =IFERROR(AVERAGE(C27:L27),0) -> 0.067011829 | O27: =IFERROR(MEDIAN(C27:L27),0) -> 0.054625129
B28: Return on Equity | C28: =IFERROR(HistoricalFS!C38/SUM(HistoricalFS!C54:C55),0) -> 0.57591934 | D28: =IFERROR(HistoricalFS!D38/SUM(HistoricalFS!D54:D55),0) -> 0.66941354 | E28: =IFERROR(HistoricalFS!E38/SUM(HistoricalFS!E54:E55),0) -> 0.72937587 | F28: =IFERROR(HistoricalFS!F38/SUM(HistoricalFS!F54:F55),0) -> 0.76947381 | G28: =IFERROR(HistoricalFS!G38/SUM(HistoricalFS!G54:G55),0) -> 0.16421949 | H28: =IFERROR(HistoricalFS!H38/SUM(HistoricalFS!H54:H55),0) -> 0.17677993 | I28: =IFERROR(HistoricalFS!I38/SUM(HistoricalFS!I54:I55),0) -> 0.19272821 | J28: =IFERROR(HistoricalFS!J38/SUM(HistoricalFS!J54:J55),0) -> 0.18479831 | ... L28: =IFERROR(HistoricalFS!L38/SUM(HistoricalFS!L54:L55),0) -> 0.20796487 | N28: =IFERROR(AVERAGE(C28:L28),0) -> 0.38592487 | O28: =IFERROR(MEDIAN(C28:L28),0) -> 0.20034654
B29: Self Sustained Growth Rate | C29: =IFERROR(C27*C28,0) -> 0.03143535 | D29: =IFERROR(D27*D28,0) -> 0.076088449 | E29: =IFERROR(E27*E28,0) -> 0.12533367 | F29: =IFERROR(F27*F28,0) -> 0.11325799 | G29: =IFERROR(G27*G28,0) -> 0 | H29: =IFERROR(H27*H28,0) -> 0.013921445 | I29: =IFERROR(I27*I28,0) -> 0.010535941 | J29: =IFERROR(J27*J28,0) -> 0 | ... L29: =IFERROR(L27*L28,0) -> 0.010279242 | N29: =IFERROR(AVERAGE(C29:L29),0) -> 0.038085209 | O29: =IFERROR(MEDIAN(C29:L29),0) -> 0.012228693
B30: Interest Coverage Ratio | C30: =IFERROR((HistoricalFS!C23-HistoricalFS!C29)/HistoricalFS!C26,0) -> 168.45714 | D30: =IFERROR((HistoricalFS!D23-HistoricalFS!D29)/HistoricalFS!D26,0) -> 268.42308 | E30: =IFERROR((HistoricalFS!E23-HistoricalFS!E29)/HistoricalFS!E26,0) -> 251.9697 | F30: =IFERROR((HistoricalFS!F23-HistoricalFS!F29)/HistoricalFS!F26,0) -> 75.076271 | G30: =IFERROR((HistoricalFS!G23-HistoricalFS!G29)/HistoricalFS!G26,0) -> 90.188034 | H30: =IFERROR((HistoricalFS!H23-HistoricalFS!H29)/HistoricalFS!H26,0) -> 111 | I30: =IFERROR((HistoricalFS!I23-HistoricalFS!I29)/HistoricalFS!I26,0) -> 114.12281 | J30: =IFERROR((HistoricalFS!J23-HistoricalFS!J29)/HistoricalFS!J26,0) -> 40.248503 | ... L30: =IFERROR((HistoricalFS!L23-HistoricalFS!L29)/HistoricalFS!L26,0) -> 33.429268 | N30: =IFERROR(AVERAGE(C30:L30),0) -> 118.82035 | O30: =IFERROR(MEDIAN(C30:L30),0) -> 100.59402
B32: Debtor Turnover Ratio | C32: =IFERROR(HistoricalFS!C11/HistoricalFS!C66,0) -> 30.564055 | D32: =IFERROR(HistoricalFS!D11/HistoricalFS!D66,0) -> 27.133588 | E32: =IFERROR(HistoricalFS!E11/HistoricalFS!E66,0) -> 21.646476 | F32: =IFERROR(HistoricalFS!F11/HistoricalFS!F66,0) -> 34.624021 | G32: =IFERROR(HistoricalFS!G11/HistoricalFS!G66,0) -> 26.750853 | H32: =IFERROR(HistoricalFS!H11/HistoricalFS!H66,0) -> 23.455277 | I32: =IFERROR(HistoricalFS!I11/HistoricalFS!I66,0) -> 19.675219 | J32: =IFERROR(HistoricalFS!J11/HistoricalFS!J66,0) -> 20.652653 | ... L32: =IFERROR(HistoricalFS!L11/HistoricalFS!L66,0) -> 19.079017 | N32: =IFERROR(AVERAGE(C32:L32),0) -> 23.963981 | O32: =IFERROR(MEDIAN(C32:L32),0) -> 22.550877
B33: Creditor Turnover Ratio | C33: =IFERROR(HistoricalFS!C11/HistoricalFS!C57,0) -> 3.8183074 | D33: =IFERROR(HistoricalFS!D11/HistoricalFS!D57,0) -> 3.3593233 | E33: =IFERROR(HistoricalFS!E11/HistoricalFS!E57,0) -> 3.6865798 | F33: =IFERROR(HistoricalFS!F11/HistoricalFS!F57,0) -> 3.3363804 | G33: =IFERROR(HistoricalFS!G11/HistoricalFS!G57,0) -> 2.2324124 | H33: =IFERROR(HistoricalFS!H11/HistoricalFS!H57,0) -> 2.5706303 | I33: =IFERROR(HistoricalFS!I11/HistoricalFS!I57,0) -> 2.8106152 | J33: =IFERROR(HistoricalFS!J11/HistoricalFS!J57,0) -> 2.4002792 | ... L33: =IFERROR(HistoricalFS!L11/HistoricalFS!L57,0) -> 2.1838014 | N33: =IFERROR(AVERAGE(C33:L33),0) -> 2.8526813 | O33: =IFERROR(MEDIAN(C33:L33),0) -> 2.6906228
B34: Inventory Turnover | C34: =IFERROR(HistoricalFS!C11/HistoricalFS!C67,0) -> 13.050767 | D34: =IFERROR(HistoricalFS!D11/HistoricalFS!D67,0) -> 14.144449 | E34: =IFERROR(HistoricalFS!E11/HistoricalFS!E67,0) -> 15.27195 | F34: =IFERROR(HistoricalFS!F11/HistoricalFS!F67,0) -> 14.377665 | G34: =IFERROR(HistoricalFS!G11/HistoricalFS!G67,0) -> 13.139983 | H34: =IFERROR(HistoricalFS!H11/HistoricalFS!H67,0) -> 12.804199 | I34: =IFERROR(HistoricalFS!I11/HistoricalFS!I67,0) -> 14.250765 | J34: =IFERROR(HistoricalFS!J11/HistoricalFS!J67,0) -> 15.389359 | ... L34: =IFERROR(HistoricalFS!L11/HistoricalFS!L67,0) -> 13.461683 | N34: =IFERROR(AVERAGE(C34:L34),0) -> 13.978165 | O34: =IFERROR(MEDIAN(C34:L34),0) -> 14.017638
B35: Fixed Asset Turnover | C35: =IFERROR(HistoricalFS!C11/HistoricalFS!C60,0) -> 7.5044128 | D35: =IFERROR(HistoricalFS!D11/HistoricalFS!D60,0) -> 7.8500442 | E35: =IFERROR(HistoricalFS!E11/HistoricalFS!E60,0) -> 8.3372216 | F35: =IFERROR(HistoricalFS!F11/HistoricalFS!F60,0) -> 7.2609965 | G35: =IFERROR(HistoricalFS!G11/HistoricalFS!G60,0) -> 0.91417686 | H35: =IFERROR(HistoricalFS!H11/HistoricalFS!H60,0) -> 1.0189031 | I35: =IFERROR(HistoricalFS!I11/HistoricalFS!I60,0) -> 1.1500057 | J35: =IFERROR(HistoricalFS!J11/HistoricalFS!J60,0) -> 1.151682 | ... L35: =IFERROR(HistoricalFS!L11/HistoricalFS!L60,0) -> 1.1225883 | N35: =IFERROR(AVERAGE(C35:L35),0) -> 3.7438733 | O35: =IFERROR(MEDIAN(C35:L35),0) -> 1.1508439
B36: Capital Turnover Ratio | C36: =IFERROR(HistoricalFS!C11/SUM(HistoricalFS!C54:C55),0) -> 4.9172598 | D36: =IFERROR(HistoricalFS!D11/SUM(HistoricalFS!D54:D55),0) -> 4.8818844 | E36: =IFERROR(HistoricalFS!E11/SUM(HistoricalFS!E54:E55),0) -> 4.9968222 | F36: =IFERROR(HistoricalFS!F11/SUM(HistoricalFS!F54:F55),0) -> 4.8344878 | G36: =IFERROR(HistoricalFS!G11/SUM(HistoricalFS!G54:G55),0) -> 0.98644964 | H36: =IFERROR(HistoricalFS!H11/SUM(HistoricalFS!H54:H55),0) -> 1.0689957 | I36: =IFERROR(HistoricalFS!I11/SUM(HistoricalFS!I54:I55),0) -> 1.204278 | J36: =IFERROR(HistoricalFS!J11/SUM(HistoricalFS!J54:J55),0) -> 1.2084814 | ... L36: =IFERROR(HistoricalFS!L11/SUM(HistoricalFS!L54:L55),0) -> 1.322719 | N36: =IFERROR(AVERAGE(C36:L36),0) -> 2.6662785 | O36: =IFERROR(MEDIAN(C36:L36),0) -> 1.2820631
B38: Debtor Days | C38: =IFERROR(365/C32,0) -> 11.942133 | D38: =IFERROR(365/D32,0) -> 13.451962 | E38: =IFERROR(365/E32,0) -> 16.861867 | F38: =IFERROR(365/F32,0) -> 10.541814 | G38: =IFERROR(365/G32,0) -> 13.644425 | H38: =IFERROR(365/H32,0) -> 15.56153 | I38: =IFERROR(365/I32,0) -> 18.551255 | J38: =IFERROR(365/J32,0) -> 17.673275 | ... L38: =IFERROR(365/L32,0) -> 19.130964 | N38: =IFERROR(AVERAGE(C38:L38),0) -> 16.00884 | O38: =IFERROR(MEDIAN(C38:L38),0) -> 16.211699
B39: Payable Days | C39: =IFERROR(365/C33,0) -> 95.592093 | D39: =IFERROR(365/D33,0) -> 108.65283 | E39: =IFERROR(365/E33,0) -> 99.007759 | F39: =IFERROR(365/F33,0) -> 109.39999 | G39: =IFERROR(365/G33,0) -> 163.50026 | H39: =IFERROR(365/H33,0) -> 141.98852 | I39: =IFERROR(365/I33,0) -> 129.86481 | J39: =IFERROR(365/J33,0) -> 152.06564 | ... L39: =IFERROR(365/L33,0) -> 167.13974 | N39: =IFERROR(AVERAGE(C39:L39),0) -> 133.86952 | O39: =IFERROR(MEDIAN(C39:L39),0) -> 135.92666
B40: Inventory Days | C40: =IFERROR(365/C34,0) -> 27.967704 | D40: =IFERROR(365/D34,0) -> 25.805177 | E40: =IFERROR(365/E34,0) -> 23.900025 | F40: =IFERROR(365/F34,0) -> 25.386597 | G40: =IFERROR(365/G34,0) -> 27.777813 | H40: =IFERROR(365/H34,0) -> 28.506273 | I40: =IFERROR(365/I34,0) -> 25.612661 | J40: =IFERROR(365/J34,0) -> 23.717688 | ... L40: =IFERROR(365/L34,0) -> 27.113995 | N40: =IFERROR(AVERAGE(C40:L40),0) -> 26.206427 | O40: =IFERROR(MEDIAN(C40:L40),0) -> 26.040755
B41: Cash Conversion Cycle (in days) | C41: =IFERROR(SUM(C38,C40)-C39,0) -> -55.682257 | D41: =IFERROR(SUM(D38,D40)-D39,0) -> -69.395696 | E41: =IFERROR(SUM(E38,E40)-E39,0) -> -58.245866 | F41: =IFERROR(SUM(F38,F40)-F39,0) -> -73.471583 | G41: =IFERROR(SUM(G38,G40)-G39,0) -> -122.07802 | H41: =IFERROR(SUM(H38,H40)-H39,0) -> -97.920718 | I41: =IFERROR(SUM(I38,I40)-I39,0) -> -85.700891 | J41: =IFERROR(SUM(J38,J40)-J39,0) -> -110.67468 | ... L41: =IFERROR(SUM(L38,L40)-L39,0) -> -120.89479 | N41: =IFERROR(AVERAGE(C41:L41),0) -> -91.654256 | O41: =IFERROR(MEDIAN(C41:L41),0) -> -91.810805
B43: CFO/Sales | C43: =IFERROR(HistoricalFS!C79/HistoricalFS!C11,0) -> 0.19636934 | D43: =IFERROR(HistoricalFS!D79/HistoricalFS!D11,0) -> 0.21057814 | E43: =IFERROR(HistoricalFS!E79/HistoricalFS!E11,0) -> 0.22663444 | F43: =IFERROR(HistoricalFS!F79/HistoricalFS!F11,0) -> 0.24440087 | G43: =IFERROR(HistoricalFS!G79/HistoricalFS!G11,0) -> 0.24819257 | H43: =IFERROR(HistoricalFS!H79/HistoricalFS!H11,0) -> 0.24461351 | I43: =IFERROR(HistoricalFS!I79/HistoricalFS!I11,0) -> 0.2325685 | J43: =IFERROR(HistoricalFS!J79/HistoricalFS!J11,0) -> 0.2348617 | ... L43: =IFERROR(HistoricalFS!L79/HistoricalFS!L11,0) -> 0.23504684 | N43: =IFERROR(AVERAGE(C43:L43),0) -> 0.23169067 | O43: =IFERROR(MEDIAN(C43:L43),0) -> 0.23495427
B44: CFO/Total Asset | C44: =IFERROR(HistoricalFS!C79/HistoricalFS!C71,0) -> 0.41461862 | D44: =IFERROR(HistoricalFS!D79/HistoricalFS!D71,0) -> 0.41904602 | E44: =IFERROR(HistoricalFS!E79/HistoricalFS!E71,0) -> 0.47823286 | F44: =IFERROR(HistoricalFS!F79/HistoricalFS!F71,0) -> 0.48245919 | G44: =IFERROR(HistoricalFS!G79/HistoricalFS!G71,0) -> 0.16979924 | H44: =IFERROR(HistoricalFS!H79/HistoricalFS!H71,0) -> 0.18195615 | I44: =IFERROR(HistoricalFS!I79/HistoricalFS!I71,0) -> 0.19279664 | J44: =IFERROR(HistoricalFS!J79/HistoricalFS!J71,0) -> 0.18521067 | ... L44: =IFERROR(HistoricalFS!L79/HistoricalFS!L71,0) -> 0.19003486 | N44: =IFERROR(AVERAGE(C44:L44),0) -> 0.29012496 | O44: =IFERROR(MEDIAN(C44:L44),0) -> 0.19141575
B45: CFO/Total Debt | C45: =IFERROR(HistoricalFS!C79/HistoricalFS!C56,0) -> 23.509025 | D45: =IFERROR(HistoricalFS!D79/HistoricalFS!D56,0) -> 0 | E45: =IFERROR(HistoricalFS!E79/HistoricalFS!E56,0) -> 89.989899 | F45: =IFERROR(HistoricalFS!F79/HistoricalFS!F56,0) -> 0 | G45: =IFERROR(HistoricalFS!G79/HistoricalFS!G56,0) -> 0 | H45: =IFERROR(HistoricalFS!H79/HistoricalFS!H56,0) -> 12.300096 | I45: =IFERROR(HistoricalFS!I79/HistoricalFS!I56,0) -> 11.557834 | J45: =IFERROR(HistoricalFS!J79/HistoricalFS!J56,0) -> 9.7958221 | ... L45: =IFERROR(HistoricalFS!L79/HistoricalFS!L56,0) -> 10.252368 | N45: =IFERROR(AVERAGE(C45:L45),0) -> 16.647179 | O45: =IFERROR(MEDIAN(C45:L45),0) -> 10.024095

Sheet Common Size Income Statement
B2: HINDUSTAN UNILEVER LTD
B3: (NSE: HINDUNILVR | BSE: 500696 )
B4: INR 1927.0
B5: 52 Week - (High- 2667.2 & Low- 1926.2)
B7: ="Common Size Income Statement"&" "&"-"&'Data Sheet'!$B$1 -> Common Size Income Statement -HINDUSTAN UNILEVER LTD
B9: Particilars | C9: ='Data Sheet'!B16 -> 42825 | D9: ='Data Sheet'!C16 -> 43190 | E9: ='Data Sheet'!D16 -> 43555 | F9: ='Data Sheet'!E16 -> 43921 | G9: ='Data Sheet'!F16 -> 44286 | H9: ='Data Sheet'!G16 -> 44651 | I9: ='Data Sheet'!H16 -> 45016 | J9: ='Data Sheet'!I16 -> 45382 | ... L9: ='Data Sheet'!K16 -> 46112
B11: ='Data Sheet'!A17 -> Sales | C11: ='Data Sheet'!B17/'Data Sheet'!B$17 -> 1 | D11: ='Data Sheet'!C17/'Data Sheet'!C$17 -> 1 | E11: ='Data Sheet'!D17/'Data Sheet'!D$17 -> 1 | F11: ='Data Sheet'!E17/'Data Sheet'!E$17 -> 1 | G11: ='Data Sheet'!F17/'Data Sheet'!F$17 -> 1 | H11: ='Data Sheet'!G17/'Data Sheet'!G$17 -> 1 | I11: ='Data Sheet'!H17/'Data Sheet'!H$17 -> 1 | J11: ='Data Sheet'!I17/'Data Sheet'!I$17 -> 1 | ... L11: ='Data Sheet'!K17/'Data Sheet'!K$17 -> 1
B12: ='Data Sheet'!A18 -> Raw Material Cost | C12: ='Data Sheet'!B18/'Data Sheet'!B$17 -> 0.41028888 | D12: ='Data Sheet'!C18/'Data Sheet'!C$17 -> 0.400422 | E12: ='Data Sheet'!D18/'Data Sheet'!D$17 -> 0.4030781 | F12: ='Data Sheet'!E18/'Data Sheet'!E$17 -> 0.39456552 | G12: ='Data Sheet'!F18/'Data Sheet'!F$17 -> 0.42827677 | H12: ='Data Sheet'!G18/'Data Sheet'!G$17 -> 0.43608664 | I12: ='Data Sheet'!H18/'Data Sheet'!H$17 -> 0.46924728 | J12: ='Data Sheet'!I18/'Data Sheet'!I$17 -> 0.4333398 | ... L12: ='Data Sheet'!K18/'Data Sheet'!K$17 -> 0.45228641
B13: ='Data Sheet'!A19 -> Change in Inventory | C13: ='Data Sheet'!B19/'Data Sheet'!B$17 -> -0.0043423195 | D13: ='Data Sheet'!C19/'Data Sheet'!C$17 -> 0.0020256014 | E13: ='Data Sheet'!D19/'Data Sheet'!D$17 -> -0.00030526584 | F13: ='Data Sheet'!E19/'Data Sheet'!E$17 -> 0.0027147274 | G13: ='Data Sheet'!F19/'Data Sheet'!F$17 -> 0.0086118908 | H13: ='Data Sheet'!G19/'Data Sheet'!G$17 -> 0.00041947908 | I13: ='Data Sheet'!H19/'Data Sheet'!H$17 -> 0.0012380324 | J13: ='Data Sheet'!I19/'Data Sheet'!I$17 -> 0.00017771746 | ... L13: ='Data Sheet'!K19/'Data Sheet'!K$17 -> 0.0066544642
B14: ='Data Sheet'!A20 -> Power and Fuel | C14: ='Data Sheet'!B20/'Data Sheet'!B$17 -> 0.008895724 | D14: ='Data Sheet'!C20/'Data Sheet'!C$17 -> 0.0082993389 | E14: ='Data Sheet'!D20/'Data Sheet'!D$17 -> 0.0078351564 | F14: ='Data Sheet'!E20/'Data Sheet'!E$17 -> 0.0075157731 | G14: ='Data Sheet'!F20/'Data Sheet'!F$17 -> 0.0072084715 | H14: ='Data Sheet'!G20/'Data Sheet'!G$17 -> 0.0060633795 | I14: ='Data Sheet'!H20/'Data Sheet'!H$17 -> 0.0063387257 | J14: ='Data Sheet'!I20/'Data Sheet'!I$17 -> 0.0072056353 | ... L14: ='Data Sheet'!K20/'Data Sheet'!K$17 -> 0.0066079295
B15: ='Data Sheet'!A21 -> Other Mfr. Exp | C15: ='Data Sheet'!B21/'Data Sheet'!B$17 -> 0.087057475 | D15: ='Data Sheet'!C21/'Data Sheet'!C$17 -> 0.08434379 | E15: ='Data Sheet'!D21/'Data Sheet'!D$17 -> 0.077359451 | F15: ='Data Sheet'!E21/'Data Sheet'!E$17 -> 0.073046276 | G15: ='Data Sheet'!F21/'Data Sheet'!F$17 -> 0.060984945 | H15: ='Data Sheet'!G21/'Data Sheet'!G$17 -> 0.063951493 | I15: ='Data Sheet'!H21/'Data Sheet'!H$17 -> 0.062578409 | J15: ='Data Sheet'!I21/'Data Sheet'!I$17 -> 0.05468851 | ... L15: ='Data Sheet'!K21/'Data Sheet'!K$17 -> 0.051250233
B16: ='Data Sheet'!A22 -> Employee Cost | C16: ='Data Sheet'!B22/'Data Sheet'!B$17 -> 0.052560159 | D16: ='Data Sheet'!C22/'Data Sheet'!C$17 -> 0.052328035 | E16: ='Data Sheet'!D22/'Data Sheet'!D$17 -> 0.047697787 | F16: ='Data Sheet'!E22/'Data Sheet'!E$17 -> 0.045748184 | G16: ='Data Sheet'!F22/'Data Sheet'!F$17 -> 0.050140342 | H16: ='Data Sheet'!G22/'Data Sheet'!G$17 -> 0.048526103 | I16: ='Data Sheet'!H22/'Data Sheet'!H$17 -> 0.047111258 | J16: ='Data Sheet'!I22/'Data Sheet'!I$17 -> 0.048613804 | ... L16: ='Data Sheet'!K22/'Data Sheet'!K$17 -> 0.04924924
B17: ='Data Sheet'!A23 -> Selling and admin | C17: ='Data Sheet'!B23/'Data Sheet'!B$17 -> 0.20170677 | D17: ='Data Sheet'!C23/'Data Sheet'!C$17 -> 0.20402307 | E17: ='Data Sheet'!D23/'Data Sheet'!D$17 -> 0.19832104 | F17: ='Data Sheet'!E23/'Data Sheet'!E$17 -> 0.1915391 | G17: ='Data Sheet'!F23/'Data Sheet'!F$17 -> 0.16811261 | H17: ='Data Sheet'!G23/'Data Sheet'!G$17 -> 0.15566487 | I17: ='Data Sheet'!H23/'Data Sheet'!H$17 -> 0.14501486 | J17: ='Data Sheet'!I23/'Data Sheet'!I$17 -> 0.17416311 | ... L17: ='Data Sheet'!K23/'Data Sheet'!K$17 -> 0.16665633
B18: ='Data Sheet'!A24 -> Other Expenses | C18: ='Data Sheet'!B24/'Data Sheet'!B$17 -> 0.044327845 | D18: ='Data Sheet'!C24/'Data Sheet'!C$17 -> 0.041637361 | E18: ='Data Sheet'!D24/'Data Sheet'!D$17 -> 0.039506487 | F18: ='Data Sheet'!E24/'Data Sheet'!E$17 -> 0.042430184 | G18: ='Data Sheet'!F24/'Data Sheet'!F$17 -> 0.046674322 | H18: ='Data Sheet'!G24/'Data Sheet'!G$17 -> 0.044979598 | I18: ='Data Sheet'!H24/'Data Sheet'!H$17 -> 0.037421591 | J18: ='Data Sheet'!I24/'Data Sheet'!I$17 -> 0.045334109 | ... L18: ='Data Sheet'!K24/'Data Sheet'!K$17 -> 0.047325805
B19: ='Data Sheet'!A25 -> Other Income | C19: ='Data Sheet'!B25/'Data Sheet'!B$17 -> 0.018273928 | D19: ='Data Sheet'!C25/'Data Sheet'!C$17 -> 0.0099310733 | E19: ='Data Sheet'!D25/'Data Sheet'!D$17 -> 0.0081912999 | F19: ='Data Sheet'!E25/'Data Sheet'!E$17 -> 0.010657819 | G19: ='Data Sheet'!F25/'Data Sheet'!F$17 -> 0.0036148677 | H19: ='Data Sheet'!G25/'Data Sheet'!G$17 -> 0.0041757236 | I19: ='Data Sheet'!H25/'Data Sheet'!H$17 -> 0.0073951799 | J19: ='Data Sheet'!I25/'Data Sheet'!I$17 -> 0.013199561 | ... L19: ='Data Sheet'!K25/'Data Sheet'!K$17 -> 0.076363467
B20: ='Data Sheet'!A26 -> Depreciation | C20: ='Data Sheet'!B26/'Data Sheet'!B$17 -> 0.013026959 | D20: ='Data Sheet'!C26/'Data Sheet'!C$17 -> 0.014629343 | E20: ='Data Sheet'!D26/'Data Sheet'!D$17 -> 0.014372933 | F20: ='Data Sheet'!E26/'Data Sheet'!E$17 -> 0.025186638 | G20: ='Data Sheet'!F26/'Data Sheet'!F$17 -> 0.022837459 | H20: ='Data Sheet'!G26/'Data Sheet'!G$17 -> 0.020802349 | I20: ='Data Sheet'!H26/'Data Sheet'!H$17 -> 0.01876857 | J20: ='Data Sheet'!I26/'Data Sheet'!I$17 -> 0.019645858 | ... L20: ='Data Sheet'!K26/'Data Sheet'!K$17 -> 0.020676925
B21: ='Data Sheet'!A27 -> Interest | C21: ='Data Sheet'!B27/'Data Sheet'!B$17 -> 0.0010554249 | D21: ='Data Sheet'!C27/'Data Sheet'!C$17 -> 0.00073146715 | E21: ='Data Sheet'!D27/'Data Sheet'!D$17 -> 0.00083948105 | F21: ='Data Sheet'!E27/'Data Sheet'!E$17 -> 0.002966091 | G21: ='Data Sheet'!F27/'Data Sheet'!F$17 -> 0.0024878796 | H21: ='Data Sheet'!G27/'Data Sheet'!G$17 -> 0.0020211265 | I21: ='Data Sheet'!H27/'Data Sheet'!H$17 -> 0.0018818092 | J21: ='Data Sheet'!I27/'Data Sheet'!I$17 -> 0.0053961484 | ... L21: ='Data Sheet'!K27/'Data Sheet'!K$17 -> 0.0063597444
B22: ='Data Sheet'!A28 -> Profit before tax | C22: ='Data Sheet'!B28/'Data Sheet'!B$17 -> 0.19501236 | D22: ='Data Sheet'!C28/'Data Sheet'!C$17 -> 0.20554227 | E22: ='Data Sheet'!D28/'Data Sheet'!D$17 -> 0.2188756 | F22: ='Data Sheet'!E28/'Data Sheet'!E$17 -> 0.23037478 | G22: ='Data Sheet'!F28/'Data Sheet'!F$17 -> 0.22550396 | H22: ='Data Sheet'!G28/'Data Sheet'!G$17 -> 0.22649964 | I22: ='Data Sheet'!H28/'Data Sheet'!H$17 -> 0.22027072 | J22: ='Data Sheet'!I28/'Data Sheet'!I$17 -> 0.22499031 | ... L22: ='Data Sheet'!K28/'Data Sheet'!K$17 -> 0.28260532
... B25: ='Data Sheet'!A31 -> Dividend Amount | C25: ='Data Sheet'!B31/'Data Sheet'!B$17 -> 0.11072915 | D25: ='Data Sheet'!C31/'Data Sheet'!C$17 -> 0.12153608 | E25: ='Data Sheet'!D31/'Data Sheet'!D$17 -> 0.12088527 | F25: ='Data Sheet'!E31/'Data Sheet'!E$17 -> 0.13573637 | G25: ='Data Sheet'!F31/'Data Sheet'!F$17 -> 0.20237943 | H25: ='Data Sheet'!G31/'Data Sheet'!G$17 -> 0.15234718 | I25: ='Data Sheet'!H31/'Data Sheet'!H$17 -> 0.15128755 | J25: ='Data Sheet'!I31/'Data Sheet'!I$17 -> 0.15946103 | ... L25: ='Data Sheet'!K31/'Data Sheet'!K$17 -> 0.14945399
B26: ='Data Sheet'!A34 -> EBITDA | C26: ='Data Sheet'!B34/'Data Sheet'!B$17 -> 0.20867258 | D26: ='Data Sheet'!C34/'Data Sheet'!C$17 -> 0.22053735 | E26: ='Data Sheet'!D34/'Data Sheet'!D$17 -> 0.23393539 | F26: ='Data Sheet'!E34/'Data Sheet'!E$17 -> 0.25832642 | G26: ='Data Sheet'!F34/'Data Sheet'!F$17 -> 0.25074424 | H26: ='Data Sheet'!G34/'Data Sheet'!G$17 -> 0.24907524 | I26: ='Data Sheet'!H34/'Data Sheet'!H$17 -> 0.24054143 | J26: ='Data Sheet'!I34/'Data Sheet'!I$17 -> 0.24995153 | ... L26: ='Data Sheet'!K34/'Data Sheet'!K$17 -> 0.30934727
B29: ="Common Size Balance Sheet"&" "&"-"&'Data Sheet'!$B$1 -> Common Size Balance Sheet -HINDUSTAN UNILEVER LTD
B31: Particilars | C31: ='Data Sheet'!B56 -> 42825 | D31: ='Data Sheet'!C56 -> 43190 | E31: ='Data Sheet'!D56 -> 43555 | F31: ='Data Sheet'!E56 -> 43921 | G31: ='Data Sheet'!F56 -> 44286 | H31: ='Data Sheet'!G56 -> 44651 | I31: ='Data Sheet'!H56 -> 45016 | J31: ='Data Sheet'!I56 -> 45382 | ... L31: ='Data Sheet'!K56 -> 46112
B33: Total Liabilities | C33: ='Data Sheet'!B61/'Data Sheet'!B$61 -> 1 | D33: ='Data Sheet'!C61/'Data Sheet'!C$61 -> 1 | E33: ='Data Sheet'!D61/'Data Sheet'!D$61 -> 1 | F33: ='Data Sheet'!E61/'Data Sheet'!E$61 -> 1 | G33: ='Data Sheet'!F61/'Data Sheet'!F$61 -> 1 | H33: ='Data Sheet'!G61/'Data Sheet'!G$61 -> 1 | I33: ='Data Sheet'!H61/'Data Sheet'!H$61 -> 1 | J33: ='Data Sheet'!I61/'Data Sheet'!I$61 -> 1 | ... L33: ='Data Sheet'!K61/'Data Sheet'!K$61 -> 1
B34: ='Data Sheet'!A57 -> Equity Share Capital | C34: ='Data Sheet'!B57/'Data Sheet'!B$61 -> 0.013752706 | D34: ='Data Sheet'!C57/'Data Sheet'!C$61 -> 0.012092711 | E34: ='Data Sheet'!D57/'Data Sheet'!D$61 -> 0.011594825 | F34: ='Data Sheet'!E57/'Data Sheet'!E$61 -> 0.010718007 | G34: ='Data Sheet'!F57/'Data Sheet'!F$61 -> 0.0034186791 | H34: ='Data Sheet'!G57/'Data Sheet'!G$61 -> 0.0033330497 | I34: ='Data Sheet'!H57/'Data Sheet'!H$61 -> 0.0032157861 | J34: ='Data Sheet'!I57/'Data Sheet'!I$61 -> 0.0029940501 | ... L34: ='Data Sheet'!K57/'Data Sheet'!K$61 -> 0.0029471519
B35: ='Data Sheet'!A58 -> Reserves | C35: ='Data Sheet'!B58/'Data Sheet'!B$61 -> 0.41563734 | D35: ='Data Sheet'!C58/'Data Sheet'!C$61 -> 0.39553242 | E35: ='Data Sheet'!D58/'Data Sheet'!D$61 -> 0.41070374 | F35: ='Data Sheet'!E58/'Data Sheet'!E$61 -> 0.3976083 | G35: ='Data Sheet'!F58/'Data Sheet'!F$61 -> 0.6901222 | H35: ='Data Sheet'!G58/'Data Sheet'!G$61 -> 0.69250844 | I35: ='Data Sheet'!H58/'Data Sheet'!H$61 -> 0.68515402 | J35: ='Data Sheet'!I58/'Data Sheet'!I$61 -> 0.64955599 | ... L35: ='Data Sheet'!K58/'Data Sheet'!K$61 -> 0.60829216
B36: ='Data Sheet'!A59 -> Borrowings | C36: ='Data Sheet'!B59/'Data Sheet'!B$61 -> 0.017636572 | D36: ='Data Sheet'!C59/'Data Sheet'!C$61 -> 0 | E36: ='Data Sheet'!D59/'Data Sheet'!D$61 -> 0.0053142949 | F36: ='Data Sheet'!E59/'Data Sheet'!E$61 -> 0 | G36: ='Data Sheet'!F59/'Data Sheet'!F$61 -> 0 | H36: ='Data Sheet'!G59/'Data Sheet'!G$61 -> 0.014793067 | I36: ='Data Sheet'!H59/'Data Sheet'!H$61 -> 0.016681035 | J36: ='Data Sheet'!I59/'Data Sheet'!I$61 -> 0.018907108 | ... L36: ='Data Sheet'!K59/'Data Sheet'!K$61 -> 0.018535704
B37: ='Data Sheet'!A60 -> Other Liabilities | C37: ='Data Sheet'!B60/'Data Sheet'!B$61 -> 0.55297339 | D37: ='Data Sheet'!C60/'Data Sheet'!C$61 -> 0.59237487 | E37: ='Data Sheet'!D60/'Data Sheet'!D$61 -> 0.57238714 | F37: ='Data Sheet'!E60/'Data Sheet'!E$61 -> 0.5916737 | G37: ='Data Sheet'!F60/'Data Sheet'!F$61 -> 0.30645912 | H37: ='Data Sheet'!G60/'Data Sheet'!G$61 -> 0.28936544 | I37: ='Data Sheet'!H60/'Data Sheet'!H$61 -> 0.29494916 | J37: ='Data Sheet'!I60/'Data Sheet'!I$61 -> 0.32854285 | ... L37: ='Data Sheet'!K60/'Data Sheet'!K$61 -> 0.37022499
B39: Total Assset | C39: ='Data Sheet'!B75/'Data Sheet'!B$75 -> 1 | D39: ='Data Sheet'!C75/'Data Sheet'!C$75 -> 1 | E39: ='Data Sheet'!D75/'Data Sheet'!D$75 -> 1 | F39: ='Data Sheet'!E75/'Data Sheet'!E$75 -> 1 | G39: ='Data Sheet'!F75/'Data Sheet'!F$75 -> 1 | H39: ='Data Sheet'!G75/'Data Sheet'!G$75 -> 1 | I39: ='Data Sheet'!H75/'Data Sheet'!H$75 -> 1 | J39: ='Data Sheet'!I75/'Data Sheet'!I$75 -> 1 | ... L39: ='Data Sheet'!K75/'Data Sheet'!K$75 -> 1
B40: ='Data Sheet'!A62 -> Net Block | C40: ='Data Sheet'!B62/'Data Sheet'!B$75 -> 0.28135744 | D40: ='Data Sheet'!C62/'Data Sheet'!C$75 -> 0.25349905 | E40: ='Data Sheet'!D62/'Data Sheet'!D$75 -> 0.25310001 | F40: ='Data Sheet'!E62/'Data Sheet'!E$75 -> 0.27187019 | G40: ='Data Sheet'!F62/'Data Sheet'!F$75 -> 0.74837067 | H40: ='Data Sheet'!G62/'Data Sheet'!G$75 -> 0.73005134 | I40: ='Data Sheet'!H62/'Data Sheet'!H$75 -> 0.72085608 | J40: ='Data Sheet'!I62/'Data Sheet'!I$75 -> 0.68473289 | ... L40: ='Data Sheet'!K62/'Data Sheet'!K$75 -> 0.72020868
B41: ='Data Sheet'!A63 -> Capital Work in Progress | C41: ='Data Sheet'!B63/'Data Sheet'!B$75 -> 0.014580415 | D41: ='Data Sheet'!C63/'Data Sheet'!C$75 -> 0.02580898 | E41: ='Data Sheet'!D63/'Data Sheet'!D$75 -> 0.021793977 | F41: ='Data Sheet'!E63/'Data Sheet'!E$75 -> 0.029623381 | G41: ='Data Sheet'!F63/'Data Sheet'!F$75 -> 0.01083794 | H41: ='Data Sheet'!G63/'Data Sheet'!G$75 -> 0.018622529 | I41: ='Data Sheet'!H63/'Data Sheet'!H$75 -> 0.01549051 | J41: ='Data Sheet'!I63/'Data Sheet'!I$75 -> 0.013059155 | ... L41: ='Data Sheet'!K63/'Data Sheet'!K$75 -> 0.011036143
B42: ='Data Sheet'!A64 -> Investments | C42: ='Data Sheet'!B64/'Data Sheet'!B$75 -> 0.24156373 | D42: ='Data Sheet'!C64/'Data Sheet'!C$75 -> 0.16084425 | E42: ='Data Sheet'!D64/'Data Sheet'!D$75 -> 0.14579419 | F42: ='Data Sheet'!E64/'Data Sheet'!E$75 -> 0.062273607 | G42: ='Data Sheet'!F64/'Data Sheet'!F$75 -> 0.039409369 | H42: ='Data Sheet'!G64/'Data Sheet'!G$75 -> 0.049939012 | I42: ='Data Sheet'!H64/'Data Sheet'!H$75 -> 0.039437853 | J42: ='Data Sheet'!I64/'Data Sheet'!I$75 -> 0.058925455 | ... L42: ='Data Sheet'!K64/'Data Sheet'!K$75 -> 0.054666533
B43: ='Data Sheet'!A65 -> Other Assets | C43: ='Data Sheet'!B74/'Data Sheet'!B$75 -> 0.11524258 | D43: ='Data Sheet'!C74/'Data Sheet'!C$75 -> 0.15071101 | E43: ='Data Sheet'!D74/'Data Sheet'!D$75 -> 0.14198293 | F43: ='Data Sheet'!E74/'Data Sheet'!E$75 -> 0.18821019 | G43: ='Data Sheet'!F74/'Data Sheet'!F$75 -> 0.058699447 | H43: ='Data Sheet'!G74/'Data Sheet'!G$75 -> 0.057030607 | I43: ='Data Sheet'!H74/'Data Sheet'!H$75 -> 0.059895726 | J43: ='Data Sheet'!I74/'Data Sheet'!I$75 -> 0.057549466 | ... L43: ='Data Sheet'!K74/'Data Sheet'!K$75 -> 0.070919762
B44: ='Data Sheet'!A67 -> Receivables | C44: ='Data Sheet'!B67/'Data Sheet'!B$75 -> 0.06908188 | D44: ='Data Sheet'!C67/'Data Sheet'!C$75 -> 0.073340052 | E44: ='Data Sheet'!D67/'Data Sheet'!D$75 -> 0.09748242 | F44: ='Data Sheet'!E67/'Data Sheet'!E$75 -> 0.057013844 | G44: ='Data Sheet'!F67/'Data Sheet'!F$75 -> 0.025574629 | H44: ='Data Sheet'!G67/'Data Sheet'!G$75 -> 0.031713613 | I44: ='Data Sheet'!H67/'Data Sheet'!H$75 -> 0.04213364 | J44: ='Data Sheet'!I67/'Data Sheet'!I$75 -> 0.038183695 | ... L44: ='Data Sheet'!K67/'Data Sheet'!K$75 -> 0.042376282
B45: ='Data Sheet'!A68 -> Inventory | C45: ='Data Sheet'!B68/'Data Sheet'!B$75 -> 0.1617853 | D45: ='Data Sheet'!C68/'Data Sheet'!C$75 -> 0.14068973 | E45: ='Data Sheet'!D68/'Data Sheet'!D$75 -> 0.13817167 | F45: ='Data Sheet'!E68/'Data Sheet'!E$75 -> 0.13729966 | G45: ='Data Sheet'!F68/'Data Sheet'!F$75 -> 0.052065755 | H45: ='Data Sheet'!G68/'Data Sheet'!G$75 -> 0.058094347 | I45: ='Data Sheet'!H68/'Data Sheet'!H$75 -> 0.058171518 | J45: ='Data Sheet'!I68/'Data Sheet'!I$75 -> 0.051242849 | ... L45: ='Data Sheet'!K68/'Data Sheet'!K$75 -> 0.060059194
B46: ='Data Sheet'!A69 -> Cash & Bank | C46: ='Data Sheet'!B69/'Data Sheet'!B$75 -> 0.11638864 | D46: ='Data Sheet'!C69/'Data Sheet'!C$75 -> 0.19510693 | E46: ='Data Sheet'!D69/'Data Sheet'!D$75 -> 0.20167481 | F46: ='Data Sheet'!E69/'Data Sheet'!E$75 -> 0.25370913 | G46: ='Data Sheet'!F69/'Data Sheet'!F$75 -> 0.065042188 | H46: ='Data Sheet'!G69/'Data Sheet'!G$75 -> 0.054548549 | I46: ='Data Sheet'!H69/'Data Sheet'!H$75 -> 0.064014669 | J46: ='Data Sheet'!I69/'Data Sheet'!I$75 -> 0.096306489 | ... L46: ='Data Sheet'!K69/'Data Sheet'!K$75 -> 0.040733402

Sheet DCF>

Sheet WACC
B2: HINDUSTAN UNILEVER LTD
B3: (NSE: HINDUNILVR | BSE: 500696 )
B4: INR 1927.0
B5: 52 Week - (High- 2667.2 & Low- 1926.2)
B7: Weighted Average Cost of Capital
B9: All figures are in INR unless stated .
B11: Peer Comps
I12: Debt/ | J12: Debt/ | K12: Levered | L12: Unlevered
B13: Name of the company | E13: Country | F13: Total Debt | G13: Total Equity | H13: Tax Rate 1 | I13: Equity | J13: Capital | K13: Beta 2 | L13: Beta 3
B15: Hind. Unilever | E15: India | F15: ='Beta Comps'!F11 -> 1478 | G15: ='Beta Comps'!E11 -> 452766.24 | H15: 0.3 | I15: =F15/G15 -> 0.0032643777 | J15: =F15/(F15+G15) -> 0.0032537562 | K15: =Levered_Raw_Beta -> 0.55799676 | L15: =K15/(1+(1-H15)*I15) -> 0.55672461
B16: ITC | E16: India | F16: ='Beta Comps'!F12 -> 2399.06 | G16: ='Beta Comps'!E12 -> 325586.39 | H16: 0.3 | I16: =F16/G16 -> 0.0073684284 | J16: =F16/(F16+G16) -> 0.0073145318 | K16: 0.55 | L16: =K16/(1+(1-H16)*I16) -> 0.54717771
B17: Nestle India | E17: India | F17: ='Beta Comps'!F13 -> 444.16 | G17: ='Beta Comps'!E13 -> 266743.72 | H17: 0.3 | I17: =F17/G17 -> 0.0016651189 | J17: =F17/(F17+G17) -> 0.0016623509 | K17: 0.82 | L17: =K17/(1+(1-H17)*I17) -> 0.81904533
B18: Varun Beverages | E18: India | F18: ='Beta Comps'!F14 -> 2508.18 | G18: ='Beta Comps'!E14 -> 140879.66 | H18: 0.3 | I18: =F18/G18 -> 0.017803706 | J18: =F18/(F18+G18) -> 0.017492278 | K18: 1.06 | L18: =K18/(1+(1-H18)*I18) -> 1.0469523
B19: Britannia Inds. | E19: India | F19: ='Beta Comps'!F15 -> 1380.28 | G19: ='Beta Comps'!E15 -> 119518.85 | H19: 0.3 | I19: =F19/G19 -> 0.011548639 | J19: =F19/(F19+G19) -> 0.01141679 | K19: 0.52 | L19: =K19/(1+(1-H19)*I19) -> 0.51583001
G21: Average | H21: =AVERAGE(H15:H19) -> 0.3 | I21: =AVERAGE(I15:I19) -> 0.0083300538 | J21: =AVERAGE(J15:J19) -> 0.0082279415 | K21: =AVERAGE(K15:K19) -> 0.70159935 | L21: =AVERAGE(L15:L19) -> 0.69714598
G22: Median | H22: =MEDIAN(H15:H19) -> 0.3 | I22: =MEDIAN(I15:I19) -> 0.0073684284 | J22: =MEDIAN(J15:J19) -> 0.0073145318 | K22: =MEDIAN(K15:K19) -> 0.55799676 | L22: =MEDIAN(L15:L19) -> 0.55672461
B25: Cost of Debt | G25: Cost of Equity
B27: Pre-Tax Cost of Debt | E27: =HistoricalFS!M26/WACC!F15 -> 0.24560217 | G27: Risk Free Rate | H27: 0.07021
B28: Tax Rate | E28: =H22 -> 0.3 | G28: Equity Risk Premium | H28: =Rm!F16-WACC!H27 -> 0.081282308
B29: Post Tax Cost Of Debt | E29: =E27*(1-E28) -> 0.17192152 | G29: Levered Beta 4 | H29: =H38 -> 0.55959614
G30: Cost of Equity | H30: =H27+(H28*H29) -> 0.11569527
B33: Capital Structure | G33: Levered Beta
D35: Current | E35: Target | G35: Comps Median Unlevered Beta | H35: =L22 -> 0.55672461
B36: Total Debt | C36: =F15 -> 1478 | D36: =C36/$C$38 -> 0.0032537562 | E36: =J22 -> 0.0073145318 | G36: Target Debt/ Equity | H36: =E40 -> 0.0073684284
B37: Market Capilitalization | C37: =G15 -> 452766.24 | D37: =C37/$C$38 -> 0.99674624 | E37: =E38-E36 -> 0.99268547 | G37: Tax Rate | H37: =E28 -> 0.3
B38: Total Capital | C38: =SUM(C36:C37) -> 454244.24 | D38: =SUM(D36:D37) -> 1 | E38: =D38 -> 1 | G38: Levered Beta | H38: =H35*(1+(1-H37)*H36) -> 0.55959614
B40: Debt/ Equity | D40: =D36/D37 -> 0.0032643777 | E40: =E36/E37 -> 0.0073684284 | G40: Weighted Average Cost Of Capital
B42: Notes | G42: Cost of Equity | H42: =H30 -> 0.11569527
B43: 1. Tax Rate are considered as Marginal Tax Rate for the country | G43: Equity Weight | H43: =E37 -> 0.99268547
B44: 2. Levered Beta is based on 5 year monthly data
B45: 3. Unlevered Beta = Levered Beta /(1+(1- Tax Rate )* Debt / Equity) | G45: Cost of Debt | H45: =E29 -> 0.17192152
B46: 4. Levered Beta = Unlevered Beta * (1+(1- Tax Rate )* Debt / Equity) | G46: Debt Weight | H46: =E36 -> 0.0073145318
G48: WACC | H48: =(H42*H43)+(H45*H46) -> 0.11610653

Sheet Beta Regression
B2: HINDUSTAN UNILEVER LTD
B3: (NSE: HINDUNILVR | BSE: 500696 )
B4: INR 1927.0
B5: 52 Week - (High- 2667.2 & Low- 1926.2)
B7: Regression Beta Calculation - 2 years weekly
B9: Hindustan Unilever Limited Weekly Returns | F9: Nifty Weekly Returns | I9: Beta Drifting
B11: Date | C11: Closing Price | D11: Weekly Return | F11: Closing Price | G11: Weekly Return | I11: Levered Raw Beta | J11: =M14 -> 0.55799676 | L11: Beta 1 | M11: =SLOPE(D13:D117,G13:G117) -> 0.55799676
B12: 45544 | C12: 2818 | F12: 25356.5 | I12: Raw Beta Weight | J12: 0.75 | L12: Beta 2 | M12: =_xlfn.COVARIANCE.S(D12:D117,G12:G117)/_xlfn.VAR.S(G12:G117) -> 0.55799676
B13: 45551 | C13: 2860.9 | D13: =C13/C12-1 -> 0.015223563 | F13: 25790.95 | G13: =F13/F12-1 -> 0.017133674
B14: 45558 | C14: 2850 | D14: =C14/C13-1 -> -0.0038099899 | F14: 26178.95 | G14: =F14/F13-1 -> 0.015044037 | I14: Market Beta | J14: 1 | L14: Beta 3 | M14: =J37 -> 0.55799676
B15: 45565 | C15: 2737.1 | D15: =C15/C14-1 -> -0.039614035 | F15: 25014.6 | G15: =F15/F14-1 -> -0.044476574 | I15: Market Beta Weight | J15: 0.25
B16: 45572 | C16: 2674.12 | D16: =C16/C15-1 -> -0.023009755 | F16: 24964.25 | G16: =F16/F15-1 -> -0.0020128245
B17: 45579 | C17: 2610.61 | D17: =C17/C16-1 -> -0.023749869 | F17: 24854.05 | G17: =F17/F16-1 -> -0.0044143125 | I17: Adjusted Beta | J17: =(Levered_Raw_Beta*Raw_Beta_Weight)+(Market_Beta*Market_Beta_Weight) -> 0.66849757
B18: 45586 | C18: 2428.97 | D18: =C18/C17-1 -> -0.069577608 | F18: 24180.8 | G18: =F18/F17-1 -> -0.027088141
B19: 45593 | C19: 2438.05 | D19: =C19/C18-1 -> 0.00373821 | F19: 24304.35 | G19: =F19/F18-1 -> 0.0051094257
B20: 45600 | C20: 2437.45 | D20: =C20/C19-1 -> -0.00024609832 | F20: 24148.2 | G20: =F20/F19-1 -> -0.0064247758 | I20: SUMMARY OUTPUT
B21: 45607 | C21: 2322.27 | D21: =C21/C20-1 -> -0.047254303 | F21: 23532.7 | G21: =F21/F20-1 -> -0.025488442
B22: 45614 | C22: 2376.75 | D22: =C22/C21-1 -> 0.023459804 | F22: 23907.25 | G22: =F22/F21-1 -> 0.015916151 | I22: Regression Statistics
B23: 45621 | C23: 2426.23 | D23: =C23/C22-1 -> 0.020818344 | F23: 24131.1 | G23: =F23/F22-1 -> 0.0093632685 | I23: Multiple R | J23: 0.38670268
B24: 45628 | C24: 2414.22 | D24: =C24/C23-1 -> -0.0049500666 | F24: 24677.8 | G24: =F24/F23-1 -> 0.022655411 | I24: R Square | J24: 0.14953896
B25: 45635 | C25: 2323.15 | D25: =C25/C24-1 -> -0.037722329 | F25: 24768.3 | G25: =F25/F24-1 -> 0.0036672637 | I25: Adjusted R Square | J25: 0.14128206
B26: 45642 | C26: 2268.52 | D26: =C26/C25-1 -> -0.023515485 | F26: 23587.5 | G26: =F26/F25-1 -> -0.047673841 | I26: Standard Error | J26: 0.024584417
B27: 45649 | C27: 2275.67 | D27: =C27/C26-1 -> 0.0031518347 | F27: 23813.4 | G27: =F27/F26-1 -> 0.0095771065 | I27: Observations | J27: 105
B28: 45656 | C28: 2338.85 | D28: =C28/C27-1 -> 0.027763252 | F28: 24004.75 | G28: =F28/F27-1 -> 0.0080353918
B29: 45663 | C29: 2373.64 | D29: =C29/C28-1 -> 0.014874832 | F29: 23431.5 | G29: =F29/F28-1 -> -0.02388069 | I29: ANOVA
B30: 45670 | C30: 2288.06 | D30: =C30/C29-1 -> -0.03605433 | F30: 23203.2 | G30: =F30/F29-1 -> -0.0097432943 | J30: df | K30: SS | L30: MS | M30: F | N30: Significance F
B31: 45677 | C31: 2301.77 | D31: =C31/C30-1 -> 0.0059919757 | F31: 23092.2 | G31: =F31/F30-1 -> -0.0047838229 | I31: Regression | J31: 1 | K31: 0.010946039 | L31: 0.010946039 | M31: 18.110781 | N31: 4.6056216e-05
B32: 45684 | C32: 2435.85 | D32: =C32/C31-1 -> 0.058250824 | F32: 23482.15 | G32: =F32/F31-1 -> 0.016886654 | I32: Residual | J32: 103 | K32: 0.062252538 | L32: 0.00060439358
B33: 45691 | C33: 2297.63 | D33: =C33/C32-1 -> -0.056744052 | F33: 23559.95 | G33: =F33/F32-1 -> 0.0033131549 | I33: Total | J33: 104 | K33: 0.073198578
B34: 45698 | C34: 2253.41 | D34: =C34/C33-1 -> -0.019245919 | F34: 22929.25 | G34: =F34/F33-1 -> -0.026770006
B35: 45705 | C35: 2178.86 | D35: =C35/C34-1 -> -0.033083194 | F35: 22795.9 | G35: =F35/F34-1 -> -0.0058157157 | J35: Coefficients | K35: Standard Error | L35: t Stat | M35: P-value | N35: Lower 95% | O35: Upper 95% | P35: Lower 95.0% | Q35: Upper 95.0%
B36: 45712 | C36: 2128.9 | D36: =C36/C35-1 -> -0.022929422 | F36: 22124.7 | G36: =F36/F35-1 -> -0.029443891 | I36: Intercept | J36: -0.0028477327 | K36: 0.0024004118 | L36: -1.1863517 | M36: 0.23821274 | N36: -0.0076083834 | O36: 0.0019129179 | P36: -0.0076083834 | Q36: 0.0019129179
B37: 45719 | C37: 2142.8 | D37: =C37/C36-1 -> 0.0065291935 | F37: 22552.5 | G37: =F37/F36-1 -> 0.019335855 | I37: X Variable 1 | J37: 0.55799676 | K37: 0.13111824 | L37: 4.2556763 | M37: 4.6056216e-05 | N37: 0.29795467 | O37: 0.81803886 | P37: 0.29795467 | Q37: 0.81803886
B38: 45726 | C38: 2113.88 | D38: =C38/C37-1 -> -0.01349636 | F38: 22397.2 | G38: =F38/F37-1 -> -0.0068861545
B39: 45733 | C39: 2183.28 | D39: =C39/C38-1 -> 0.032830624 | F39: 23350.4 | G39: =F39/F38-1 -> 0.042558891
B40: 45740 | C40: 2195.58 | D40: =C40/C39-1 -> 0.0056337254 | F40: 23519.35 | G40: =F40/F39-1 -> 0.0072354221
B41: 45747 | C41: 2181.68 | D41: =C41/C40-1 -> -0.0063309012 | F41: 22904.45 | G41: =F41/F40-1 -> -0.02614443
B42: 45754 | C42: 2299.87 | D42: =C42/C41-1 -> 0.054173848 | F42: 22828.55 | G42: =F42/F41-1 -> -0.0033137665
B43: 45761 | C43: 2308.47 | D43: =C43/C42-1 -> 0.0037393418 | F43: 23851.65 | G43: =F43/F42-1 -> 0.044816688
B44: 45768 | C44: 2266.87 | D44: =C44/C43-1 -> -0.018020594 | F44: 24039.35 | G44: =F44/F43-1 -> 0.0078694765
B45: 45775 | C45: 2253.65 | D45: =C45/C44-1 -> -0.0058318298 | F45: 24346.7 | G45: =F45/F44-1 -> 0.012785287
B46: 45782 | C46: 2267.55 | D46: =C46/C45-1 -> 0.0061677723 | F46: 24008 | G46: =F46/F45-1 -> -0.013911536
B47: 45789 | C47: 2314.69 | D47: =C47/C46-1 -> 0.020788957 | F47: 25019.8 | G47: =F47/F46-1 -> 0.042144285
B48: 45796 | C48: 2293.11 | D48: =C48/C47-1 -> -0.0093230627 | F48: 24853.15 | G48: =F48/F47-1 -> -0.0066607247
B49: 45803 | C49: 2282.52 | D49: =C49/C48-1 -> -0.0046181823 | F49: 24750.7 | G49: =F49/F48-1 -> -0.0041222139
... B117: 46275 | C117: 1945.8 | D117: =C117/C116-1 -> 0.00041131105 | F117: 23434.05 | G117: =F117/F116-1 -> 0.00010882786

Sheet Beta Comps
B10: S.No. | C10: Company | D10: CMP Rs. | E10: Mar Cap Rs.Cr. | F10: Debt Rs.Cr. | G10: Debt / Eq
B11: 1 | C11: Hind. Unilever | D11: 1927 | E11: 452766.24 | F11: 1478 | G11: 0.03
B12: 2 | C12: ITC | D12: 259.85 | E12: 325586.39 | F12: 2399.06 | G12: 0.03
B13: 3 | C13: Nestle India | D13: 1383.3 | E13: 266743.72 | F13: 444.16 | G13: 0.08
B14: 4 | C14: Varun Beverages | D14: 416.5 | E14: 140879.66 | F14: 2508.18 | G14: 0.13
B15: 5 | C15: Britannia Inds. | D15: 4962 | E15: 119518.85 | F15: 1380.28 | G15: 0.27

Sheet Rm
B10: Return on Markets
B12: Year | C12: Annual
B13: 2000 | C13: -0.1465
B14: 2001 | C14: -0.1618 | E14: Average Return | F14: =AVERAGE(C13:C38) -> 0.15149231
B15: 2002 | C15: 0.0325 | E15: Dividend Yield | F15: 1.3% 1
B16: 2003 | C16: 0.719 | E16: Total Market Return | F16: =SUM(F14:F15) -> 0.15149231
B17: 2004 | C17: 0.1068
B18: 2005 | C18: 0.3634
B19: 2006 | C19: 0.3983
B20: 2007 | C20: 0.5477
B21: 2008 | C21: -0.5179
B22: 2009 | C22: 0.7576
B23: 2010 | C23: 0.1795
B24: 2011 | C24: -0.2462
B25: 2012 | C25: 0.277
B26: 2013 | C26: 0.0676
B27: 2014 | C27: 0.3139
B28: 2015 | C28: -0.0406
... B38: 2025 | C38: 0.1051

Sheet Intrinsic Growth
B2: HINDUSTAN UNILEVER LTD
B3: (NSE: HINDUNILVR | BSE: 500696 )
B4: INR 1927.0
B5: 52 Week - (High- 2667.2 & Low- 1926.2)
B7: Calculation of ROIC | G7: ='Raw FS'!K3 -> 44621 | H7: ='Raw FS'!L3 -> 44986 | I7: ='Raw FS'!M3 -> 45352 | J7: ='Raw FS'!N3 -> 45717 | K7: ='Raw FS'!O3 -> 46082
B9: Current Assets
B10: ='Raw FS'!C36 -> Inventories | G10: ='Raw FS'!K36 -> 4096 | H10: ='Raw FS'!L36 -> 4251 | I10: ='Raw FS'!M36 -> 4022 | J10: ='Raw FS'!N36 -> 4415 | K10: ='Raw FS'!O36 -> 4789
B11: ='Raw FS'!C37 -> Trade receivables | G11: ='Raw FS'!K37 -> 2236 | H11: ='Raw FS'!L37 -> 3079 | I11: ='Raw FS'!M37 -> 2997 | J11: ='Raw FS'!N37 -> 3819 | K11: ='Raw FS'!O37 -> 3379
B12: ='Raw FS'!C42 -> Loans n Advances | G12: ='Raw FS'!K42 -> 170 | H12: ='Raw FS'!L42 -> 188 | I12: ='Raw FS'!M42 -> 172 | J12: ='Raw FS'!N42 -> 619 | K12: ='Raw FS'!O42 -> 1024
B13: ='Raw FS'!C43 -> Other asset items | G13: ='Raw FS'!K43 -> 3851 | H13: ='Raw FS'!L43 -> 4189 | I13: ='Raw FS'!M43 -> 4345 | J13: ='Raw FS'!N43 -> 4302 | K13: ='Raw FS'!O43 -> 4631
B14: Total Current Assets | G14: =SUM(G10:G13) -> 10353 | H14: =SUM(H10:H13) -> 11707 | I14: =SUM(I10:I13) -> 11536 | J14: =SUM(J10:J13) -> 13155 | K14: =SUM(K10:K13) -> 13823
B16: Current Liabilities
B17: ='Raw FS'!C13 -> Trade Payables | G17: ='Raw FS'!K13 -> 9068 | H17: ='Raw FS'!L13 -> 9574 | I17: ='Raw FS'!M13 -> 10486 | J17: ='Raw FS'!N13 -> 11315 | K17: ='Raw FS'!O13 -> 13325
B18: ='Raw FS'!C14 -> Advance from Customers | G18: ='Raw FS'!K14 -> 119 | H18: ='Raw FS'!L14 -> 98 | I18: ='Raw FS'!M14 -> 91 | J18: ='Raw FS'!N14 -> 0 | K18: ='Raw FS'!O14 -> 0
B19: ='Raw FS'!C15 -> Other liability items | G19: ='Raw FS'!K15 -> 11189 | H19: ='Raw FS'!L15 -> 11664 | I19: ='Raw FS'!M15 -> 15005 | J19: ='Raw FS'!N15 -> 17291 | K19: ='Raw FS'!O15 -> 15927
B20: Total Current Liabilities | G20: =SUM(G17:G19) -> 20376 | H20: =SUM(H17:H19) -> 21336 | I20: =SUM(I17:I19) -> 25582 | J20: =SUM(J17:J19) -> 28606 | K20: =SUM(K17:K19) -> 29252
A22: # | B22: Net Working Capital | G22: =G14-G20 -> -10023 | H22: =H14-H20 -> -9629 | I22: =I14-I20 -> -14046 | J22: =J14-J20 -> -15451 | K22: =K14-K20 -> -15429
B25: Non Current Assets
B26: ='Raw FS'!C19 -> Land | G26: ='Raw FS'!K19 -> 477 | H26: ='Raw FS'!L19 -> 609 | I26: ='Raw FS'!M19 -> 633 | J26: ='Raw FS'!N19 -> 628 | K26: ='Raw FS'!O19 -> 636
B27: ='Raw FS'!C20 -> Building | G27: ='Raw FS'!K20 -> 2788 | H27: ='Raw FS'!L20 -> 3101 | I27: ='Raw FS'!M20 -> 3590 | J27: ='Raw FS'!N20 -> 3833 | K27: ='Raw FS'!O20 -> 4067
B28: ='Raw FS'!C21 -> Plant Machinery | G28: ='Raw FS'!K21 -> 6566 | H28: ='Raw FS'!L21 -> 7612 | I28: ='Raw FS'!M21 -> 8946 | J28: ='Raw FS'!N21 -> 9900 | K28: ='Raw FS'!O21 -> 9296
B29: ='Raw FS'!C22 -> Equipments | G29: ='Raw FS'!K22 -> 181 | H29: ='Raw FS'!L22 -> 185 | I29: ='Raw FS'!M22 -> 206 | J29: ='Raw FS'!N22 -> 245 | K29: ='Raw FS'!O22 -> 286
B30: ='Raw FS'!C23 -> Furniture n fittings | G30: ='Raw FS'!K23 -> 152 | H30: ='Raw FS'!L23 -> 161 | I30: ='Raw FS'!M23 -> 165 | J30: ='Raw FS'!N23 -> 174 | K30: ='Raw FS'!O23 -> 220
B31: ='Raw FS'!C25 -> Vehicles | G31: ='Raw FS'!K25 -> 0 | H31: ='Raw FS'!L25 -> 33 | I31: ='Raw FS'!M25 -> 39 | J31: ='Raw FS'!N25 -> 102 | K31: ='Raw FS'!O25 -> 103
B32: ='Raw FS'!C26 -> Intangible Assets | G32: ='Raw FS'!K26 -> 45262 | H32: ='Raw FS'!L26 -> 45692 | I32: ='Raw FS'!M26 -> 45692 | J32: ='Raw FS'!N26 -> 45692 | K32: ='Raw FS'!O26 -> 49195
B33: ='Raw FS'!C27 -> Other fixed assets | G33: ='Raw FS'!K27 -> 152 | H33: ='Raw FS'!L27 -> 171 | I33: ='Raw FS'!M27 -> 180 | J33: ='Raw FS'!N27 -> 190 | K33: ='Raw FS'!O27 -> 210
B34: Gross Block | G34: =SUM(G26:G33) -> 55578 | H34: =SUM(H26:H33) -> 57564 | I34: =SUM(I26:I33) -> 59451 | J34: =SUM(J26:J33) -> 60764 | K34: =SUM(K26:K33) -> 64013
B35: Accumulated Depreciation | G35: =-'Raw FS'!K29 -> -4105 | H35: =-'Raw FS'!L29 -> -4886 | I35: =-'Raw FS'!M29 -> -5707 | J35: =-'Raw FS'!N29 -> -6429 | K35: =-'Raw FS'!O29 -> -6585
A36: # | B36: Net Non Current Asset | G36: =SUM(G34:G35) -> 51473 | H36: =SUM(H34:H35) -> 52678 | I36: =SUM(I34:I35) -> 53744 | J36: =SUM(J34:J35) -> 54335 | K36: =SUM(K34:K35) -> 57428
A38: # | B38: Invested Capital | G38: =G36+G22 -> 41450 | H38: =H36+H22 -> 43049 | I38: =I36+I22 -> 39698 | J38: =J36+J22 -> 38884 | K38: =K36+K22 -> 41999
B39: EBIT | G39: =HistoricalFS!H32+HistoricalFS!H26 -> 11766 | H39: =HistoricalFS!I32+HistoricalFS!I26 -> 13010 | I39: =HistoricalFS!J32+HistoricalFS!J26 -> 13443 | J39: =HistoricalFS!K32+HistoricalFS!K26 -> 13445 | K39: =HistoricalFS!L32+HistoricalFS!L26 -> 13706
A41: # | B41: ROIC | G41: =G39/G38 -> 0.28386007 | H41: =H39/H38 -> 0.30221376 | I41: =I39/I38 -> 0.33863167 | J41: =J39/J38 -> 0.34577204 | K41: =K39/K38 -> 0.3263411
B44: Calculation of Reinvestment Rate | G44: ='Raw FS'!K3 -> 44621 | H44: ='Raw FS'!L3 -> 44986 | I44: ='Raw FS'!M3 -> 45352 | J44: ='Raw FS'!N3 -> 45717 | K44: ='Raw FS'!O3 -> 46082
B46: Net Capex | G46: =-SUM('Raw FS'!K62:K63) -> 1053 | H46: =-SUM('Raw FS'!L62:L63) -> 1011 | I46: =-SUM('Raw FS'!M62:M63) -> 1457 | J46: =-SUM('Raw FS'!N62:N63) -> 1262 | K46: =-SUM('Raw FS'!O62:O63) -> 1332
B47: Change in Working Capital | H47: =H22-G22 -> 394 | I47: =I22-H22 -> -4417 | J47: =J22-I22 -> -1405 | K47: =K22-J22 -> 22
B49: EBIT | G49: =G39 -> 11766 | H49: =H39 -> 13010 | I49: =I39 -> 13443 | J49: =J39 -> 13445 | K49: =K39 -> 13706
B50: Marginal Tax Rate | G50: 0.25 | H50: 0.25 | I50: 0.25 | J50: 0.25 | K50: 0.25
B51: EBIT(1-T) | G51: =G49*(1-G50) -> 8824.5 | H51: =H49*(1-H50) -> 9757.5 | I51: =I49*(1-I50) -> 10082.25 | J51: =J49*(1-J50) -> 10083.75 | K51: =K49*(1-K50) -> 10279.5
B53: Reinvestment | H53: =SUM(H46:H47) -> 1405 | I53: =SUM(I46:I47) -> -2960 | J53: =SUM(J46:J47) -> -143 | K53: =SUM(K46:K47) -> 1354
B54: Reinvestment Rate | H54: =H53/H51 -> 0.1439918 | I54: =I53/I51 -> -0.29358526 | J54: =J53/J51 -> -0.014181232 | K54: =K53/K51 -> 0.13171847
J56: 4 year average | K56: =AVERAGE(H54:K54) -> -0.0080140559
J57: 4 year median | K57: =MEDIAN(H54:K54) -> 0.058768618
B60: Calculation of Growth Rate | G60: ='Raw FS'!K3 -> 44621 | H60: ='Raw FS'!L3 -> 44986 | I60: ='Raw FS'!M3 -> 45352 | J60: ='Raw FS'!N3 -> 45717 | K60: ='Raw FS'!O3 -> 46082
B62: Reinvestment Rate | H62: =H54 -> 0.1439918 | I62: =I54 -> -0.29358526 | J62: =J54 -> -0.014181232 | K62: =K54 -> 0.13171847
B63: ROIC | H63: =H41 -> 0.30221376 | I63: =I41 -> 0.33863167 | J63: =J41 -> 0.34577204 | K63: =K41 -> 0.3263411
B64: Intrinsic Rate | H64: =H62*H63 -> 0.043516303 | I64: =I62*I63 -> -0.099417267 | J64: =J62*J63 -> -0.0049034736 | K64: =K62*K63 -> 0.04298515
J66: 4 year average | K66: =AVERAGE(H64:K64) -> -0.0044548218
J67: 4 year median | K67: =MEDIAN(H64:K64) -> 0.019040838

Sheet DCF
B2: HINDUSTAN UNILEVER LTD
B3: (NSE: HINDUNILVR | BSE: 500696 )
B4: INR 1927.0
B5: 52 Week - (High- 2667.2 & Low- 1926.2)
B7: Calculation of PV of FCFF | E7: ='Intrinsic Growth'!K7 -> 46082 | F7: =E7+366 -> 46448 | G7: =F7+366 -> 46814 | H7: =G7+366 -> 47180 | I7: =H7+366 -> 47546 | J7: =I7+366 -> 47912
B9: EBIT | E9: ='Data Sheet'!K34-'Data Sheet'!K26 -> 18610 | F9: =E9*(1+$E$19) -> 18964.35 | G9: =F9*(1+$E$19) -> 19325.447 | H9: =G9*(1+$E$19) -> 19693.42 | I9: =H9*(1+$E$19) -> 20068.399 | J9: =I9*(1+$E$19) -> 20450.518
B10: Tax Rate | E10: 0.25 | F10: 0.25 | G10: 0.25 | H10: 0.25 | I10: 0.25 | J10: 0.25
B11: EBIT(1-T) | E11: =E9*(1-E10) -> 13957.5 | F11: =E11*(1+$E$19) -> 14223.263 | G11: =F11*(1+$E$19) -> 14494.085 | H11: =G11*(1+$E$19) -> 14770.065 | I11: =H11*(1+$E$19) -> 15051.299 | J11: =I11*(1+$E$19) -> 15337.889
B12: Less: Reinvestment Rate | E12: ='Intrinsic Growth'!K57 -> 0.058768618 | F12: =E12+(($J$12-E12)/4) -> 0.093901464 | G12: =F12+(($J$12-F12)/4) -> 0.1202511 | H12: =G12+(($J$12-G12)/4) -> 0.14001332 | I12: =H12+(($J$12-H12)/4) -> 0.15483499 | J12: 0.1993
B13: Free Cash Flow to Firm (FCFF) | E13: =E11*(1-E12) -> 13137.237 | F13: =E13*(1+$E$19) -> 13387.381 | G13: =F13*(1+$E$19) -> 13642.288 | H13: =G13*(1+$E$19) -> 13902.049 | I13: =H13*(1+$E$19) -> 14166.755 | J13: =I13*(1+$E$19) -> 14436.502
B14: Mid Year Convention | F14: 0.5 | G14: =1+F14 -> 1.5 | H14: =1+G14 -> 2.5 | I14: =1+H14 -> 3.5 | J14: =1+I14 -> 4.5
B15: Discounting Factor | F15: =1/(1+$E$21)^F14 -> 0.94655788 | G15: =1/(1+$E$21)^G14 -> 0.84808918 | H15: =1/(1+$E$21)^H14 -> 0.75986401 | I15: =1/(1+$E$21)^I14 -> 0.68081673 | J15: =1/(1+$E$21)^J14 -> 0.60999261
B17: PV of FCFF | F17: =F13*F15 -> 12671.931 | G17: =G13*G15 -> 11569.877 | H17: =H13*H15 -> 10563.666 | I17: =I13*I15 -> 9644.964 | J17: =J13*J15 -> 8806.1596
B19: Expected Growth | E19: ='Intrinsic Growth'!K67 -> 0.019040838
B20: Terminal Growth | E20: 0.06
B21: WACC | E21: =WACC!H48 -> 0.11610653
B25: Calculation of Terminal Value | F25: Sensitivity Analysis
F26: =D43 -> 921.49308 | G26: 0.1 | H26: 0.1161 | I26: 0.12 | J26: 0.13
B27: FCFF(N+1) | D27: =J13*(1+E19) -> 14711.385 | F27: 0.04 | G27: 877.30659 | H27: 742.59411 | I27: 718.11995 | J27: 665.05774
B28: WACC | D28: =E21 -> 0.11610653 | F28: 0.055 | G28: 1089.5554 | H28: 865.84307 | I28: 828.32609 | J28: 749.95728
B29: Terminal Growth Rate | D29: =E20 -> 0.06 | F29: 0.06 | G29: 1195.6799 | H29: 921.57239 | I29: 877.30659 | J29: 786.3428
F30: 0.078 | G30: 1977.1415 | H30: 1243.3105 | I30: 1150.198 | J30: 975.2676
B31: Terminal Value | D31: =D27/(D28-D29) -> 262204.49 | F31: 0.09 | G31: 4061.0393 | H31: 1704.3452 | I31: 1514.0531 | J31: 1195.6799
B34: Calculation of Equity Value
B35: FCFF(N+1) | D35: =SUM(F17:J17) -> 53256.598
B36: PV of Terminal Value | D36: =D31*J15 -> 159942.8
B37: Value Of Operating Assets | D37: =SUM(D35:D36) -> 213199.4
B39: Add: Cash | D39: ='Data Sheet'!K69 -> 3248
B40: Less: Debt | D40: =SUM('Raw FS'!O8:O9) -> 0
B41: Value Of Equity | D41: =D37+D39-D40 -> 216447.4
B42: No. Of Shares | D42: ='Data Sheet'!B6 -> 234.88771
B43: Equity Value Per Share | D43: =D41/D42 -> 921.49308
B45: Share Price | D45: 1927
B46: Discount/Premium | D46: =D45/D43 -> 2.0911714

Sheet Relative Valuation
B2: HINDUSTAN UNILEVER LTD
B3: (NSE: HINDUNILVR | BSE: 500696 )
B4: INR 1927.0
B5: 52 Week - (High- 2667.2 & Low- 1926.2)
B7: Amount in crores
B8: Comparable Company Valuation
D10: Market Data | K10: Financials | O10: Valuation
B11: Company | C11: Ticker | D11: Share Price | E11: Share Outstanding | F11: Equity Value | G11: Net Debt | H11: Enterprise Value | K11: Revenue | L11: EBITDA | M11: Net Income | O11: EV/REVENUE | P11: EV/EBITDA | Q11: P/E
B13: =Data!C3 -> Hind. Unilever | C13: HINDUNILVR | D13: =Data!D3 -> 1927 | E13: =Data!E3 -> 234.96 | F13: =Data!F3 -> 452767.92 | G13: =Data!I3 -> -1770 | H13: =F13+G13 -> 450997.92 | K13: =Data!K3 -> 66052 | L13: =Data!L3 -> 16084.091 | M13: =Data!M3 -> 14971 | O13: =$H13/K13 -> 6.8279222 | P13: =$H13/L13 -> 28.04 | Q13: =F13/M13 -> 30.242998
B14: =Data!C4 -> ITC | C14: ITC | D14: =Data!D4 -> 259.85 | E14: =Data!E4 -> 1252.98 | F14: =Data!F4 -> 325586.85 | G14: =Data!I4 -> -609.73 | H14: =F14+G14 -> 324977.12 | K14: =Data!K4 -> 76487.98 | L14: =Data!L4 -> 28481.781 | M14: =Data!M4 -> 20183.53 | O14: =$H14/K14 -> 4.2487345 | P14: =$H14/L14 -> 11.41 | Q14: =F14/M14 -> 16.131314
B15: =Data!C5 -> Nestle India | C15: NESTLEIND | D15: =Data!D5 -> 1383.3 | E15: =Data!E5 -> 192.83 | F15: =Data!F5 -> 266741.74 | G15: =Data!I5 -> -896.71 | H15: =F15+G15 -> 265845.03 | K15: =Data!K5 -> 24436.62 | L15: =Data!L5 -> 5803.2095 | M15: =Data!M5 -> 3860.49 | O15: =$H15/K15 -> 10.878961 | P15: =$H15/L15 -> 45.81 | Q15: =F15/M15 -> 69.095306
B16: =Data!C6 -> Varun Beverages | C16: VBL | D16: =Data!D6 -> 416.5 | E16: =Data!E6 -> 338.25 | F16: =Data!F6 -> 140881.12 | G16: =Data!I6 -> 509.69 | H16: =F16+G16 -> 141390.82 | K16: =Data!K6 -> 24126.49 | L16: =Data!L6 -> 6042.3425 | M16: =Data!M6 -> 3409.28 | O16: =$H16/K16 -> 5.8603972 | P16: =$H16/L16 -> 23.4 | Q16: =F16/M16 -> 41.322838
B17: =Data!C7 -> Britannia Inds. | C17: BRITANNIA | D17: =Data!D7 -> 4962 | E17: =Data!E7 -> 24.09 | F17: =Data!F7 -> 119534.58 | G17: =Data!I7 -> 1027.84 | H17: =F17+G17 -> 120562.42 | K17: =Data!K7 -> 19529.34 | L17: =Data!L7 -> 3829.81 | M17: =Data!M7 -> 2610.26 | O17: =$H17/K17 -> 6.1733996 | P17: =$H17/L17 -> 31.48 | Q17: =F17/M17 -> 45.794128
B18: =Data!C8 -> Marico | C18: MARICO | D18: =Data!D8 -> 802.1 | E18: =Data!E8 -> 130.02 | F18: =Data!F8 -> 104289.04 | G18: =Data!I8 -> 64 | H18: =F18+G18 -> 104353.04 | K18: =Data!K8 -> 14277 | L18: =Data!L8 -> 2688.1258 | M18: =Data!M8 -> 1952 | O18: =$H18/K18 -> 7.3091715 | P18: =$H18/L18 -> 38.82 | Q18: =F18/M18 -> 53.426763
B19: =Data!C9 -> United Spirits | C19: UNITDSPR | D19: =Data!D9 -> 1395 | E19: =Data!E9 -> 72.74 | F19: =Data!F9 -> 101472.3 | G19: =Data!I9 -> -1564 | H19: =F19+G19 -> 99908.3 | K19: =Data!K9 -> 12626 | L19: =Data!L9 -> 2789.1764 | M19: =Data!M9 -> 1884 | O19: =$H19/K19 -> 7.9129019 | P19: =$H19/L19 -> 35.82 | Q19: =F19/M19 -> 53.860032
B20: =Data!C10 -> Tata Consumer | C20: TATACONSUM | D20: =Data!D10 -> 991 | E20: =Data!E10 -> 98.97 | F20: =Data!F10 -> 98079.27 | G20: =Data!I10 -> -600.98 | H20: =F20+G20 -> 97478.29 | K20: =Data!K10 -> 20860.4 | L20: =Data!L10 -> 3104.4041 | M20: =Data!M10 -> 1642.24 | O20: =$H20/K20 -> 4.6728869 | P20: =$H20/L20 -> 31.4 | Q20: =F20/M20 -> 59.72286
B21: =Data!C11 -> Godrej Consumer | C21: GODREJCP | D21: =Data!D11 -> 865 | E21: =Data!E11 -> 102.33 | F21: =Data!F11 -> 88515.45 | G21: =Data!I11 -> 3415.11 | H21: =F21+G21 -> 91930.56 | K21: =Data!K11 -> 15948.95 | L21: =Data!L11 -> 3496.7881 | M21: =Data!M11 -> 1913.54 | O21: =$H21/K21 -> 5.7640509 | P21: =$H21/L21 -> 26.29 | Q21: =F21/M21 -> 46.257434
B22: =Data!C12 -> Dabur India | C22: DABUR | D22: =Data!D12 -> 376 | E22: =Data!E12 -> 177.4 | F22: =Data!F12 -> 66702.4 | G22: =Data!I12 -> 725.25 | H22: =F22+G22 -> 67427.65 | K22: =Data!K12 -> 13552.38 | L22: =Data!L12 -> 3152.2978 | M22: =Data!M12 -> 1946.56 | O22: =$H22/K22 -> 4.9753364 | P22: =$H22/L22 -> 21.39 | Q22: =F22/M22 -> 34.266809
B25: High | O25: =MAX(O13:O22) -> 10.878961 | P25: =MAX(P13:P22) -> 45.81 | Q25: =MAX(Q13:Q22) -> 69.095306
B26: 75th Percentile | O26: =QUARTILE(O13:O22,3) -> 7.1888592 | P26: =QUARTILE(P13:P22,3) -> 34.735 | Q26: =QUARTILE(Q13:Q22,3) -> 53.751715
B27: Average | O27: =AVERAGE(O13:O22) -> 6.4623762 | P27: =AVERAGE(P13:P22) -> 29.386 | Q27: =AVERAGE(Q13:Q22) -> 45.012048
B28: Median | O28: =MEDIAN(O13:O22) -> 6.0168984 | P28: =MEDIAN(P13:P22) -> 29.72 | Q28: =MEDIAN(Q13:Q22) -> 46.025781
B29: 25th Percentile | O29: =QUARTILE(O13:O22,1) -> 5.1725151 | P29: =QUARTILE(P13:P22,1) -> 24.1225 | Q29: =QUARTILE(Q13:Q22,1) -> 36.030816
B30: Low | O30: =MIN(O13:O22) -> 4.2487345 | P30: =MIN(P13:P22) -> 11.41 | Q30: =MIN(Q13:Q22) -> 16.131314
B32: Hindustan Unilever Ltd Comparable Valuation | O32: EV/REVENUE | P32: EV/EBITDA | Q32: P/E
B34: Implied Enterprise Value | O34: =O$28*K13 -> 397428.17 | P34: =P$28*L13 -> 478019.19 | Q34: =Q36+Q35 -> 687281.96
B35: Nebt Debt | O35: =$G$13 -> -1770 | P35: =$G$13 -> -1770 | Q35: =$G$13 -> -1770
B36: Implied Market Value | O36: =O34-O35 -> 399198.17 | P36: =P34-P35 -> 479789.19 | Q36: =Q28*M13 -> 689051.96
B37: Share Outstanding | O37: =$E$13 -> 234.96 | P37: =$E$13 -> 234.96 | Q37: =$E$13 -> 234.96
B38: Implied Value per Share | O38: =O36/O37 -> 1699.0048 | P38: =P36/P37 -> 2042.0037 | Q38: =Q36/Q37 -> 2932.6352
B40: Source: Screener.in
O41: =IF(O38>$D$13, "Undervalued", "Overvalued") -> Overvalued | P41: =IF(P38>$D$13, "Undervalued", "Overvalued") -> Undervalued | Q41: =IF(Q38>$D$13, "Undervalued", "Overvalued") -> Undervalued

Sheet Football Field
B2: HINDUSTAN UNILEVER LTD
B3: (NSE: HINDUNILVR | BSE: 500696 )
B4: INR 1927.0
B5: 52 Week - (High- 2667.2 & Low- 1926.2)
B24: Football Field Analysis
C25: OpenLow | D25: Low | E25: OpenHigh | F25: High
B26: Comps | C26: 1699.0048 | D26: 1699.0048 | E26: 2932.6352 | F26: 2932.6352
B27: DCF Bear | C27: 665.05774 | D27: 665.05774 | E27: 1195.6799 | F27: 1195.6799
B28: DCF Base | C28: 742.59411 | D28: 742.59411 | E28: 1704.3452 | F28: 1704.3452
B29: DCF Bull | C29: 877.30659 | D29: 877.30659 | E29: 4061.0393 | F29: 4061.0393
B30: 52W H/L | C30: 1926.2 | D30: 1926.2 | E30: 2667.2 | F30: 2667.2

Sheet Historical Approach
B2: HINDUSTAN UNILEVER LTD
B3: (NSE: HINDUNILVR | BSE: 500696 )
B4: INR 1927.0
B5: 52 Week - (High- 2667.2 & Low- 1926.2)
A8: # | B8: Date | C8: Adjusted price | D8: Return | E8: Sorted Return | G8: Calculation of Value at Risk - HUL (Historical Approach)
B9: 35582 | C9: 118.9 | D9: =(C9-C10)/C10 -> -0.75317612 | E9: 0.29775158
B10: 41365 | C10: 481.72 | D10: =(C10-C11)/C11 -> 1.3955443 | E10: 0.25024656 | G10: Mean | K10: =AVERAGE(E9:E376) -> 0.012539886
B11: 38749 | C11: 201.09 | D11: =(C11-C12)/C12 -> 0.075922953 | E11: 0.24815344 | G11: STD. Deviation | K11: =_xlfn.STDEV.S(E9:E376) -> 0.074874624
B12: 36220 | C12: 186.9 | D12: =(C12-C13)/C13 -> -0.75711185 | E12: 0.23602936 | G12: Min | K12: =MIN(E9:E376) -> -0.19653806
B13: 42005 | C13: 769.49 | D13: =(C13-C14)/C14 -> -0.68272902 | E13: 0.22688499 | G13: Max | K13: =MAX(E9:E376) -> 0.29775158
B14: 44743 | C14: 2425.34 | D14: =(C14-C15)/C15 -> 25.669672 | E14: 0.18237172 | G14: CMP | K14: 1927
B15: 35521 | C15: 90.94 | D15: =(C15-C16)/C16 -> -0.61521537 | E15: 0.18011939
B16: 36557 | C16: 236.34 | D16: =(C16-C17)/C17 -> -0.073212815 | E16: 0.1738353 | G16: Percentile | H16: Confidence | I16: VAR % | J16: Stock Price | K16: VAR (INR)
B17: 40422 | C17: 255.01 | D17: =(C17-C18)/C18 -> -0.89667258 | E17: 0.1684307 | G17: 0.05 | H17: =100%-G17 -> 0.95 | I17: =_xlfn.PERCENTILE.INC($E$9:$E$376,G17) -> -0.099898156 | J17: =$K$14*(1-I17) -> 2119.5037 | K17: =$K$14-J17 -> -192.50375
B18: 44409 | C18: 2467.98 | D18: =(C18-C19)/C19 -> 14.402734 | E18: 0.16748978 | G18: 0.01 | H18: =100%-G18 -> 0.99 | I18: =_xlfn.PERCENTILE.INC($E$9:$E$376,G18) -> -0.1484996 | J18: =$K$14*(1-I18) -> 2213.1587 | K18: =$K$14-J18 -> -286.15874
B19: 36161 | C19: 160.23 | D19: =(C19-C20)/C20 -> -0.05368533 | E19: 0.16615721 | G19: 0.005 | H19: =100%-G19 -> 0.995 | I19: =_xlfn.PERCENTILE.INC($E$9:$E$376,G19) -> -0.15396889 | J19: =$K$14*(1-I19) -> 2223.6981 | K19: =$K$14-J19 -> -296.69805
B20: 39142 | C20: 169.32 | D20: =(C20-C21)/C21 -> -0.23290898 | E20: 0.16363137 | G20: 0.1 | H20: =100%-G20 -> 0.9 | I20: =_xlfn.PERCENTILE.INC($E$9:$E$376,G20) -> -0.071616609 | J20: =$K$14*(1-I20) -> 2065.0052 | K20: =$K$14-J20 -> -138.00521
B21: 39965 | C21: 220.73 | D21: =(C21-C22)/C22 -> 0.84989943 | E21: 0.15905272
B22: 38292 | C22: 119.32 | D22: =(C22-C23)/C23 -> -0.39661188 | E22: 0.15867159
B23: 39630 | C23: 197.75 | D23: =(C23-C24)/C24 -> 0.17219917 | E23: 0.15690634
B24: 37956 | C24: 168.7 | D24: =(C24-C25)/C25 -> -0.25112088 | E24: 0.14699483
B25: 36342 | C25: 225.27 | D25: =(C25-C26)/C26 -> 0.66422872 | E25: 0.14658727
B26: 38504 | C26: 135.36 | D26: =(C26-C27)/C27 -> -0.32770438 | E26: 0.14517766
B27: 36526 | C27: 201.34 | D27: =(C27-C28)/C28 -> -0.77756419 | E27: 0.14203063
B28: 42856 | C28: 905.16 | D28: =(C28-C29)/C29 -> -0.58612932 | E28: 0.1412361
B29: 44256 | C29: 2187.06 | D29: =(C29-C30)/C30 -> 16.264446 | E29: 0.14044803
B30: 35827 | C30: 126.68 | D30: =(C30-C31)/C31 -> -0.097399359 | E30: 0.13900378
B31: 35977 | C31: 140.35 | D31: =(C31-C32)/C32 -> -0.89203348 | E31: 0.13423307
B32: 43191 | C32: 1299.94 | D32: =(C32-C33)/C33 -> 7.8557804 | E32: 0.13166188
... B376: 38838 | C376: 192.63 | D376: =(C376-C377)/C377 -> #DIV/0! | E376: -0.19653806

Sheet Monte Carlo
B2: HINDUSTAN UNILEVER LTD
B3: (NSE: HINDUNILVR | BSE: 500696 )
B4: INR 1927.0
B5: 52 Week - (High- 2667.2 & Low- 1926.2)
A7: # | B7: Date | C7: Adjusted price | D7: Return | E7: Sorted Return | G7: Replication | H7: Simulated Return | I7: Calculation of Value at Risk - HUL (Simulation)
B8: 35582 | C8: 118.9 | D8: =(C8-C9)/C9 -> -0.75317612 | E8: 0.29775158 | G8: 1 | H8: =_xlfn.NORM.INV(RAND(),M$10,M$11) -> -0.10527362
B9: 41365 | C9: 481.72 | D9: =(C9-C10)/C10 -> 1.3955443 | E9: 0.25024656 | G9: 2 | H9: =_xlfn.NORM.INV(RAND(),M$10,M$11) -> 0.07675901 | I9: Historical Approach
B10: 38749 | C10: 201.09 | D10: =(C10-C11)/C11 -> 0.075922953 | E10: 0.24815344 | G10: 3 | H10: =_xlfn.NORM.INV(RAND(),M$10,M$11) -> 0.021967062 | I10: Mean | M10: =AVERAGE(E8:E375) -> 0.012539886
B11: 36220 | C11: 186.9 | D11: =(C11-C12)/C12 -> -0.75711185 | E11: 0.23602936 | G11: 4 | H11: =_xlfn.NORM.INV(RAND(),M$10,M$11) -> -0.063176837 | I11: STD. Deviation | M11: =_xlfn.STDEV.S(E8:E375) -> 0.074874624
B12: 42005 | C12: 769.49 | D12: =(C12-C13)/C13 -> -0.68272902 | E12: 0.22688499 | G12: 5 | H12: =_xlfn.NORM.INV(RAND(),M$10,M$11) -> -0.039642302 | I12: Min | M12: =MIN(E8:E375) -> -0.19653806
B13: 44743 | C13: 2425.34 | D13: =(C13-C14)/C14 -> 25.669672 | E13: 0.18237172 | G13: 6 | H13: =_xlfn.NORM.INV(RAND(),M$10,M$11) -> 0.085628565 | I13: Max | M13: =MAX(E8:E375) -> 0.29775158
B14: 35521 | C14: 90.94 | D14: =(C14-C15)/C15 -> -0.61521537 | E14: 0.18011939 | G14: 7 | H14: =_xlfn.NORM.INV(RAND(),M$10,M$11) -> -0.06919625 | I14: CMP | M14: 1927
B15: 36557 | C15: 236.34 | D15: =(C15-C16)/C16 -> -0.073212815 | E15: 0.1738353 | G15: 8 | H15: =_xlfn.NORM.INV(RAND(),M$10,M$11) -> 0.058522963
B16: 40422 | C16: 255.01 | D16: =(C16-C17)/C17 -> -0.89667258 | E16: 0.1684307 | G16: 9 | H16: =_xlfn.NORM.INV(RAND(),M$10,M$11) -> -0.0024429956 | I16: Monte Carlo Simulation
B17: 44409 | C17: 2467.98 | D17: =(C17-C18)/C18 -> 14.402734 | E17: 0.16748978 | G17: 10 | H17: =_xlfn.NORM.INV(RAND(),M$10,M$11) -> 0.022537406 | I17: Mean | M17: =AVERAGE(H8:H10007) -> 0.011077691
B18: 36161 | C18: 160.23 | D18: =(C18-C19)/C19 -> -0.05368533 | E18: 0.16615721 | G18: 11 | H18: =_xlfn.NORM.INV(RAND(),M$10,M$11) -> -0.17903702 | I18: STD. Deviation | M18: =_xlfn.STDEV.S(H8:H10007) -> 0.074388882
B19: 39142 | C19: 169.32 | D19: =(C19-C20)/C20 -> -0.23290898 | E19: 0.16363137 | G19: 12 | H19: =_xlfn.NORM.INV(RAND(),M$10,M$11) -> 0.11753005 | I19: Min | M19: =MIN(H8:H10007) -> -0.26243465
B20: 39965 | C20: 220.73 | D20: =(C20-C21)/C21 -> 0.84989943 | E20: 0.15905272 | G20: 13 | H20: =_xlfn.NORM.INV(RAND(),M$10,M$11) -> 0.025987439 | I20: Max | M20: =MAX(H8:H10007) -> 0.32165114
B21: 38292 | C21: 119.32 | D21: =(C21-C22)/C22 -> -0.39661188 | E21: 0.15867159 | G21: 14 | H21: =_xlfn.NORM.INV(RAND(),M$10,M$11) -> 0.1047087 | I21: CMP | M21: 1927
B22: 39630 | C22: 197.75 | D22: =(C22-C23)/C23 -> 0.17219917 | E22: 0.15690634 | G22: 15 | H22: =_xlfn.NORM.INV(RAND(),M$10,M$11) -> -0.042605129
B23: 37956 | C23: 168.7 | D23: =(C23-C24)/C24 -> -0.25112088 | E23: 0.14699483 | G23: 16 | H23: =_xlfn.NORM.INV(RAND(),M$10,M$11) -> 0.034371379 | I23: Percentile | J23: Confidence | K23: VAR % | L23: Stock Price | M23: VAR (INR)
B24: 36342 | C24: 225.27 | D24: =(C24-C25)/C25 -> 0.66422872 | E24: 0.14658727 | G24: 17 | H24: =_xlfn.NORM.INV(RAND(),M$10,M$11) -> 0.11442649 | I24: 0.05 | J24: =100%-I24 -> 0.95 | K24: =_xlfn.PERCENTILE.INC($H$8:$H$10007,I24) -> -0.11139199 | L24: =$M$14*(1-K24) -> 2141.6524 | M24: =$M$14-L24 -> -214.65237
B25: 38504 | C25: 135.36 | D25: =(C25-C26)/C26 -> -0.32770438 | E25: 0.14517766 | G25: 18 | H25: =_xlfn.NORM.INV(RAND(),M$10,M$11) -> 0.029351261 | I25: 0.01 | J25: =100%-I25 -> 0.99 | K25: =_xlfn.PERCENTILE.INC($H$8:$H$10007,I25) -> -0.16130241 | L25: =$M$14*(1-K25) -> 2237.8298 | M25: =$M$14-L25 -> -310.82975
B26: 36526 | C26: 201.34 | D26: =(C26-C27)/C27 -> -0.77756419 | E26: 0.14203063 | G26: 19 | H26: =_xlfn.NORM.INV(RAND(),M$10,M$11) -> 0.11090199 | I26: 0.005 | J26: =100%-I26 -> 0.995 | K26: =_xlfn.PERCENTILE.INC($H$8:$H$10007,I26) -> -0.182194 | L26: =$M$14*(1-K26) -> 2278.0878 | M26: =$M$14-L26 -> -351.08784
B27: 42856 | C27: 905.16 | D27: =(C27-C28)/C28 -> -0.58612932 | E27: 0.1412361 | G27: 20 | H27: =_xlfn.NORM.INV(RAND(),M$10,M$11) -> 0.001752574 | I27: 0.1 | J27: =100%-I27 -> 0.9 | K27: =_xlfn.PERCENTILE.INC($H$8:$H$10007,I27) -> -0.084493404 | L27: =$M$14*(1-K27) -> 2089.8188 | M27: =$M$14-L27 -> -162.81879
B28: 44256 | C28: 2187.06 | D28: =(C28-C29)/C29 -> 16.264446 | E28: 0.14044803 | G28: 21 | H28: =_xlfn.NORM.INV(RAND(),M$10,M$11) -> -0.0065259278
B29: 35827 | C29: 126.68 | D29: =(C29-C30)/C30 -> -0.097399359 | E29: 0.13900378 | G29: 22 | H29: =_xlfn.NORM.INV(RAND(),M$10,M$11) -> 0.081723264
B30: 35977 | C30: 140.35 | D30: =(C30-C31)/C31 -> -0.89203348 | E30: 0.13423307 | G30: 23 | H30: =_xlfn.NORM.INV(RAND(),M$10,M$11) -> -0.014128988
B31: 43191 | C31: 1299.94 | D31: =(C31-C32)/C32 -> 7.8557804 | E31: 0.13166188 | G31: 24 | H31: =_xlfn.NORM.INV(RAND(),M$10,M$11) -> -0.014496792
B32: 37773 | C32: 146.79 | D32: =(C32-C33)/C33 -> -0.48233178 | E32: 0.13019711 | G32: 25 | H32: =_xlfn.NORM.INV(RAND(),M$10,M$11) -> -0.12261803
B33: 40695 | C33: 283.56 | D33: =(C33-C34)/C34 -> 0.28441364 | E33: 0.12837246 | G33: 26 | H33: =_xlfn.NORM.INV(RAND(),M$10,M$11) -> -0.049926216
B34: 40330 | C34: 220.77 | D34: =(C34-C35)/C35 -> 0.46925329 | E34: 0.12798896 | G34: 27 | H34: =_xlfn.NORM.INV(RAND(),M$10,M$11) -> -0.035485095
B35: 38657 | C35: 150.26 | D35: =(C35-C36)/C36 -> -0.26720312 | E35: 0.12790872 | G35: 28 | H35: =_xlfn.NORM.INV(RAND(),M$10,M$11) -> 0.082193486
B36: 37288 | C36: 205.05 | D36: =(C36-C37)/C37 -> 1.7977896 | E36: 0.1270199 | G36: 29 | H36: =_xlfn.NORM.INV(RAND(),M$10,M$11) -> -0.064865346
B37: 35431 | C37: 73.29 | D37: =(C37-C38)/C38 -> -0.96598425 | E37: 0.12184295 | G37: 30 | H37: =_xlfn.NORM.INV(RAND(),M$10,M$11) -> 0.056232127
B38: 44166 | C38: 2154.59 | D38: =(C38-C39)/C39 -> 19.82333 | E38: 0.12028597 | G38: 31 | H38: =_xlfn.NORM.INV(RAND(),M$10,M$11) -> 0.10894754
B39: 38231 | C39: 103.47 | D39: =(C39-C40)/C40 -> -0.53898592 | E39: 0.11956287 | G39: 32 | H39: =_xlfn.NORM.INV(RAND(),M$10,M$11) -> 0.08138146
... B375: 38838 | C375: 192.63 | D375: =(C375-C376)/C376 -> #DIV/0! | E375: -0.19653806 | G375: 368 | H375: =_xlfn.NORM.INV(RAND(),M$10,M$11) -> 0.16102095
G376: 369 | H376: =_xlfn.NORM.INV(RAND(),M$10,M$11) -> 0.042141332
G377: 370 | H377: =_xlfn.NORM.INV(RAND(),M$10,M$11) -> -0.083741309
G378: 371 | H378: =_xlfn.NORM.INV(RAND(),M$10,M$11) -> 0.041004028
G379: 372 | H379: =_xlfn.NORM.INV(RAND(),M$10,M$11) -> -0.066111378
G380: 373 | H380: =_xlfn.NORM.INV(RAND(),M$10,M$11) -> 0.05424709
G381: 374 | H381: =_xlfn.NORM.INV(RAND(),M$10,M$11) -> 0.018481552
G382: 375 | H382: =_xlfn.NORM.INV(RAND(),M$10,M$11) -> 0.017637644
G383: 376 | H383: =_xlfn.NORM.INV(RAND(),M$10,M$11) -> -0.081686895
G384: 377 | H384: =_xlfn.NORM.INV(RAND(),M$10,M$11) -> 0.090752047
G385: 378 | H385: =_xlfn.NORM.INV(RAND(),M$10,M$11) -> -0.080837612
G386: 379 | H386: =_xlfn.NORM.INV(RAND(),M$10,M$11) -> 0.049445897
G387: 380 | H387: =_xlfn.NORM.INV(RAND(),M$10,M$11) -> 0.065261576
... G10007: 10000 | H10007: =_xlfn.NORM.INV(RAND(),M$10,M$11) -> -0.051533943

Sheet Dupont Analysis
B2: HINDUSTAN UNILEVER LTD
B3: (NSE: HINDUNILVR | BSE: 500696 )
B4: INR 1927.0
B5: 52 Week - (High- 2667.2 & Low- 1926.2)
B7: About the Company
B8: Hindustan Unilever Limited (HUL) is an Indian's fast-moving consumer goods company, headquartered in Mumbai. It is a subsidiary of the Anglo-Dutch company Unilever. Its products include foods, beverages, cleaning agents, personal care products and other consumer staples.The company was established in India in 1931 as Hindustan Vanaspati Manufacturing Co. Following a merger of constituent groups in 1956, it was renamed Hindustan Lever Limited. The company was renamed again in June 2007 as Hindustan Unilever Limited.
B15: Financial Summary
B54: Dupont Analysis - Return on Equity & Return on Asset
B57: Return on Equity (ROE)
C58: =HistoricalFS!F9 -> 43921 | D58: =HistoricalFS!G9 -> 44286 | E58: =HistoricalFS!H9 -> 44651 | F58: =HistoricalFS!I9 -> 45016 | G58: =HistoricalFS!J9 -> 45382 | H58: =HistoricalFS!K9 -> 45747 | I58: =HistoricalFS!L9 -> 46112
B59: Net Profit | C59: ='Data Sheet'!E30 -> 6748 | D59: ='Data Sheet'!F30 -> 7995 | E59: ='Data Sheet'!G30 -> 8879 | F59: ='Data Sheet'!H30 -> 10120 | G59: ='Data Sheet'!I30 -> 10277 | H59: ='Data Sheet'!J30 -> 10649 | I59: ='Data Sheet'!K30 -> 15040
B60: Average Shareholder's Equity | C60: =(('Data Sheet'!E57+'Data Sheet'!E58)+('Data Sheet'!D58+'Data Sheet'!D57))/2 -> 8048 | D60: =(('Data Sheet'!F57+'Data Sheet'!F58)+('Data Sheet'!E58+'Data Sheet'!E57))/2 -> 27951.5 | E60: =(('Data Sheet'!G57+'Data Sheet'!G58)+('Data Sheet'!F58+'Data Sheet'!F57))/2 -> 48367.5 | F60: =(('Data Sheet'!H57+'Data Sheet'!H58)+('Data Sheet'!G58+'Data Sheet'!G57))/2 -> 49682.5 | G60: =(('Data Sheet'!I57+'Data Sheet'!I58)+('Data Sheet'!H58+'Data Sheet'!H57))/2 -> 50761 | H60: =(('Data Sheet'!J57+'Data Sheet'!J58)+('Data Sheet'!I58+'Data Sheet'!I57))/2 -> 50310 | I60: =(('Data Sheet'!K57+'Data Sheet'!K58)+('Data Sheet'!J58+'Data Sheet'!J57))/2 -> 49070.5
B61: Return on Equity (ROE) | C61: =C59/C60 -> 0.83846918 | D61: =D59/D60 -> 0.28603116 | E61: =E59/E60 -> 0.18357368 | F61: =F59/F60 -> 0.20369345 | G61: =G59/G60 -> 0.20245858 | H61: =H59/H60 -> 0.21166766 | I61: =I59/I60 -> 0.30649779
B64: ROE - Dupont Equation
C65: =C58 -> 43921 | D65: =D58 -> 44286 | E65: =E58 -> 44651 | F65: =F58 -> 45016 | G65: =G58 -> 45382 | H65: =H58 -> 45747 | I65: =I58 -> 46112
B66: =B59 -> Net Profit | C66: =C59 -> 6748 | D66: =D59 -> 7995 | E66: =E59 -> 8879 | F66: =F59 -> 10120 | G66: =G59 -> 10277 | H66: =H59 -> 10649 | I66: =I59 -> 15040
B67: Revenue | C67: ='Data Sheet'!E17 -> 39783 | D67: ='Data Sheet'!F17 -> 47028 | E67: ='Data Sheet'!G17 -> 52446 | F67: ='Data Sheet'!H17 -> 60580 | G67: ='Data Sheet'!I17 -> 61896 | H67: ='Data Sheet'!J17 -> 61328 | I67: ='Data Sheet'!K17 -> 64468
B68: Net Profit Margin (A) | C68: =C66/C67 -> 0.16962019 | D68: =D66/D67 -> 0.1700051 | E68: =E66/E67 -> 0.16929794 | F68: =F66/F67 -> 0.16705183 | G68: =G66/G67 -> 0.16603658 | H68: =H66/H67 -> 0.1736401 | I68: =I66/I67 -> 0.23329404
B70: Revenue | C70: =C67 -> 39783 | D70: =D67 -> 47028 | E70: =E67 -> 52446 | F70: =F67 -> 60580 | G70: =G67 -> 61896 | H70: =H67 -> 61328 | I70: =I67 -> 64468
B71: Average Total Asset | C71: =('Data Sheet'!E66+'Data Sheet'!D66)/2 -> 19391 | D71: =('Data Sheet'!F66+'Data Sheet'!E66)/2 -> 44446.5 | E71: =('Data Sheet'!G66+'Data Sheet'!F66)/2 -> 69623 | F71: =('Data Sheet'!H66+'Data Sheet'!G66)/2 -> 71791.5 | G71: =('Data Sheet'!I66+'Data Sheet'!H66)/2 -> 75783 | H71: =('Data Sheet'!J66+'Data Sheet'!I66)/2 -> 79176 | I71: =('Data Sheet'!K66+'Data Sheet'!J66)/2 -> 79800.5
B72: Asset Turnover Ratio (B) | C72: =C70/C71 -> 2.0516219 | D72: =D70/D71 -> 1.0580811 | E72: =E70/E71 -> 0.75328555 | F72: =F70/F71 -> 0.84383249 | G72: =G70/G71 -> 0.8167531 | H72: =H70/H71 -> 0.77457815 | I72: =I70/I71 -> 0.80786461
B74: Average Total Asset | C74: =C71 -> 19391 | D74: =D71 -> 44446.5 | E74: =E71 -> 69623 | F74: =F71 -> 71791.5 | G74: =G71 -> 75783 | H74: =H71 -> 79176 | I74: =I71 -> 79800.5
B75: Average Shareholder's Equity | C75: =C60 -> 8048 | D75: =D60 -> 27951.5 | E75: =E60 -> 48367.5 | F75: =F60 -> 49682.5 | G75: =G60 -> 50761 | H75: =H60 -> 50310 | I75: =I60 -> 49070.5
B76: Equity Multiplier (C) | C76: =C74/C75 -> 2.4094185 | D76: =D74/D75 -> 1.5901293 | E76: =E74/E75 -> 1.4394583 | F76: =F74/F75 -> 1.4450058 | G76: =G74/G75 -> 1.4929375 | H76: =H74/H75 -> 1.5737627 | I76: =I74/I75 -> 1.6262418
B79: Return on Equity (A*B*C) | C79: =C76*C72*C68 -> 0.83846918 | D79: =D76*D72*D68 -> 0.28603116 | E79: =E76*E72*E68 -> 0.18357368 | F79: =F76*F72*F68 -> 0.20369345 | G79: =G76*G72*G68 -> 0.20245858 | H79: =H76*H72*H68 -> 0.21166766 | I79: =I76*I72*I68 -> 0.30649779
B81: Return on Asset (ROE)
C82: =C58 -> 43921 | D82: =D58 -> 44286 | E82: =E58 -> 44651 | F82: =F58 -> 45016 | G82: =G58 -> 45382 | H82: =H58 -> 45747 | I82: =I58 -> 46112
B83: Net Profit | C83: =C66 -> 6748 | D83: =D66 -> 7995 | E83: =E66 -> 8879 | F83: =F66 -> 10120 | G83: =G66 -> 10277 | H83: =H66 -> 10649 | I83: =I66 -> 15040
B84: Average Total Asset | C84: =C71 -> 19391 | D84: =D71 -> 44446.5 | E84: =E71 -> 69623 | F84: =F71 -> 71791.5 | G84: =G71 -> 75783 | H84: =H71 -> 79176 | I84: =I71 -> 79800.5
B85: Return on Asset (ROA) | C85: =C83/C84 -> 0.34799649 | D85: =D83/D84 -> 0.17987918 | E85: =E83/E84 -> 0.1275297 | F85: =F83/F84 -> 0.14096376 | G85: =G83/G84 -> 0.13561089 | H85: =H83/H84 -> 0.13449783 | I85: =I83/I84 -> 0.18847
B87: ROA - Dupont Equation
C88: =C58 -> 43921 | D88: =D58 -> 44286 | E88: =E58 -> 44651 | F88: =F58 -> 45016 | G88: =G58 -> 45382 | H88: =H58 -> 45747 | I88: =I58 -> 46112
B89: Net Profit | C89: =C66 -> 6748 | D89: =D66 -> 7995 | E89: =E66 -> 8879 | F89: =F66 -> 10120 | G89: =G66 -> 10277 | H89: =H66 -> 10649 | I89: =I66 -> 15040
B90: Revenue | C90: =C67 -> 39783 | D90: =D67 -> 47028 | E90: =E67 -> 52446 | F90: =F67 -> 60580 | G90: =G67 -> 61896 | H90: =H67 -> 61328 | I90: =I67 -> 64468
B91: Net Profit Margin (A) | C91: =C89/C90 -> 0.16962019 | D91: =D89/D90 -> 0.1700051 | E91: =E89/E90 -> 0.16929794 | F91: =F89/F90 -> 0.16705183 | G91: =G89/G90 -> 0.16603658 | H91: =H89/H90 -> 0.1736401 | I91: =I89/I90 -> 0.23329404
B93: Revenue | C93: =C90 -> 39783 | D93: =D90 -> 47028 | E93: =E90 -> 52446 | F93: =F90 -> 60580 | G93: =G90 -> 61896 | H93: =H90 -> 61328 | I93: =I90 -> 64468
B94: Average Total Asset | C94: =C71 -> 19391 | D94: =D71 -> 44446.5 | E94: =E71 -> 69623 | F94: =F71 -> 71791.5 | G94: =G71 -> 75783 | H94: =H71 -> 79176 | I94: =I71 -> 79800.5
B95: Asset Turnover Ratio (B) | C95: =C93/C94 -> 2.0516219 | D95: =D93/D94 -> 1.0580811 | E95: =E93/E94 -> 0.75328555 | F95: =F93/F94 -> 0.84383249 | G95: =G93/G94 -> 0.8167531 | H95: =H93/H94 -> 0.77457815 | I95: =I93/I94 -> 0.80786461
B97: Return on Asset (A*B) | C97: =C91*C95 -> 0.34799649 | D97: =D91*D95 -> 0.17987918 | E97: =E91*E95 -> 0.1275297 | F97: =F91*F95 -> 0.14096376 | G97: =G91*G95 -> 0.13561089 | H97: =H91*H95 -> 0.13449783 | I97: =I91*I95 -> 0.18847

Sheet Altman Z Score
B2: HINDUSTAN UNILEVER LTD
B3: (NSE: HINDUNILVR | BSE: 500696 )
B4: INR 1927.0
B5: 52 Week - (High- 2667.2 & Low- 1926.2)
B9: Altman's Z Score Analysis Calculation
B25: Working Capital/ Total Assets
C26: ='Dupont Analysis'!C88 -> 43921 | D26: ='Dupont Analysis'!D88 -> 44286 | E26: ='Dupont Analysis'!E88 -> 44651 | F26: ='Dupont Analysis'!F88 -> 45016 | G26: ='Dupont Analysis'!G88 -> 45382 | H26: ='Dupont Analysis'!H88 -> 45747 | I26: ='Dupont Analysis'!I88 -> 46112
B27: Working Capital | C27: ='Data Sheet'!E65-'Data Sheet'!E60 -> 898 | D27: ='Data Sheet'!F65-'Data Sheet'!F60 -> -7223 | E27: ='Data Sheet'!G65-'Data Sheet'!G60 -> -6203 | F27: ='Data Sheet'!H65-'Data Sheet'!H60 -> -5169 | G27: ='Data Sheet'!I65-'Data Sheet'!I60 -> -6692 | H27: ='Data Sheet'!J65-'Data Sheet'!J60 -> -8104 | I27: ='Data Sheet'!K65-'Data Sheet'!K60 -> -12450
B28: Total Assets | C28: ='Data Sheet'!E66 -> 20153 | D28: ='Data Sheet'!F66 -> 68740 | E28: ='Data Sheet'!G66 -> 70506 | F28: ='Data Sheet'!H66 -> 73077 | G28: ='Data Sheet'!I66 -> 78489 | H28: ='Data Sheet'!J66 -> 79863 | I28: ='Data Sheet'!K66 -> 79738
B29: Working Capital/ Total Assets (A) | C29: =C27/C28 -> 0.044559123 | D29: =D27/D28 -> -0.1050771 | E29: =E27/E28 -> -0.087978328 | F29: =F27/F28 -> -0.07073361 | G29: =G27/G28 -> -0.085260355 | H29: =H27/H28 -> -0.10147377 | I29: =I27/I28 -> -0.15613635
B32: Retained Earnings / Total Assets
C33: =C26 -> 43921 | D33: =D26 -> 44286 | E33: =E26 -> 44651 | F33: =F26 -> 45016 | G33: =G26 -> 45382 | H33: =H26 -> 45747 | I33: =I26 -> 46112
B34: Retained Earnings | C34: ='Data Sheet'!E58 -> 8013 | D34: ='Data Sheet'!F58 -> 47439 | E34: ='Data Sheet'!G58 -> 48826 | F34: ='Data Sheet'!H58 -> 50069 | G34: ='Data Sheet'!I58 -> 50983 | H34: ='Data Sheet'!J58 -> 49167 | I34: ='Data Sheet'!K58 -> 48504
B35: Total Assets | C35: =C28 -> 20153 | D35: =D28 -> 68740 | E35: =E28 -> 70506 | F35: =F28 -> 73077 | G35: =G28 -> 78489 | H35: =H28 -> 79863 | I35: =I28 -> 79738
B36: Retained Earnings / Total Assets (B) | C36: =C34/C35 -> 0.3976083 | D36: =D34/D35 -> 0.6901222 | E36: =E34/E35 -> 0.69250844 | F36: =F34/F35 -> 0.68515402 | G36: =G34/G35 -> 0.64955599 | H36: =H34/H35 -> 0.61564179 | I36: =I34/I35 -> 0.60829216
B38: EBIT/ Total Assets
C39: =C33 -> 43921 | D39: =D33 -> 44286 | E39: =E33 -> 44651 | F39: =F33 -> 45016 | G39: =G33 -> 45382 | H39: =H33 -> 45747 | I39: =I33 -> 46112
B40: EBIT | C40: =HistoricalFS!F23-HistoricalFS!F29 -> 8859 | D40: =HistoricalFS!G23-HistoricalFS!G29 -> 10552 | E40: =HistoricalFS!H23-HistoricalFS!H29 -> 11766 | F40: =HistoricalFS!I23-HistoricalFS!I29 -> 13010 | G40: =HistoricalFS!J23-HistoricalFS!J29 -> 13443 | H40: =HistoricalFS!K23-HistoricalFS!K29 -> 13445 | I40: =HistoricalFS!L23-HistoricalFS!L29 -> 13706
B41: Total Asset | C41: =C35 -> 20153 | D41: =D35 -> 68740 | E41: =E35 -> 70506 | F41: =F35 -> 73077 | G41: =G35 -> 78489 | H41: =H35 -> 79863 | I41: =I35 -> 79738
B42: EBIT/ Total Assets (C) | C42: =C40/C41 -> 0.43958716 | D42: =D40/D41 -> 0.15350596 | E42: =E40/E41 -> 0.16687941 | F42: =F40/F41 -> 0.17803139 | G42: =G40/G41 -> 0.17127241 | H42: =H40/H41 -> 0.1683508 | I42: =I40/I41 -> 0.17188793
B44: Market Cap / Long Term Liabilities
C45: =C39 -> 43921 | D45: =D39 -> 44286 | E45: =E39 -> 44651 | F45: =F39 -> 45016 | G45: =G39 -> 45382 | H45: =H39 -> 45747 | I45: =I39 -> 46112
B46: Market Cap | C46: ='Data Sheet'!E90*'Data Sheet'!E70 -> 475163.28 | D46: ='Data Sheet'!F90*'Data Sheet'!F70 -> 546873.2 | E46: ='Data Sheet'!G90*'Data Sheet'!G70 -> 460764.5 | F46: ='Data Sheet'!H90*'Data Sheet'!H70 -> 575853.4 | G46: ='Data Sheet'!I90*'Data Sheet'!I70 -> 509277.9 | H46: ='Data Sheet'!J90*'Data Sheet'!J70 -> 508041.8 | I46: ='Data Sheet'!K90*'Data Sheet'!K70 -> 482972
B47: Total Liabilities | C47: =HistoricalFS!F58 -> 20153 | D47: =HistoricalFS!G58 -> 68740 | E47: =HistoricalFS!H58 -> 70506 | F47: =HistoricalFS!I58 -> 73077 | G47: =HistoricalFS!J58 -> 78489 | H47: =HistoricalFS!K58 -> 79863 | I47: =HistoricalFS!L58 -> 79738
B48: Market Cap / Long Term Liabilities (D) | C48: =C46/C47 -> 23.577794 | D48: =D46/D47 -> 7.9556765 | E48: =E46/E47 -> 6.5351105 | F48: =F46/F47 -> 7.8800909 | G48: =G46/G47 -> 6.4885258 | H48: =H46/H47 -> 6.3614164 | I48: =I46/I47 -> 6.0569866
B50: Sales / Total Assets
C51: =C26 -> 43921 | D51: =D26 -> 44286 | E51: =E26 -> 44651 | F51: =F26 -> 45016 | G51: =G26 -> 45382 | H51: =H26 -> 45747 | I51: =I26 -> 46112
B52: Sales | C52: ='Data Sheet'!E17 -> 39783 | D52: ='Data Sheet'!F17 -> 47028 | E52: ='Data Sheet'!G17 -> 52446 | F52: ='Data Sheet'!H17 -> 60580 | G52: ='Data Sheet'!I17 -> 61896 | H52: ='Data Sheet'!J17 -> 61328 | I52: ='Data Sheet'!K17 -> 64468
B53: Total Asset | C53: =C35 -> 20153 | D53: =D35 -> 68740 | E53: =E35 -> 70506 | F53: =F35 -> 73077 | G53: =G35 -> 78489 | H53: =H35 -> 79863 | I53: =I35 -> 79738
B54: Sales / Total Assets (E) | C54: =C52/C53 -> 1.9740485 | D54: =D52/D53 -> 0.68414315 | E54: =E52/E53 -> 0.74385159 | F54: =F52/F53 -> 0.8289886 | G54: =G52/G53 -> 0.78859458 | H54: =H52/H53 -> 0.76791505 | I54: =I52/I53 -> 0.80849783
B56: Altman's Z Score
C57: =C51 -> 43921 | D57: =D51 -> 44286 | E57: =E51 -> 44651 | F57: =F51 -> 45016 | G57: =G51 -> 45382 | H57: =H51 -> 45747 | I57: =I51 -> 46112
B58: Final Score | C58: =(C29*1.2)+(C36*1.4)+(C42*3.3)+(C48*0.6)+(C54*1) -> 18.181485 | D58: =(D29*1.2)+(D36*1.4)+(D42*3.3)+(D48*0.6)+(D54*1) -> 6.8041973 | E58: =(E29*1.2)+(E36*1.4)+(E42*3.3)+(E48*0.6)+(E54*1) -> 6.0795578 | F58: =(F29*1.2)+(F36*1.4)+(F42*3.3)+(F48*0.6)+(F54*1) -> 7.018882 | G58: =(G29*1.2)+(G36*1.4)+(G42*3.3)+(G48*0.6)+(G54*1) -> 6.053975 | H58: =(H29*1.2)+(H36*1.4)+(H42*3.3)+(H48*0.6)+(H54*1) -> 5.8804525 | I58: =(I29*1.2)+(I36*1.4)+(I42*3.3)+(I48*0.6)+(I54*1) -> 5.6741654
B59: Financial Stability | C59: =IF(C58<1.81, "Distressed", IF(C58>3, "Strong","Grey Zone")) -> Strong | D59: =IF(D58<1.81, "Distressed", IF(D58>3, "Strong","Grey Zone")) -> Strong | E59: =IF(E58<1.81, "Distressed", IF(E58>3, "Strong","Grey Zone")) -> Strong | F59: =IF(F58<1.81, "Distressed", IF(F58>3, "Strong","Grey Zone")) -> Strong | G59: =IF(G58<1.81, "Distressed", IF(G58>3, "Strong","Grey Zone")) -> Strong | H59: =IF(H58<1.81, "Distressed", IF(H58>3, "Strong","Grey Zone")) -> Strong | I59: =IF(I58<1.81, "Distressed", IF(I58>3, "Strong","Grey Zone")) -> Strong

Sheet Data Room>

Sheet Data Sheet
A1: COMPANY NAME | B1: HINDUSTAN UNILEVER LTD | E1: =IF(B2<>B3, "A NEW VERSION OF THE WORKSHEET IS AVAILABLE", "")
A2: LATEST VERSION | B2: 2.1 | E2: PLEASE DO NOT MAKE ANY CHANGES TO THIS SHEET
A3: CURRENT VERSION | B3: 2.1
A5: META
A6: Number of shares | B6: =IF(B9>0, B9/B8, 0) -> 234.88771
A7: Face Value | B7: 1
A8: Current Price | B8: 1960
A9: Market Capitalization | B9: 460379.91
A15: PROFIT & LOSS | B15: =B26+B34 -> 7352 | K15: =K17-K18-K20-K21-K22-K23-K19 -> 17232
A16: Report Date | B16: 42825 | C16: 43190 | D16: 43555 | E16: 43921 | F16: 44286 | G16: 44651 | H16: 45016 | I16: 45382 | J16: 45747 | K16: 46112
A17: Sales | B17: 33162 | C17: 35545 | D17: 39310 | E17: 39783 | F17: 47028 | G17: 52446 | H17: 60580 | I17: 61896 | J17: 61328 | K17: 64468
A18: Raw Material Cost | B18: 13606 | C18: 14233 | D18: 15845 | E18: 15697 | F18: 20141 | G18: 22871 | H18: 28427 | I18: 26822 | J18: 26602 | K18: 29158
A19: Change in Inventory | B19: -144 | C19: 72 | D19: -12 | E19: 108 | F19: 405 | G19: 22 | H19: 75 | I19: 11 | J19: 125 | K19: 429
A20: Power and Fuel | B20: 295 | C20: 295 | D20: 308 | E20: 299 | F20: 339 | G20: 318 | H20: 384 | I20: 446 | J20: 403 | K20: 426
A21: Other Mfr. Exp | B21: 2887 | C21: 2998 | D21: 3041 | E21: 2906 | F21: 2868 | G21: 3354 | H21: 3791 | I21: 3385 | J21: 3687 | K21: 3304
A22: Employee Cost | B22: 1743 | C22: 1860 | D22: 1875 | E22: 1820 | F22: 2358 | G22: 2545 | H22: 2854 | I22: 3009 | J22: 2952 | K22: 3175
A23: Selling and admin | B23: 6689 | C23: 7252 | D23: 7796 | E23: 7620 | F23: 7906 | G23: 8164 | H23: 8785 | I23: 10780 | J23: 10145 | K23: 10744
A24: Other Expenses | B24: 1470 | C24: 1480 | D24: 1553 | E24: 1688 | F24: 2195 | G24: 2359 | H24: 2267 | I24: 2806 | J24: 2966 | K24: 3051
A25: Other Income | B25: 606 | C25: 353 | D25: 322 | E25: 424 | F25: 170 | G25: 219 | H25: 448 | I25: 817 | J25: 1355 | K25: 4923
A26: Depreciation | B26: 432 | C26: 520 | D26: 565 | E26: 1002 | F26: 1074 | G26: 1091 | H26: 1137 | I26: 1216 | J26: 1253 | K26: 1333
A27: Interest | B27: 35 | C27: 26 | D27: 33 | E27: 118 | F27: 117 | G27: 106 | H27: 114 | I27: 334 | J27: 381 | K27: 410
... A31: Dividend Amount | B31: 3672 | C31: 4320 | D31: 4752 | E31: 5400 | F31: 9517.5 | G31: 7990 | H31: 9165 | I31: 9870 | J31: 12455 | K31: 9635
A32: Effective Tax Rate | B32: =B29/B28 -> 0.30570589 | C32: =C29/C28 -> 0.28456064 | D32: =D29/D28 -> 0.29567643 | E32: =E29/E28 -> 0.26284779 | F32: =F29/F28 -> 0.24573314 | G32: =G29/G28 -> 0.25145214 | H32: =H29/H28 -> 0.23988309 | I32: =I29/I28 -> 0.26166882 | ... K32: =K29/K28 -> 0.1734453
A34: EBITDA | B34: =+B30+B29+B27+B26 -> 6920 | C34: =+C30+C29+C27+C26 -> 7839 | D34: =+D30+D29+D27+D26 -> 9196 | E34: =+E30+E29+E27+E26 -> 10277 | F34: =+F30+F29+F27+F26 -> 11792 | G34: =+G30+G29+G27+G26 -> 13063 | H34: =+H30+H29+H27+H26 -> 14572 | I34: =+I30+I29+I27+I26 -> 15471 | ... K34: =+K30+K29+K27+K26 -> 19943
B37: =B30-B31 -> 804 | C37: =C30-C31 -> 894 | D37: =D30-D31 -> 1302 | E37: =E30-E31 -> 1348 | F37: =F30-F31 -> -1522.5 | G37: =G30-G31 -> 889 | H37: =H30-H31 -> 955 | I37: =I30-I31 -> 407 | ... K37: =K30-K31 -> 5405
A40: Quarters
A41: Report Date | B41: 45382 | C41: 45473 | D41: 45565 | E41: 45657 | F41: 45747 | G41: 45838 | H41: 45930 | I41: 46022 | J41: 46112 | K41: 46203
A42: Sales | B42: 15210 | C42: 15707 | D42: 15926 | E42: 15556 | F42: 15190 | G42: 15757 | H42: 15919 | I42: 16441 | J42: 16351 | K42: 17341
A43: Expenses | B43: 11675 | C43: 11965 | D43: 12139 | E43: 11867 | F43: 11572 | G43: 12118 | H43: 12137 | I43: 12660 | J43: 12514 | K43: 13394
A44: Other Income | B44: 309 | C44: 209 | D44: 203 | E44: 733 | F44: 149 | G44: 103 | H44: 269 | I44: 4048 | J44: 503 | K44: 113
A45: Depreciation | B45: 320 | C45: 329 | D45: 338 | E45: 318 | F45: 318 | G45: 326 | H45: 322 | I45: 337 | J45: 348 | K45: 353
A46: Interest | B46: 105 | C46: 93 | D46: 110 | E46: 109 | F46: 77 | G46: 122 | H46: 124 | I46: 88 | J46: 76 | K46: 75
A47: Profit before tax | B47: 3419 | C47: 3529 | D47: 3542 | E47: 3995 | F47: 3372 | G47: 3294 | H47: 3605 | I47: 7404 | J47: 3916 | K47: 3632
A48: Tax | B48: 858 | C48: 917 | D48: 947 | E48: 1006 | F48: 897 | G48: 526 | H48: 911 | I48: 801 | J48: 922 | K48: 952
A49: Net profit | B49: 2558 | C49: 2610 | D49: 2591 | E49: 2984 | F49: 2464 | G49: 2756 | H49: 2685 | I49: 6607 | J49: 2992 | K49: 2673
A50: Operating Profit | B50: 3535 | C50: 3742 | D50: 3787 | E50: 3689 | F50: 3618 | G50: 3639 | H50: 3782 | I50: 3781 | J50: 3837 | K50: 3947
A51: EBITDA | B51: =B49+B48+B46+B45 -> 3841 | C51: =C49+C48+C46+C45 -> 3949 | D51: =D49+D48+D46+D45 -> 3986 | E51: =E49+E48+E46+E45 -> 4417 | F51: =F49+F48+F46+F45 -> 3756 | G51: =G49+G48+G46+G45 -> 3730 | H51: =H49+H48+H46+H45 -> 4042 | I51: =I49+I48+I46+I45 -> 7833 | ... K51: =K49+K48+K46+K45 -> 4053
A55: BALANCE SHEET
A56: Report Date | B56: 42825 | C56: 43190 | D56: 43555 | E56: 43921 | F56: 44286 | G56: 44651 | H56: 45016 | I56: 45382 | J56: 45747 | K56: 46112
A57: Equity Share Capital | B57: 216 | C57: 216 | D57: 216 | E57: 216 | F57: 235 | G57: 235 | H57: 235 | I57: 235 | J57: 235 | K57: 235
A58: Reserves | B58: 6528 | C58: 7065 | D58: 7651 | E58: 8013 | F58: 47439 | G58: 48826 | H58: 50069 | I58: 50983 | J58: 49167 | K58: 48504
A59: Borrowings | B59: 277 | D59: 99 | G59: 1043 | H59: 1219 | I59: 1484 | J59: 1648 | K59: 1478
A60: Other Liabilities | B60: 8685 | C60: 10581 | D60: 10663 | E60: 11924 | F60: 21066 | G60: 20402 | H60: 21554 | I60: 25787 | J60: 28813 | K60: 29521
A61: Total | B61: 15706 | C61: 17862 | D61: 18629 | E61: 20153 | F61: 68740 | G61: 70506 | H61: 73077 | I61: 78489 | J61: 79863 | K61: 79738
A62: Net Block | B62: 4419 | C62: 4528 | D62: 4715 | E62: 5479 | F62: 51443 | G62: 51473 | H62: 52678 | I62: 53744 | J62: 54335 | K62: 57428
A63: Capital Work in Progress | B63: 229 | C63: 461 | D63: 406 | E63: 597 | F63: 745 | G63: 1313 | H63: 1132 | I63: 1025 | J63: 1009 | K63: 880
A64: Investments | B64: 3794 | C64: 2873 | D64: 2716 | E64: 1255 | F64: 2709 | G64: 3521 | H64: 2882 | I64: 4625 | J64: 3810 | K64: 4359
A65: Other Assets | B65: 7264 | C65: 10000 | D65: 10792 | E65: 12822 | F65: 13843 | G65: 14199 | H65: 16385 | I65: 19095 | J65: 20709 | K65: 17071
A66: Total | B66: 15706 | C66: 17862 | D66: 18629 | E66: 20153 | F66: 68740 | G66: 70506 | H66: 73077 | I66: 78489 | J66: 79863 | K66: 79738
A67: Receivables | B67: 1085 | C67: 1310 | D67: 1816 | E67: 1149 | F67: 1758 | G67: 2236 | H67: 3079 | I67: 2997 | J67: 3819 | K67: 3379
A68: Inventory | B68: 2541 | C68: 2513 | D68: 2574 | E68: 2767 | F68: 3579 | G68: 4096 | H68: 4251 | I68: 4022 | J68: 4415 | K68: 4789
A69: Cash & Bank | B69: 1828 | C69: 3485 | D69: 3757 | E69: 5113 | F69: 4471 | G69: 3846 | H69: 4678 | I69: 7559 | J69: 7554 | K69: 3248
A70: No. of Equity Shares | B70: 216 | C70: 216 | D70: 216 | E70: 216 | F70: 235 | G70: 235 | H70: 235 | I70: 235 | J70: 235 | K70: 235
A71: New Bonus Shares
A72: Face value | B72: 1 | C72: 1 | D72: 1 | E72: 1 | F72: 1 | G72: 1 | H72: 1 | I72: 1 | J72: 1 | K72: 1
H73: =H62-G62+H45 -> 1527 | I73: =I62-H62+I45 -> 1403 | J73: =J62-I62+J45 -> 939 | K73: =K62-J62+K45 -> 3446
A74: Other Assets | B74: =B65-SUM(B67:B69) -> 1810 | C74: =C65-SUM(C67:C69) -> 2692 | D74: =D65-SUM(D67:D69) -> 2645 | E74: =E65-SUM(E67:E69) -> 3793 | F74: =F65-SUM(F67:F69) -> 4035 | G74: =G65-SUM(G67:G69) -> 4021 | H74: =H65-SUM(H67:H69) -> 4377 | I74: =I65-SUM(I67:I69) -> 4517 | ... K74: =K65-SUM(K67:K69) -> 5655
A75: Total Asset | B75: =B61 -> 15706 | C75: =C61 -> 17862 | D75: =D61 -> 18629 | E75: =E61 -> 20153 | F75: =F61 -> 68740 | G75: =G61 -> 70506 | H75: =H61 -> 73077 | I75: =I61 -> 78489 | ... K75: =K61 -> 79738
A80: CASH FLOW:
A81: Report Date | B81: 42825 | C81: 43190 | D81: 43555 | E81: 43921 | F81: 44286 | G81: 44651 | H81: 45016 | I81: 45382 | J81: 45747 | K81: 46112
A82: Cash from Operating Activity | B82: 5185 | C82: 6059 | D82: 5800 | E82: 7623 | F82: 9163 | G82: 9048 | H82: 9991 | I82: 15469 | J82: 11886 | K82: 10999
A83: Cash from Investing Activity | B83: -1173 | C83: -1063 | D83: -438 | E83: 1791 | F83: -1228 | G83: -1728 | H83: -1484 | I83: -5324 | J83: 6473 | K83: -3676
A84: Cash from Financing Activity | B84: -4214 | C84: -4975 | D84: -5390 | E84: -6819 | F84: -9309 | G84: -8015 | H84: -8953 | I84: -10034 | J84: -13101 | K84: -10810
A85: Net Cash Flow | B85: -202 | C85: 21 | D85: -28 | E85: 2595 | F85: -1374 | G85: -695 | H85: -446 | I85: 111 | J85: 5258 | K85: -3487
A90: PRICE: | B90: 872.61 | C90: 1276.11 | D90: 1633.53 | E90: 2199.83 | F90: 2327.12 | G90: 1960.7 | H90: 2450.44 | I90: 2167.14 | J90: 2161.88 | K90: 2055.2
A92: DERIVED:
A93: Adjusted Equity Shares in Cr | B93: 216.43 | C93: 216.45 | D93: 216.47 | E93: 216.48 | F93: 234.96 | G93: 234.96 | H93: 234.96 | I93: 234.96 | J93: 234.96 | K93: 234.96

Sheet Cash Flow Data 
C2: 42064 | D2: 42430 | E2: 42795 | F2: 43160 | G2: 43525 | H2: 43891 | I2: 44256 | J2: 44621 | K2: 44986 | L2: 45352 | M2: 45717 | N2: 46082
B3: Cash from Operating Activity - | C3: 3292 | D3: 4171 | E3: 5185 | F3: 6059 | G3: 5800 | H3: 7623 | I3: 9163 | J3: 9048 | K3: 9991 | L3: 15469 | M3: 11886 | N3: 10999
B4: Profit from operations | C4: 5510 | D4: 6025 | E4: 6512 | F4: 7485 | G4: 8909 | H4: 9723 | I4: 11672 | J4: 12829 | K4: 14089 | L4: 14537 | M4: 14942 | N4: 15153
B5: Receivables | C5: 3 | D5: -257 | E5: 173 | F5: 0 | G5: 0 | H5: 0 | I5: 0 | J5: 0 | K5: 0 | L5: 0 | M5: 0 | N5: 0
B6: Inventory | C6: 91 | D6: 89 | E6: 37 | F6: -146 | G6: -195 | H6: -331 | I6: -543 | J6: -758 | K6: -339 | L6: 74 | M6: -584 | N6: -692
B7: Payables | C7: -327 | D7: 164 | E7: 501 | F7: 0 | G7: 0 | H7: 0 | I7: 0 | J7: 0 | K7: 0 | L7: 0 | M7: 0 | N7: 0
B8: Loans Advances | C8: -148 | D8: 0 | E8: 0 | F8: 0 | G8: 0 | H8: 0 | I8: 0 | J8: 0 | K8: 0 | L8: 0 | M8: 0 | N8: 0
B9: Operating Deposits | C9: 0 | D9: 0 | E9: -46 | F9: 0 | G9: 0 | H9: 0 | I9: 0 | J9: 0 | K9: 0 | L9: 0 | M9: 0 | N9: 0
B10: Other WC items | C10: 38 | D10: -77 | E10: -99 | F10: 982 | G10: -147 | H10: 742 | I10: 442 | J10: -242 | K10: -621 | L10: 1239 | M10: -204 | N10: 1378
B11: Working capital changes | C11: -342 | D11: -81 | E11: 566 | F11: 836 | G11: -342 | H11: 411 | I11: -101 | J11: -1000 | K11: -960 | L11: 1313 | M11: -788 | N11: 686
B12: Direct taxes | C12: -1862 | D12: -1765 | E12: -1859 | F12: -2264 | G12: -2767 | H12: -2505 | I12: -2407 | J12: -2784 | K12: -3138 | L12: -381 | M12: -2268 | N12: -4840
B13: Other operating items | C13: -14 | D13: -8 | E13: -21 | F13: 0 | G13: 0 | H13: 0 | I13: 0 | J13: 0 | K13: 0 | L13: 0 | M13: 0 | N13: 0
B14: Exceptional CF items | C14: 0 | D14: 0 | E14: -13 | F14: 2 | G14: 0 | H14: -6 | I14: -1 | J14: 3 | K14: 0 | L14: 0 | M14: 0 | N14: 0
... B35: CFO/OP | C35: 0.95 | D35: 1 | E35: 1.11 | F35: 1.11 | G35: 0.96 | H35: 1.03 | I35: 1 | J35: 0.92 | K35: 0.93 | L35: 1.08 | M35: 0.96 | N35: 10

Sheet Data
B2: S.No. | C2: Company | D2: CMP Rs. | E2: No. Eq. Shares Cr. | F2: Market Cap | G2: Debt Rs.Cr. | H2: Cash End Rs.Cr. | I2: Net Debt | J2: EV | K2: Sales Rs.Cr. | L2: EBITDA | M2: NP 12M Rs.Cr. | N2: EV / EBITDA
B3: 1 | C3: Hind. Unilever | D3: 1927 | E3: 234.96 | F3: =E3*D3 -> 452767.92 | G3: 1478 | H3: 3248 | I3: =G3-H3 -> -1770 | J3: =F3+G3-H3 -> 450997.92 | K3: 66052 | L3: =J3/N3 -> 16084.091 | M3: 14971 | N3: 28.04
B4: 2 | C4: ITC | D4: 259.85 | E4: 1252.98 | F4: =E4*D4 -> 325586.85 | G4: 2399.06 | H4: 3008.79 | I4: =G4-H4 -> -609.73 | J4: =F4+G4-H4 -> 324977.12 | K4: 76487.98 | L4: =J4/N4 -> 28481.781 | M4: 20183.53 | N4: 11.41
B5: 3 | C5: Nestle India | D5: 1383.3 | E5: 192.83 | F5: =E5*D5 -> 266741.74 | G5: 444.16 | H5: 1340.87 | I5: =G5-H5 -> -896.71 | J5: =F5+G5-H5 -> 265845.03 | K5: 24436.62 | L5: =J5/N5 -> 5803.2095 | M5: 3860.49 | N5: 45.81
B6: 4 | C6: Varun Beverages | D6: 416.5 | E6: 338.25 | F6: =E6*D6 -> 140881.12 | G6: 2508.18 | H6: 1998.49 | I6: =G6-H6 -> 509.69 | J6: =F6+G6-H6 -> 141390.82 | K6: 24126.49 | L6: =J6/N6 -> 6042.3425 | M6: 3409.28 | N6: 23.4
B7: 5 | C7: Britannia Inds. | D7: 4962 | E7: 24.09 | F7: =E7*D7 -> 119534.58 | G7: 1380.28 | H7: 352.44 | I7: =G7-H7 -> 1027.84 | J7: =F7+G7-H7 -> 120562.42 | K7: 19529.34 | L7: =J7/N7 -> 3829.81 | M7: 2610.26 | N7: 31.48
B8: 6 | C8: Marico | D8: 802.1 | E8: 130.02 | F8: =E8*D8 -> 104289.04 | G8: 557 | H8: 493 | I8: =G8-H8 -> 64 | J8: =F8+G8-H8 -> 104353.04 | K8: 14277 | L8: =J8/N8 -> 2688.1258 | M8: 1952 | N8: 38.82
B9: 7 | C9: United Spirits | D9: 1395 | E9: 72.74 | F9: =E9*D9 -> 101472.3 | G9: 413 | H9: 1977 | I9: =G9-H9 -> -1564 | J9: =F9+G9-H9 -> 99908.3 | K9: 12626 | L9: =J9/N9 -> 2789.1764 | M9: 1884 | N9: 35.82
B10: 8 | C10: Tata Consumer | D10: 991 | E10: 98.97 | F10: =E10*D10 -> 98079.27 | G10: 2819.51 | H10: 3420.49 | I10: =G10-H10 -> -600.98 | J10: =F10+G10-H10 -> 97478.29 | K10: 20860.4 | L10: =J10/N10 -> 3104.4041 | M10: 1642.24 | N10: 31.4
B11: 9 | C11: Godrej Consumer | D11: 865 | E11: 102.33 | F11: =E11*D11 -> 88515.45 | G11: 4420.52 | H11: 1005.41 | I11: =G11-H11 -> 3415.11 | J11: =F11+G11-H11 -> 91930.56 | K11: 15948.95 | L11: =J11/N11 -> 3496.7881 | M11: 1913.54 | N11: 26.29
B12: 10 | C12: Dabur India | D12: 376 | E12: 177.4 | F12: =E12*D12 -> 66702.4 | G12: 1287.32 | H12: 562.07 | I12: =G12-H12 -> 725.25 | J12: =F12+G12-H12 -> 67427.65 | K12: 13552.38 | L12: =J12/N12 -> 3152.2978 | M12: 1946.56 | N12: 21.39
B20: 11 | C20: Radico Khaitan | D20: 4368.1 | E20: 13.4 | F20: =E20*D20 -> 58532.54 | G20: 498.45 | H20: 88.33 | J20: =F20+G20-H20 -> 58942.66 | K20: 6228.08 | L20: =J20/N20 -> 1162.8065 | M20: 703.55 | N20: 50.69
B21: 12 | C21: Colgate-Palmoliv | D21: 1797.4 | E21: 27.2 | F21: =E21*D21 -> 48889.28 | G21: 47.41 | H21: 1468.82 | J21: =F21+G21-H21 -> 47467.87 | K21: 6204.28 | L21: =J21/N21 -> 1994.4483 | M21: 1347.77 | N21: 23.8
B22: 13 | C22: Cupid | D22: 280 | E22: 134.47 | F22: =E22*D22 -> 37651.6 | G22: 56.38 | H22: 186.45 | J22: =F22+G22-H22 -> 37521.53 | K22: 483.64 | L22: =J22/N22 -> 191.33876 | M22: 137.41 | N22: 196.1
B23: 14 | C23: Patanjali Foods | D23: 341 | E23: 108.81 | F23: =E23*D23 -> 37104.21 | G23: 2788.83 | H23: 746.36 | J23: =F23+G23-H23 -> 39146.68 | K23: 42753.63 | L23: =J23/N23 -> 2145.0236 | M23: 1970.34 | N23: 18.25
B24: 15 | C24: United Breweries | D24: 1256.1 | E24: 26.44 | F24: =E24*D24 -> 33211.284 | G24: 1316.53 | H24: 571.56 | J24: =F24+G24-H24 -> 33956.254 | K24: 9442.48 | L24: =J24/N24 -> 862.05265 | M24: 395.64 | N24: 39.39

Sheet Raw FS
C3: Particulars | D3: 42064 | E3: 42430 | F3: 42795 | G3: 43160 | H3: 43525 | I3: 43891 | J3: 44256 | K3: 44621 | L3: 44986 | M3: 45352 | N3: 45717 | O3: 46082
C5: Equity Capital | D5: 216 | E5: 216 | F5: 216 | G5: 216 | H5: 216 | I5: 216 | J5: 235 | K5: 235 | L5: 235 | M5: 235 | N5: 235 | O5: 235
C6: Reserves | D6: 3811 | E6: 6357 | F6: 6528 | G6: 7065 | H6: 7651 | I6: 8013 | J6: 47439 | K6: 48826 | L6: 50069 | M6: 50983 | N6: 49167 | O6: 48504
C7: Borrowings -
C8: Long term Borrowings | D8: 7 | E8: 0 | F8: 0 | G8: 0 | H8: 0 | I8: 0 | J8: 0 | K8: 0 | L8: 0 | M8: 0 | N8: 0 | O8: 0
C9: Short term Borrowings | D9: 36 | E9: 177 | F9: 277 | G9: 0 | H9: 99 | I9: 0 | J9: 0 | K9: 0 | L9: 98 | M9: 13 | N9: 1 | O9: 0
C10: Lease Liabilities | D10: 0 | E10: 0 | F10: 0 | G10: 0 | H10: 0 | I10: 0 | J10: 0 | K10: 1043 | L10: 1121 | M10: 1471 | N10: 1647 | O10: 1478
C11: Other Liabilities -
C12: Non controlling int | D12: 25 | E12: 20 | F12: 22 | G12: 20 | H12: 18 | I12: 17 | J12: 20 | K12: 26 | L12: 218 | M12: 205 | N12: 207 | O12: 269
C13: Trade Payables | D13: 5506 | E13: 5685 | F13: 6186 | G13: 7170 | H13: 7206 | I13: 7535 | J13: 8802 | K13: 9068 | L13: 9574 | M13: 10486 | N13: 11315 | O13: 13325
C14: Advance from Customers | D14: 45 | E14: 45 | F14: 78 | G14: 62 | H14: 43 | I14: 158 | J14: 96 | K14: 119 | L14: 98 | M14: 91 | N14: 0 | O14: 0
C15: Other liability items | D15: 4783 | E15: 2293 | F15: 2399 | G15: 3329 | H15: 3396 | I15: 4214 | J15: 12148 | K15: 11189 | L15: 11664 | M15: 15005 | N15: 17291 | O15: 15927
C16: Total Liabilities | D16: 14430 | E16: 14793 | F16: 15706 | G16: 17862 | H16: 18629 | I16: 20153 | J16: 68740 | K16: 70506 | L16: 73077 | M16: 78489 | N16: 79863 | O16: 79738
C18: Fixed Assets -
C19: Land | D19: 102 | E19: 88 | F19: 89 | G19: 87 | H19: 86 | I19: 59 | J19: 477 | K19: 477 | L19: 609 | M19: 633 | N19: 628 | O19: 636
C20: Building | D20: 1173 | E20: 931 | F20: 1210 | G20: 1343 | H20: 1527 | I20: 2044 | J20: 2602 | K20: 2788 | L20: 3101 | M20: 3590 | N20: 3833 | O20: 4067
C21: Plant Machinery | D21: 3481 | E21: 2370 | F21: 3270 | G21: 3691 | H21: 4092 | I21: 5001 | J21: 6097 | K21: 6566 | L21: 7612 | M21: 8946 | N21: 9900 | O21: 9296
C22: Equipments | D22: 106 | E22: 41 | F22: 62 | G22: 74 | H22: 95 | I22: 139 | J22: 175 | K22: 181 | L22: 185 | M22: 206 | N22: 245 | O22: 286
C23: Furniture n fittings | D23: 108 | E23: 61 | F23: 66 | G23: 76 | H23: 88 | I23: 154 | J23: 156 | K23: 152 | L23: 161 | M23: 165 | N23: 174 | O23: 220
C24: Railway sidings | D24: 0 | E24: 0 | F24: 0 | G24: 0 | H24: 0 | I24: 0 | J24: 0 | K24: 0 | L24: 0 | M24: 0 | N24: 0 | O24: 0
C25: Vehicles | D25: 1 | E25: 0 | F25: 0 | G25: 0 | H25: 0 | I25: 0 | J25: 0 | K25: 0 | L25: 33 | M25: 39 | N25: 102 | O25: 103
C26: Intangible Assets | D26: 247 | E26: 85 | F26: 455 | G26: 455 | H26: 511 | I26: 511 | J26: 45262 | K26: 45262 | L26: 45692 | M26: 45692 | N26: 45692 | O26: 49195
C27: Other fixed assets | D27: 193 | E27: 19 | F27: 19 | G27: 26 | H27: 60 | I27: 71 | J27: 155 | K27: 152 | L27: 171 | M27: 180 | N27: 190 | O27: 210
C28: Gross Block | D28: 5412 | E28: 3595 | F28: 5171 | G28: 5752 | H28: 6459 | I28: 7979 | J28: 54924 | K28: 55578 | L28: 57564 | M28: 59451 | N28: 60764 | O28: 64013
C29: Accumulated Depreciation | D29: 2591 | E29: 337 | F29: 752 | G29: 1224 | H29: 1744 | I29: 2500 | J29: 3481 | K29: 4105 | L29: 4886 | M29: 5707 | N29: 6429 | O29: 6585
C30: Net Block | D30: =D28-D29 -> 2821 | E30: =E28-E29 -> 3258 | F30: =F28-F29 -> 4419 | G30: =G28-G29 -> 4528 | H30: =H28-H29 -> 4715 | I30: =I28-I29 -> 5479 | J30: =J28-J29 -> 51443 | K30: =K28-K29 -> 51473 | ... O30: =O28-O29 -> 57428
C32: CWIP | D32: 516 | E32: 408 | F32: 229 | G32: 461 | H32: 406 | I32: 597 | J32: 745 | K32: 1313 | L32: 1132 | M32: 1025 | N32: 1009 | O32: 880
C33: Investments | D33: 3025 | E33: 2592 | F33: 3794 | G33: 2873 | H33: 2716 | I33: 1255 | J33: 2709 | K33: 3521 | L33: 2882 | M33: 4625 | N33: 3810 | O33: 4359
C35: Other Assets -
C36: Inventories | D36: 2849 | E36: 2726 | F36: 2541 | G36: 2513 | H36: 2574 | I36: 2767 | J36: 3579 | K36: 4096 | L36: 4251 | M36: 4022 | N36: 4415 | O36: 4789
C37: Trade receivables | D37: 1010 | E37: 1264 | F37: 1085 | G37: 1310 | H37: 1816 | I37: 1149 | J37: 1758 | K37: 2236 | L37: 3079 | M37: 2997 | N37: 3819 | O37: 3379
C38: Receivables over 6m | D38: 78 | E38: 0 | F38: 0 | G38: 0 | H38: 0 | I38: 0 | J38: 0 | K38: 197 | L38: 407 | M38: 200 | N38: 313 | O38: 339
C39: Receivables under 6m | D39: 973 | E39: 1294 | F39: 1124 | G39: 1359 | H39: 1848 | I39: 1185 | J39: 1869 | K39: 2142 | L39: 2748 | M39: 2862 | N39: 3574 | O39: 3117
C40: Prov for Doubtful | D40: -41 | E40: -30 | F40: -39 | G40: -49 | H40: -32 | I40: -36 | J40: -111 | K40: -103 | L40: -76 | M40: -65 | N40: -68 | O40: -77
C41: Cash Equivalents | D41: 2689 | E41: 3009 | F41: 1828 | G41: 3485 | H41: 3757 | I41: 5113 | J41: 4471 | K41: 3846 | L41: 4678 | M41: 7559 | N41: 7554 | O41: 3248
C42: Loans n Advances | D42: 0 | E42: 0 | F42: 71 | G42: 40 | H42: 26 | I42: 19 | J42: 78 | K42: 170 | L42: 188 | M42: 172 | N42: 619 | O42: 1024
C43: Other asset items | D43: 1519 | E43: 1536 | F43: 1739 | G43: 2652 | H43: 2619 | I43: 3774 | J43: 3957 | K43: 3851 | L43: 4189 | M43: 4345 | N43: 4302 | O43: 4631
C44: Total Assets | D44: 14430 | E44: 14793 | F44: 15706 | G44: 17862 | H44: 18629 | I44: 20153 | J44: 68740 | K44: 70506 | L44: 73077 | M44: 78489 | N44: 79863 | O44: 79738
C48: Cash from Operating Activity - | D48: 3292 | E48: 4171 | F48: 5185 | G48: 6059 | H48: 5800 | I48: 7623 | J48: 9163 | K48: 9048 | L48: 9991 | M48: 15469 | N48: 11886 | O48: 10999
C49: Profit from operations | D49: 5510 | E49: 6025 | F49: 6512 | G49: 7485 | H49: 8909 | I49: 9723 | J49: 11672 | K49: 12829 | L49: 14089 | M49: 14537 | N49: 14942 | O49: 15153
C50: Receivables | D50: 3 | E50: -257 | F50: 173 | G50: 0 | H50: 0 | I50: 0 | J50: 0 | K50: 0 | L50: 0 | M50: 0 | N50: 0 | O50: 0
... C83: CFO/OP | D83: 0.95 | E83: 1 | F83: 1.11 | G83: 1.11 | H83: 0.96 | I83: 1.03 | J83: 1 | K83: 0.92 | L83: 0.93 | M83: 1.08 | N83: 0.96 | O83: 1.05
